Workbook

Sheet AOP Summary
C2: Zone | D2: ZH | F2: AOP 2026-27 OVERALL STATUS | K2: APR 25 | O2: OCT 25 | V2: NOV 25 | AD2: DEC 25 | AM2: JAN 26 | AU2: FEB 26 | BD2: MAR 26 | BJ2: APRIL 26 | BP2: MAY 26 | BV2: JUNE 26 | CB2: JULY 26 | CH2: AUGUST 26
F4: Planned | G4: Actual | H4: WIP | I4: YTS | K4: March 25 Carry Forward | L4: APR 25 Planned | M4: APR 25 Actual | O4: AUG 25 Carry Forward | P4: SEP 25 Carry Forward | Q4: Oct 25 Planned | R4: Oct 25 Actual | S4: TOTAL Oct 25 Actual | T4: WIP | V4: AUG 25 Carry Forward | W4: SEP 25 Carry Forward | X4: OCT 25 Carry Forward | Y4: NOV 25 Planned | Z4: NOV 25 Actual | AA4: TOTAL NOV 25 Actual | AB4: WIP | AD4: AUG 25 Carry Forward | AE4: SEP 25 Carry Forward | AF4: OCT 25 Carry Forward | AG4: NOV 25 Carry Forward | AH4: DEC 25 Planned | AI4: DEC 25 Actual | AJ4: TOTAL DEC 25 Actual | AK4: WIP | AM4: OCT 25 Carry Forward | AN4: NOV 25 Carry Forward | AO4: DEC 25 Carry Forward | AP4: JAN 26 Planned | AQ4: JAN 26 Actual | AR4: TOTAL JAN 26 Actual | AS4: WIP | AU4: NOV 25 Carry Forward | AV4: DEC 25 Carry Forward | AW4: JAN 26 Carry Forward | AX4: FEB 26 Planned | AY4: FEB 26 Actual | AZ4: TOTAL FEB 26 Actual | BA4: WIP | BD4: MAR 26 Planned | BE4: TOTAL MAR 26 Actual | BF4: WIP | BG4: YTS | BH4: TOTAL MAR 26 Actual | BJ4: APRIL 26 Planned | BK4: APR 26 Actual | BL4: WIP | BM4: YTS | BN4: TOTAL APR 26 Actual | BP4: MAY 26 Planned | BQ4: MAY 26 Actual | BR4: WIP | BS4: YTS | BT4: TOTAL MAY 26 Actual | BV4: JUNE 26 Planned | BW4: JUNE 26 Actual | BX4: WIP | BY4: YTS | BZ4: TOTAL JUNE 26 Actual | CB4: JULY 26 Planned | CC4: JULY 26 Actual | CD4: WIP | CE4: YTS | CF4: TOTAL JULY 26 Actual | CH4: AUGUST 26 Planned | CI4: AUGUST 26 Actual | CJ4: WIP | CK4: YTS | CL4: TOTAL JULY 26 Actual
K5: Actual | O5: Actual | P5: Actual | V5: Actual | W5: Actual | X5: Actual | AD5: Actual | AE5: Actual | AF5: Actual | AG5: Actual | AM5: Actual | AN5: Actual | AO5: Actual | AU5: Actual | AV5: Actual | AW5: Actual
C6: NORTH WEST | D6: RT | F6: =SUM(L6,Q6,Y6,AH6,AP6,AX6,BD6,BJ6,BP6) -> 77 | G6: =SUM(S6,AA6,AJ6,AR6,AZ6,BH6,BN6,BT6,BZ6) -> 70 | H6: =SUM(T6,AB6,AK6,AS6,BA6,BF6,BL6,BR6,BX6,CD6,CJ6) -> 30 | I6: =SUM(BG6,BM6,BS6,BY6,CE6,CK6) -> 0 | K6: =COUNTIFS(MASTER[ZH],$D6,MASTER[Planned (Month) Bucket],"March 25 PLANNED",MASTER[Actual (Month) Bucket],"April 25") -> 0 | L6: =COUNTIFS(MASTER[ZH],$D6,MASTER[Planned (Month) Bucket],"April 25 PLANNED") -> 0 | M6: =COUNTIFS(MASTER[ZH],$D6,MASTER[Planned (Month) Bucket],"April 25 PLANNED",MASTER[Actual (Month) Bucket],"April 25") -> 0 | O6: =COUNTIFS(MASTER[ZH],$D6,MASTER[Planned (Month) Bucket],"AUGUST 25 PLANNED",MASTER[Actual (Month) Bucket],"OCTOBER 25") -> 0 | P6: =COUNTIFS(MASTER[ZH],$D6,MASTER[Planned (Month) Bucket],"SEPTEMBER 25 PLANNED",MASTER[Actual (Month) Bucket],"OCTOBER 25") -> 0 | Q6: =COUNTIFS(MASTER[ZH],$D6,MASTER[Planned (Month) Bucket],"OCTOBER 25 PLANNED") -> 0 | R6: =COUNTIFS(MASTER[ZH],$D6,MASTER[Planned (Month) Bucket],"OCTOBER 25 PLANNED",MASTER[Actual (Month) Bucket],"OCTOBER 25") -> 0 | S6: =O6+P6+R6 -> 0 | T6: =COUNTIFS(MASTER[EPC Status (Current Week)],T$4,MASTER[ZH],$D6,MASTER[Planned (Month) Bucket],"OCTOBER 25 PLANNED") -> 0 | V6: =COUNTIFS(MASTER[ZH],$D6,MASTER[Planned (Month) Bucket],"AUGUST 25 PLANNED",MASTER[Actual (Month) Bucket],"NOVEMBER 25") -> 0 | W6: =COUNTIFS(MASTER[ZH],$D6,MASTER[Planned (Month) Bucket],"SEPTEMBER 25 PLANNED",MASTER[Actual (Month) Bucket],"NOVEMBER 25") -> 0 | X6: =COUNTIFS(MASTER[ZH],$D6,MASTER[Planned (Month) Bucket],"OCTOBER 25 PLANNED",MASTER[Actual (Month) Bucket],"NOVEMBER 25") -> 0 | Y6: =COUNTIFS(MASTER[ZH],$D6,MASTER[Planned (Month) Bucket],"NOVEMBER 25 PLANNED") -> 0 | Z6: =COUNTIFS(MASTER[ZH],$D6,MASTER[Planned (Month) Bucket],"NOVEMBER 25 PLANNED",MASTER[Actual (Month) Bucket],"NOVEMBER 25") -> 0 | AA6: =V6+W6+X6+Z6 -> 0 | AB6: =COUNTIFS(MASTER[EPC Status (Current Week)],AB$4,MASTER[ZH],$D6,MASTER[Planned (Month) Bucket],"NOVEMBER 25 PLANNED") -> 0 | AD6: =COUNTIFS(MASTER[ZH],$D6,MASTER[Planned (Month) Bucket],"AUGUST 25 PLANNED",MASTER[Actual (Month) Bucket],"DECEMBER 25") -> 0 | AE6: =COUNTIFS(MASTER[ZH],$D6,MASTER[Planned (Month) Bucket],"SEPTEMBER 25 PLANNED",MASTER[Actual (Month) Bucket],"DECEMBER 25") -> 0 | AF6: =COUNTIFS(MASTER[ZH],$D6,MASTER[Planned (Month) Bucket],"OCTOBER 25 PLANNED",MASTER[Actual (Month) Bucket],"DECEMBER 25") -> 0 | AG6: =COUNTIFS(MASTER[ZH],$D6,MASTER[Planned (Month) Bucket],"NOVEMBER 25 PLANNED",MASTER[Actual (Month) Bucket],"DECEMBER 25") -> 0 | AH6: =COUNTIFS(MASTER[ZH],$D6,MASTER[Planned (Month) Bucket],"DECEMBER 25 PLANNED") -> 0 | AI6: =COUNTIFS(MASTER[ZH],$D6,MASTER[Planned (Month) Bucket],"DECEMBER 25 PLANNED",MASTER[Actual (Month) Bucket],"DECEMBER 25") -> 0 | AJ6: =SUM(AD6,AE6,AF6,AG6,AI6) -> 0 | AK6: =COUNTIFS(MASTER[EPC Status (Current Week)],AK$4,MASTER[ZH],$D6,MASTER[Planned (Month) Bucket],"DECEMBER 25 PLANNED") -> 0 | AM6: =COUNTIFS(MASTER[ZH],$D6,MASTER[Planned (Month) Bucket],"OCTOBER 25 PLANNED",MASTER[Actual (Month) Bucket],"JANUARY 26") -> 0 | AN6: =COUNTIFS(MASTER[ZH],$D6,MASTER[Planned (Month) Bucket],"NOVEMBER 25 PLANNED",MASTER[Actual (Month) Bucket],"JANUARY 26") -> 0 | AO6: =COUNTIFS(MASTER[ZH],$D6,MASTER[Planned (Month) Bucket],"DECEMBER 25 PLANNED",MASTER[Actual (Month) Bucket],"JANUARY 26") -> 0 | AP6: =COUNTIFS(MASTER[ZH],$D6,MASTER[Planned (Month) Bucket],"JANUARY 26 PLANNED") -> 1 | AQ6: =COUNTIFS(MASTER[ZH],$D6,MASTER[Planned (Month) Bucket],"JANUARY 26 PLANNED",MASTER[Actual (Month) Bucket],"JANUARY 26") -> 0 | AR6: =SUM(AM6,AN6,AO6,AQ6) -> 0 | AS6: =COUNTIFS(MASTER[EPC Status (Current Week)],AS$4,MASTER[ZH],$D6,MASTER[Planned (Month) Bucket],"JANUARY 26 PLANNED") -> 0 | AU6: =COUNTIFS(MASTER[ZH],$D6,MASTER[Planned (Month) Bucket],"NOVEMBER 25 PLANNED",MASTER[Actual (Month) Bucket],"FEBRUARY 26") -> 0 | AV6: =COUNTIFS(MASTER[ZH],$D6,MASTER[Planned (Month) Bucket],"DECEMBER 25 PLANNED",MASTER[Actual (Month) Bucket],"FEBRUARY 26") -> 0 | AW6: =COUNTIFS(MASTER[ZH],$D6,MASTER[Planned (Month) Bucket],"JANUARY 26 PLANNED",MASTER[Actual (Month) Bucket],"FEBRUARY 26") -> 0 | AX6: =COUNTIFS(MASTER[ZH],$D6,MASTER[Planned (Month) Bucket],"FEBRUARY 26 PLANNED") -> 1 | AY6: =COUNTIFS(MASTER[ZH],$D6,MASTER[Planned (Month) Bucket],"FEBRUARY 26 PLANNED",MASTER[Actual (Month) Bucket],"FEBRUARY 26") -> 0 | AZ6: =SUM(AU6,AV6,AW6,AY6) -> 0 | BA6: =COUNTIFS(MASTER[EPC Status (Current Week)],BA$4,MASTER[ZH],$D6,MASTER[Planned (Month) Bucket],"FEBRUARY 26 PLANNED") -> 0 | BD6: =COUNTIFS(MASTER[ZH],$D6,MASTER[Planned (Month) Bucket],"MARCH 26 PLANNED") -> 33 | BE6: =COUNTIFS(MASTER[ZH],$D6,MASTER[Planned (Month) Bucket],"MARCH 26 PLANNED",MASTER[Actual (Month) Bucket],"MARCH 26")+COUNTIFS(MASTER[ZH],$D6,MASTER[Planned (Month) Bucket],"FEBRUARY 26 PLANNED",MASTER[Actual (Month) Bucket],"MARCH 26")+COUNTIFS(MASTER[ZH],$D6,MASTER[Planned (Month) Bucket],"DECEMBER 25 PLANNED",MASTER[Actual (Month) Bucket],"MARCH 26") -> 0 | BF6: =COUNTIFS(MASTER[EPC Status (Current Week)],BF$4,MASTER[ZH],$D6,MASTER[Planned (Month) Bucket],"MARCH 26 PLANNED") -> 1 | BG6: =COUNTIFS(MASTER[EPC Status (Current Week)],BG$4,MASTER[ZH],$D6,MASTER[Planned (Month) Bucket],"MARCH 26 PLANNED") -> 0 | BH6: =BE6 -> 0 | BJ6: =COUNTIFS(MASTER[ZH],$D6,MASTER[Planned (Month) Bucket],"APRIL 26 PLANNED") -> 8 | BK6: =COUNTIFS(MASTER[ZH],$D6,MASTER[Planned (Month) Bucket],"APRIL 26 PLANNED",MASTER[Actual (Month) Bucket],"APRIL 26")+COUNTIFS(MASTER[ZH],$D6,MASTER[Planned (Month) Bucket],"MARCH 26 PLANNED",MASTER[Actual (Month) Bucket],"APRIL 26")+COUNTIFS(MASTER[ZH],$D6,MASTER[Planned (Month) Bucket],"FEBRUARY 26 PLANNED",MASTER[Actual (Month) Bucket],"APRIL 26")+COUNTIFS(MASTER[ZH],$D6,MASTER[Planned (Month) Bucket],"JANUARY 26 PLANNED",MASTER[Actual (Month) Bucket],"APRIL 26")+COUNTIFS(MASTER[ZH],$D6,MASTER[Planned (Month) Bucket],"MAY 26 PLANNED",MASTER[Actual (Month) Bucket],"APRIL 26") -> 33 | BL6: =COUNTIFS(MASTER[EPC Status (Current Week)],BL$4,MASTER[ZH],$D6,MASTER[Planned (Month) Bucket],"APRIL 26 PLANNED") -> 2 | BM6: =COUNTIFS(MASTER[EPC Status (Current Week)],BM$4,MASTER[ZH],$D6,MASTER[Planned (Month) Bucket],"APRIL 26 PLANNED") -> 0 | BN6: =BK6 -> 33 | BP6: =COUNTIFS(MASTER[ZH],$D6,MASTER[Planned (Month) Bucket],"MAY 26 PLANNED") -> 34 | BQ6: =COUNTIFS(MASTER[ZH],$D6,MASTER[Planned (Month) Bucket],"NOVEMBER 25 PLANNED",MASTER[Actual (Month) Bucket],"MAY 26")+COUNTIFS(MASTER[ZH],$D6,MASTER[Planned (Month) Bucket],"DECEMBER 25 PLANNED",MASTER[Actual (Month) Bucket],"MAY 26")+COUNTIFS(MASTER[ZH],$D6,MASTER[Planned (Month) Bucket],"FEBRUARY 26 PLANNED",MASTER[Actual (Month) Bucket],"MAY 26")+COUNTIFS(MASTER[ZH],$D6,MASTER[Planned (Month) Bucket],"MARCH 26 PLANNED",MASTER[Actual (Month) Bucket],"MAY 26")+COUNTIFS(MASTER[ZH],$D6,MASTER[Planned (Month) Bucket],"APRIL 26 PLANNED",MASTER[Actual (Month) Bucket],"MAY 26")+COUNTIFS(MASTER[ZH],$D6,MASTER[Planned (Month) Bucket],"MAY 26 PLANNED",MASTER[Actual (Month) Bucket],"MAY 26") -> 35 | BR6: =COUNTIFS(MASTER[EPC Status (Current Week)],BR$4,MASTER[ZH],$D6,MASTER[Planned (Month) Bucket],"MAY 26 PLANNED") -> 4 | BS6: =COUNTIFS(MASTER[EPC Status (Current Week)],BS$4,MASTER[ZH],$D6,MASTER[Planned (Month) Bucket],"MAY 26 PLANNED") -> 0 | BT6: =BQ6 -> 35 | BV6: =COUNTIFS(MASTER[ZH],$D6,MASTER[Planned (Month) Bucket],"JUNE 26 PLANNED") -> 19 | BW6: =COUNTIFS(MASTER[ZH],$D6,MASTER[Planned (Month) Bucket],"JUNE 26 PLANNED",MASTER[Actual (Month) Bucket],"JUNE 26")+COUNTIFS(MASTER[ZH],$D6,MASTER[Planned (Month) Bucket],"MAY 26 PLANNED",MASTER[Actual (Month) Bucket],"JUNE 26")+COUNTIFS(MASTER[ZH],$D6,MASTER[Planned (Month) Bucket],"APRIL 26 PLANNED",MASTER[Actual (Month) Bucket],"JUNE 26")+COUNTIFS(MASTER[ZH],$D6,MASTER[Planned (Month) Bucket],"MARCH 26 PLANNED",MASTER[Actual (Month) Bucket],"JUNE 26")+COUNTIFS(MASTER[ZH],$D6,MASTER[Planned (Month) Bucket],"FEBRUARY 26 PLANNED",MASTER[Actual (Month) Bucket],"JUNE 26") -> 2 | BX6: =COUNTIFS(MASTER[EPC Status (Current Week)],BX$4,MASTER[ZH],$D6,MASTER[Planned (Month) Bucket],"JUNE 26 PLANNED") -> 19 | BY6: =COUNTIFS(MASTER[EPC Status (Current Week)],BY$4,MASTER[ZH],$D6,MASTER[Planned (Month) Bucket],"JUNE 26 PLANNED") -> 0 | BZ6: =BW6 -> 2 | CB6: =COUNTIFS(MASTER[ZH],$D6,MASTER[Planned (Month) Bucket],"JULY 26 PLANNED") -> 4 | CC6: =COUNTIFS(MASTER[ZH],$D6,MASTER[Planned (Month) Bucket],"JULY 26 PLANNED",MASTER[Actual (Month) Bucket],"JULY 26") -> 0 | CD6: =COUNTIFS(MASTER[EPC Status (Current Week)],CD$4,MASTER[ZH],$D6,MASTER[Planned (Month) Bucket],"JULY 26 PLANNED") -> 4 | CE6: =COUNTIFS(MASTER[EPC Status (Current Week)],CE$4,MASTER[ZH],$D6,MASTER[Planned (Month) Bucket],"JULY 26 PLANNED") -> 0 | CF6: =CC6 -> 0 | CH6: =COUNTIFS(MASTER[ZH],$D6,MASTER[Planned (Month) Bucket],"AUGUST 26 PLANNED") -> 0 | CI6: =COUNTIFS(MASTER[ZH],$D6,MASTER[Planned (Month) Bucket],"AUGUST 26 PLANNED",MASTER[Actual (Month) Bucket],"AUG 26") -> 0 | CJ6: =COUNTIFS(MASTER[EPC Status (Current Week)],CJ$4,MASTER[ZH],$D6,MASTER[Planned (Month) Bucket],"AUGUST 26 PLANNED") -> 0 | CK6: =COUNTIFS(MASTER[EPC Status (Current Week)],CK$4,MASTER[ZH],$D6,MASTER[Planned (Month) Bucket],"AUGUST 26 PLANNED") -> 0 | CL6: =CI6 -> 0
D7: BK | F7: =SUM(L7,Q7,Y7,AH7,AP7,AX7,BD7,BJ7,BP7) -> 48 | G7: =SUM(S7,AA7,AJ7,AR7,AZ7,BH7,BN7,BT7,BZ7) -> 37 | H7: =SUM(T7,AB7,AK7,AS7,BA7,BF7,BL7,BR7,BX7,CD7,CJ7) -> 27 | I7: =SUM(BG7,BM7,BS7,BY7,CE7,CK7) -> 0 | K7: =COUNTIFS(MASTER[ZH],$D7,MASTER[Planned (Month) Bucket],"March 25 PLANNED",MASTER[Actual (Month) Bucket],"April 25") -> 0 | L7: =COUNTIFS(MASTER[ZH],$D7,MASTER[Planned (Month) Bucket],"April 25 PLANNED") -> 0 | M7: =COUNTIFS(MASTER[ZH],$D7,MASTER[Planned (Month) Bucket],"April 25 PLANNED",MASTER[Actual (Month) Bucket],"April 25") -> 0 | O7: =COUNTIFS(MASTER[ZH],$D7,MASTER[Planned (Month) Bucket],"AUGUST 25 PLANNED",MASTER[Actual (Month) Bucket],"OCTOBER 25") -> 0 | P7: =COUNTIFS(MASTER[ZH],$D7,MASTER[Planned (Month) Bucket],"SEPTEMBER 25 PLANNED",MASTER[Actual (Month) Bucket],"OCTOBER 25") -> 0 | Q7: =COUNTIFS(MASTER[ZH],$D7,MASTER[Planned (Month) Bucket],"OCTOBER 25 PLANNED") -> 0 | R7: =COUNTIFS(MASTER[ZH],$D7,MASTER[Planned (Month) Bucket],"OCTOBER 25 PLANNED",MASTER[Actual (Month) Bucket],"OCTOBER 25") -> 0 | S7: =O7+P7+R7 -> 0 | T7: =COUNTIFS(MASTER[EPC Status (Current Week)],T$4,MASTER[ZH],$D7,MASTER[Planned (Month) Bucket],"OCTOBER 25 PLANNED") -> 0 | V7: =COUNTIFS(MASTER[ZH],$D7,MASTER[Planned (Month) Bucket],"AUGUST 25 PLANNED",MASTER[Actual (Month) Bucket],"NOVEMBER 25") -> 0 | W7: =COUNTIFS(MASTER[ZH],$D7,MASTER[Planned (Month) Bucket],"SEPTEMBER 25 PLANNED",MASTER[Actual (Month) Bucket],"NOVEMBER 25") -> 0 | X7: =COUNTIFS(MASTER[ZH],$D7,MASTER[Planned (Month) Bucket],"OCTOBER 25 PLANNED",MASTER[Actual (Month) Bucket],"NOVEMBER 25") -> 0 | Y7: =COUNTIFS(MASTER[ZH],$D7,MASTER[Planned (Month) Bucket],"NOVEMBER 25 PLANNED") -> 0 | Z7: =COUNTIFS(MASTER[ZH],$D7,MASTER[Planned (Month) Bucket],"NOVEMBER 25 PLANNED",MASTER[Actual (Month) Bucket],"NOVEMBER 25") -> 0 | AA7: =V7+W7+X7+Z7 -> 0 | AB7: =COUNTIFS(MASTER[EPC Status (Current Week)],AB$4,MASTER[ZH],$D7,MASTER[Planned (Month) Bucket],"NOVEMBER 25 PLANNED") -> 0 | AD7: =COUNTIFS(MASTER[ZH],$D7,MASTER[Planned (Month) Bucket],"AUGUST 25 PLANNED",MASTER[Actual (Month) Bucket],"DECEMBER 25") -> 0 | AE7: =COUNTIFS(MASTER[ZH],$D7,MASTER[Planned (Month) Bucket],"SEPTEMBER 25 PLANNED",MASTER[Actual (Month) Bucket],"DECEMBER 25") -> 0 | AF7: =COUNTIFS(MASTER[ZH],$D7,MASTER[Planned (Month) Bucket],"OCTOBER 25 PLANNED",MASTER[Actual (Month) Bucket],"DECEMBER 25") -> 0 | AG7: =COUNTIFS(MASTER[ZH],$D7,MASTER[Planned (Month) Bucket],"NOVEMBER 25 PLANNED",MASTER[Actual (Month) Bucket],"DECEMBER 25") -> 0 | AH7: =COUNTIFS(MASTER[ZH],$D7,MASTER[Planned (Month) Bucket],"DECEMBER 25 PLANNED") -> 0 | AI7: =COUNTIFS(MASTER[ZH],$D7,MASTER[Planned (Month) Bucket],"DECEMBER 25 PLANNED",MASTER[Actual (Month) Bucket],"DECEMBER 25") -> 0 | AJ7: =SUM(AD7,AE7,AF7,AG7,AI7) -> 0 | AK7: =COUNTIFS(MASTER[EPC Status (Current Week)],AK$4,MASTER[ZH],$D7,MASTER[Planned (Month) Bucket],"DECEMBER 25 PLANNED") -> 0 | AM7: =COUNTIFS(MASTER[ZH],$D7,MASTER[Planned (Month) Bucket],"OCTOBER 25 PLANNED",MASTER[Actual (Month) Bucket],"JANUARY 26") -> 0 | AN7: =COUNTIFS(MASTER[ZH],$D7,MASTER[Planned (Month) Bucket],"NOVEMBER 25 PLANNED",MASTER[Actual (Month) Bucket],"JANUARY 26") -> 0 | AO7: =COUNTIFS(MASTER[ZH],$D7,MASTER[Planned (Month) Bucket],"DECEMBER 25 PLANNED",MASTER[Actual (Month) Bucket],"JANUARY 26") -> 0 | AP7: =COUNTIFS(MASTER[ZH],$D7,MASTER[Planned (Month) Bucket],"JANUARY 26 PLANNED") -> 0 | AQ7: =COUNTIFS(MASTER[ZH],$D7,MASTER[Planned (Month) Bucket],"JANUARY 26 PLANNED",MASTER[Actual (Month) Bucket],"JANUARY 26") -> 0 | AR7: =SUM(AM7,AN7,AO7,AQ7) -> 0 | AS7: =COUNTIFS(MASTER[EPC Status (Current Week)],AS$4,MASTER[ZH],$D7,MASTER[Planned (Month) Bucket],"JANUARY 26 PLANNED") -> 0 | AU7: =COUNTIFS(MASTER[ZH],$D7,MASTER[Planned (Month) Bucket],"NOVEMBER 25 PLANNED",MASTER[Actual (Month) Bucket],"FEBRUARY 26") -> 0 | AV7: =COUNTIFS(MASTER[ZH],$D7,MASTER[Planned (Month) Bucket],"DECEMBER 25 PLANNED",MASTER[Actual (Month) Bucket],"FEBRUARY 26") -> 0 | AW7: =COUNTIFS(MASTER[ZH],$D7,MASTER[Planned (Month) Bucket],"JANUARY 26 PLANNED",MASTER[Actual (Month) Bucket],"FEBRUARY 26") -> 0 | AX7: =COUNTIFS(MASTER[ZH],$D7,MASTER[Planned (Month) Bucket],"FEBRUARY 26 PLANNED") -> 0 | AY7: =COUNTIFS(MASTER[ZH],$D7,MASTER[Planned (Month) Bucket],"FEBRUARY 26 PLANNED",MASTER[Actual (Month) Bucket],"FEBRUARY 26") -> 0 | AZ7: =SUM(AU7,AV7,AW7,AY7) -> 0 | BA7: =COUNTIFS(MASTER[EPC Status (Current Week)],BA$4,MASTER[ZH],$D7,MASTER[Planned (Month) Bucket],"FEBRUARY 26 PLANNED") -> 0 | BD7: =COUNTIFS(MASTER[ZH],$D7,MASTER[Planned (Month) Bucket],"MARCH 26 PLANNED") -> 12 | BE7: =COUNTIFS(MASTER[ZH],$D7,MASTER[Planned (Month) Bucket],"MARCH 26 PLANNED",MASTER[Actual (Month) Bucket],"MARCH 26")+COUNTIFS(MASTER[ZH],$D7,MASTER[Planned (Month) Bucket],"FEBRUARY 26 PLANNED",MASTER[Actual (Month) Bucket],"MARCH 26")+COUNTIFS(MASTER[ZH],$D7,MASTER[Planned (Month) Bucket],"JANUARY 26 PLANNED",MASTER[Actual (Month) Bucket],"MARCH 26") -> 0 | BF7: =COUNTIFS(MASTER[EPC Status (Current Week)],BF$4,MASTER[ZH],$D7,MASTER[Planned (Month) Bucket],"MARCH 26 PLANNED") -> 0 | BG7: =COUNTIFS(MASTER[EPC Status (Current Week)],BG$4,MASTER[ZH],$D7,MASTER[Planned (Month) Bucket],"MARCH 26 PLANNED") -> 0 | BH7: =BE7 -> 0 | BJ7: =COUNTIFS(MASTER[ZH],$D7,MASTER[Planned (Month) Bucket],"APRIL 26 PLANNED") -> 12 | BK7: =COUNTIFS(MASTER[ZH],$D7,MASTER[Planned (Month) Bucket],"APRIL 26 PLANNED",MASTER[Actual (Month) Bucket],"APRIL 26")+COUNTIFS(MASTER[ZH],$D7,MASTER[Planned (Month) Bucket],"MARCH 26 PLANNED",MASTER[Actual (Month) Bucket],"APRIL 26")+COUNTIFS(MASTER[ZH],$D7,MASTER[Planned (Month) Bucket],"FEBRUARY 26 PLANNED",MASTER[Actual (Month) Bucket],"APRIL 26")+COUNTIFS(MASTER[ZH],$D7,MASTER[Planned (Month) Bucket],"JANUARY 26 PLANNED",MASTER[Actual (Month) Bucket],"APRIL 26")+COUNTIFS(MASTER[ZH],$D7,MASTER[Planned (Month) Bucket],"MAY 26 PLANNED",MASTER[Actual (Month) Bucket],"APRIL 26") -> 16 | BL7: =COUNTIFS(MASTER[EPC Status (Current Week)],BL$4,MASTER[ZH],$D7,MASTER[Planned (Month) Bucket],"APRIL 26 PLANNED") -> 1 | BM7: =COUNTIFS(MASTER[EPC Status (Current Week)],BM$4,MASTER[ZH],$D7,MASTER[Planned (Month) Bucket],"APRIL 26 PLANNED") -> 0 | BN7: =BK7 -> 16 | BP7: =COUNTIFS(MASTER[ZH],$D7,MASTER[Planned (Month) Bucket],"MAY 26 PLANNED") -> 24 | BQ7: =COUNTIFS(MASTER[ZH],$D7,MASTER[Planned (Month) Bucket],"NOVEMBER 25 PLANNED",MASTER[Actual (Month) Bucket],"MAY 26")+COUNTIFS(MASTER[ZH],$D7,MASTER[Planned (Month) Bucket],"DECEMBER 25 PLANNED",MASTER[Actual (Month) Bucket],"MAY 26")+COUNTIFS(MASTER[ZH],$D7,MASTER[Planned (Month) Bucket],"FEBRUARY 26 PLANNED",MASTER[Actual (Month) Bucket],"MAY 26")+COUNTIFS(MASTER[ZH],$D7,MASTER[Planned (Month) Bucket],"MARCH 26 PLANNED",MASTER[Actual (Month) Bucket],"MAY 26")+COUNTIFS(MASTER[ZH],$D7,MASTER[Planned (Month) Bucket],"APRIL 26 PLANNED",MASTER[Actual (Month) Bucket],"MAY 26")+COUNTIFS(MASTER[ZH],$D7,MASTER[Planned (Month) Bucket],"MAY 26 PLANNED",MASTER[Actual (Month) Bucket],"MAY 26") -> 20 | BR7: =COUNTIFS(MASTER[EPC Status (Current Week)],BR$4,MASTER[ZH],$D7,MASTER[Planned (Month) Bucket],"MAY 26 PLANNED") -> 10 | BS7: =COUNTIFS(MASTER[EPC Status (Current Week)],BS$4,MASTER[ZH],$D7,MASTER[Planned (Month) Bucket],"MAY 26 PLANNED") -> 0 | BT7: =BQ7 -> 20 | BV7: =COUNTIFS(MASTER[ZH],$D7,MASTER[Planned (Month) Bucket],"JUNE 26 PLANNED") -> 13 | BW7: =COUNTIFS(MASTER[ZH],$D7,MASTER[Planned (Month) Bucket],"JUNE 26 PLANNED",MASTER[Actual (Month) Bucket],"JUNE 26")+COUNTIFS(MASTER[ZH],$D7,MASTER[Planned (Month) Bucket],"MAY 26 PLANNED",MASTER[Actual (Month) Bucket],"JUNE 26")+COUNTIFS(MASTER[ZH],$D7,MASTER[Planned (Month) Bucket],"APRIL 26 PLANNED",MASTER[Actual (Month) Bucket],"JUNE 26")+COUNTIFS(MASTER[ZH],$D7,MASTER[Planned (Month) Bucket],"MARCH 26 PLANNED",MASTER[Actual (Month) Bucket],"JUNE 26")+COUNTIFS(MASTER[ZH],$D7,MASTER[Planned (Month) Bucket],"FEBRUARY 26 PLANNED",MASTER[Actual (Month) Bucket],"JUNE 26") -> 1 | BX7: =COUNTIFS(MASTER[EPC Status (Current Week)],BX$4,MASTER[ZH],$D7,MASTER[Planned (Month) Bucket],"JUNE 26 PLANNED") -> 13 | BY7: =COUNTIFS(MASTER[EPC Status (Current Week)],BY$4,MASTER[ZH],$D7,MASTER[Planned (Month) Bucket],"JUNE 26 PLANNED") -> 0 | BZ7: =BW7 -> 1 | CB7: =COUNTIFS(MASTER[ZH],$D7,MASTER[Planned (Month) Bucket],"JULY 26 PLANNED") -> 3 | CC7: =COUNTIFS(MASTER[ZH],$D7,MASTER[Planned (Month) Bucket],"JULY 26 PLANNED",MASTER[Actual (Month) Bucket],"JULY 26") -> 0 | CD7: =COUNTIFS(MASTER[EPC Status (Current Week)],CD$4,MASTER[ZH],$D7,MASTER[Planned (Month) Bucket],"JULY 26 PLANNED") -> 3 | CE7: =COUNTIFS(MASTER[EPC Status (Current Week)],CE$4,MASTER[ZH],$D7,MASTER[Planned (Month) Bucket],"JULY 26 PLANNED") -> 0 | CF7: =CC7 -> 0 | CH7: =COUNTIFS(MASTER[ZH],$D7,MASTER[Planned (Month) Bucket],"AUGUST 26 PLANNED") -> 0 | CI7: =COUNTIFS(MASTER[ZH],$D7,MASTER[Planned (Month) Bucket],"AUGUST 26 PLANNED",MASTER[Actual (Month) Bucket],"AUG 26") -> 0 | CJ7: =COUNTIFS(MASTER[EPC Status (Current Week)],CJ$4,MASTER[ZH],$D7,MASTER[Planned (Month) Bucket],"AUGUST 26 PLANNED") -> 0 | CK7: =COUNTIFS(MASTER[EPC Status (Current Week)],CK$4,MASTER[ZH],$D7,MASTER[Planned (Month) Bucket],"AUGUST 26 PLANNED") -> 0 | CL7: =CI7 -> 0
D8: KC | F8: =SUM(L8,Q8,Y8,AH8,AP8,AX8,BD8,BJ8,BP8) -> 54 | G8: =SUM(S8,AA8,AJ8,AR8,AZ8,BH8,BN8,BT8,BZ8) -> 39 | H8: =SUM(T8,AB8,AK8,AS8,BA8,BF8,BL8,BR8,BX8,CD8,CJ8) -> 21 | I8: =SUM(BG8,BM8,BS8,BY8,CE8,CK8) -> 0 | K8: =COUNTIFS(MASTER[ZH],$D8,MASTER[Planned (Month) Bucket],"March 25 PLANNED",MASTER[Actual (Month) Bucket],"April 25") -> 0 | L8: =COUNTIFS(MASTER[ZH],$D8,MASTER[Planned (Month) Bucket],"April 25 PLANNED") -> 0 | M8: =COUNTIFS(MASTER[ZH],$D8,MASTER[Planned (Month) Bucket],"April 25 PLANNED",MASTER[Actual (Month) Bucket],"April 25") -> 0 | O8: =COUNTIFS(MASTER[ZH],$D8,MASTER[Planned (Month) Bucket],"AUGUST 25 PLANNED",MASTER[Actual (Month) Bucket],"OCTOBER 25") -> 0 | P8: =COUNTIFS(MASTER[ZH],$D8,MASTER[Planned (Month) Bucket],"SEPTEMBER 25 PLANNED",MASTER[Actual (Month) Bucket],"OCTOBER 25") -> 0 | Q8: =COUNTIFS(MASTER[ZH],$D8,MASTER[Planned (Month) Bucket],"OCTOBER 25 PLANNED") -> 0 | R8: =COUNTIFS(MASTER[ZH],$D8,MASTER[Planned (Month) Bucket],"OCTOBER 25 PLANNED",MASTER[Actual (Month) Bucket],"OCTOBER 25") -> 0 | S8: =O8+P8+R8 -> 0 | T8: =COUNTIFS(MASTER[EPC Status (Current Week)],T$4,MASTER[ZH],$D8,MASTER[Planned (Month) Bucket],"OCTOBER 25 PLANNED") -> 0 | V8: =COUNTIFS(MASTER[ZH],$D8,MASTER[Planned (Month) Bucket],"AUGUST 25 PLANNED",MASTER[Actual (Month) Bucket],"NOVEMBER 25") -> 0 | W8: =COUNTIFS(MASTER[ZH],$D8,MASTER[Planned (Month) Bucket],"SEPTEMBER 25 PLANNED",MASTER[Actual (Month) Bucket],"NOVEMBER 25") -> 0 | X8: =COUNTIFS(MASTER[ZH],$D8,MASTER[Planned (Month) Bucket],"OCTOBER 25 PLANNED",MASTER[Actual (Month) Bucket],"NOVEMBER 25") -> 0 | Y8: =COUNTIFS(MASTER[ZH],$D8,MASTER[Planned (Month) Bucket],"NOVEMBER 25 PLANNED") -> 0 | Z8: =COUNTIFS(MASTER[ZH],$D8,MASTER[Planned (Month) Bucket],"NOVEMBER 25 PLANNED",MASTER[Actual (Month) Bucket],"NOVEMBER 25") -> 0 | AA8: =V8+W8+X8+Z8 -> 0 | AB8: =COUNTIFS(MASTER[EPC Status (Current Week)],AB$4,MASTER[ZH],$D8,MASTER[Planned (Month) Bucket],"NOVEMBER 25 PLANNED") -> 0 | AD8: =COUNTIFS(MASTER[ZH],$D8,MASTER[Planned (Month) Bucket],"AUGUST 25 PLANNED",MASTER[Actual (Month) Bucket],"DECEMBER 25") -> 0 | AE8: =COUNTIFS(MASTER[ZH],$D8,MASTER[Planned (Month) Bucket],"SEPTEMBER 25 PLANNED",MASTER[Actual (Month) Bucket],"DECEMBER 25") -> 0 | AF8: =COUNTIFS(MASTER[ZH],$D8,MASTER[Planned (Month) Bucket],"OCTOBER 25 PLANNED",MASTER[Actual (Month) Bucket],"DECEMBER 25") -> 0 | AG8: =COUNTIFS(MASTER[ZH],$D8,MASTER[Planned (Month) Bucket],"NOVEMBER 25 PLANNED",MASTER[Actual (Month) Bucket],"DECEMBER 25") -> 0 | AH8: =COUNTIFS(MASTER[ZH],$D8,MASTER[Planned (Month) Bucket],"DECEMBER 25 PLANNED") -> 0 | AI8: =COUNTIFS(MASTER[ZH],$D8,MASTER[Planned (Month) Bucket],"DECEMBER 25 PLANNED",MASTER[Actual (Month) Bucket],"DECEMBER 25") -> 0 | AJ8: =SUM(AD8,AE8,AF8,AG8,AI8) -> 0 | AK8: =COUNTIFS(MASTER[EPC Status (Current Week)],AK$4,MASTER[ZH],$D8,MASTER[Planned (Month) Bucket],"DECEMBER 25 PLANNED") -> 0 | AM8: =COUNTIFS(MASTER[ZH],$D8,MASTER[Planned (Month) Bucket],"OCTOBER 25 PLANNED",MASTER[Actual (Month) Bucket],"JANUARY 26") -> 0 | AN8: =COUNTIFS(MASTER[ZH],$D8,MASTER[Planned (Month) Bucket],"NOVEMBER 25 PLANNED",MASTER[Actual (Month) Bucket],"JANUARY 26") -> 0 | AO8: =COUNTIFS(MASTER[ZH],$D8,MASTER[Planned (Month) Bucket],"DECEMBER 25 PLANNED",MASTER[Actual (Month) Bucket],"JANUARY 26") -> 0 | AP8: =COUNTIFS(MASTER[ZH],$D8,MASTER[Planned (Month) Bucket],"JANUARY 26 PLANNED") -> 1 | AQ8: =COUNTIFS(MASTER[ZH],$D8,MASTER[Planned (Month) Bucket],"JANUARY 26 PLANNED",MASTER[Actual (Month) Bucket],"JANUARY 26") -> 0 | AR8: =SUM(AM8,AN8,AO8,AQ8) -> 0 | AS8: =COUNTIFS(MASTER[EPC Status (Current Week)],AS$4,MASTER[ZH],$D8,MASTER[Planned (Month) Bucket],"JANUARY 26 PLANNED") -> 1 | AU8: =COUNTIFS(MASTER[ZH],$D8,MASTER[Planned (Month) Bucket],"NOVEMBER 25 PLANNED",MASTER[Actual (Month) Bucket],"FEBRUARY 26") -> 0 | AV8: =COUNTIFS(MASTER[ZH],$D8,MASTER[Planned (Month) Bucket],"DECEMBER 25 PLANNED",MASTER[Actual (Month) Bucket],"FEBRUARY 26") -> 0 | AW8: =COUNTIFS(MASTER[ZH],$D8,MASTER[Planned (Month) Bucket],"JANUARY 26 PLANNED",MASTER[Actual (Month) Bucket],"FEBRUARY 26") -> 0 | AX8: =COUNTIFS(MASTER[ZH],$D8,MASTER[Planned (Month) Bucket],"FEBRUARY 26 PLANNED") -> 2 | AY8: =COUNTIFS(MASTER[ZH],$D8,MASTER[Planned (Month) Bucket],"FEBRUARY 26 PLANNED",MASTER[Actual (Month) Bucket],"FEBRUARY 26") -> 0 | AZ8: =SUM(AU8,AV8,AW8,AY8) -> 0 | BA8: =COUNTIFS(MASTER[EPC Status (Current Week)],BA$4,MASTER[ZH],$D8,MASTER[Planned (Month) Bucket],"FEBRUARY 26 PLANNED") -> 1 | BD8: =COUNTIFS(MASTER[ZH],$D8,MASTER[Planned (Month) Bucket],"MARCH 26 PLANNED") -> 15 | BE8: =COUNTIFS(MASTER[ZH],$D8,MASTER[Planned (Month) Bucket],"MARCH 26 PLANNED",MASTER[Actual (Month) Bucket],"MARCH 26")+COUNTIFS(MASTER[ZH],$D8,MASTER[Planned (Month) Bucket],"FEBRUARY 26 PLANNED",MASTER[Actual (Month) Bucket],"MARCH 26")+COUNTIFS(MASTER[ZH],$D8,MASTER[Planned (Month) Bucket],"JANUARY 26 PLANNED",MASTER[Actual (Month) Bucket],"MARCH 26")+COUNTIFS(MASTER[ZH],$D8,MASTER[Planned (Month) Bucket],"NOVEMBER 25 PLANNED",MASTER[Actual (Month) Bucket],"MARCH 26") -> 0 | BF8: =COUNTIFS(MASTER[EPC Status (Current Week)],BF$4,MASTER[ZH],$D8,MASTER[Planned (Month) Bucket],"MARCH 26 PLANNED") -> 0 | BG8: =COUNTIFS(MASTER[EPC Status (Current Week)],BG$4,MASTER[ZH],$D8,MASTER[Planned (Month) Bucket],"MARCH 26 PLANNED") -> 0 | BH8: =BE8 -> 0 | BJ8: =COUNTIFS(MASTER[ZH],$D8,MASTER[Planned (Month) Bucket],"APRIL 26 PLANNED") -> 13 | BK8: =COUNTIFS(MASTER[ZH],$D8,MASTER[Planned (Month) Bucket],"APRIL 26 PLANNED",MASTER[Actual (Month) Bucket],"APRIL 26")+COUNTIFS(MASTER[ZH],$D8,MASTER[Planned (Month) Bucket],"MARCH 26 PLANNED",MASTER[Actual (Month) Bucket],"APRIL 26")+COUNTIFS(MASTER[ZH],$D8,MASTER[Planned (Month) Bucket],"FEBRUARY 26 PLANNED",MASTER[Actual (Month) Bucket],"APRIL 26")+COUNTIFS(MASTER[ZH],$D8,MASTER[Planned (Month) Bucket],"JANUARY 26 PLANNED",MASTER[Actual (Month) Bucket],"APRIL 26")+COUNTIFS(MASTER[ZH],$D8,MASTER[Planned (Month) Bucket],"MAY 26 PLANNED",MASTER[Actual (Month) Bucket],"APRIL 26") -> 17 | BL8: =COUNTIFS(MASTER[EPC Status (Current Week)],BL$4,MASTER[ZH],$D8,MASTER[Planned (Month) Bucket],"APRIL 26 PLANNED") -> 6 | BM8: =COUNTIFS(MASTER[EPC Status (Current Week)],BM$4,MASTER[ZH],$D8,MASTER[Planned (Month) Bucket],"APRIL 26 PLANNED") -> 0 | BN8: =BK8 -> 17 | BP8: =COUNTIFS(MASTER[ZH],$D8,MASTER[Planned (Month) Bucket],"MAY 26 PLANNED") -> 23 | BQ8: =COUNTIFS(MASTER[ZH],$D8,MASTER[Planned (Month) Bucket],"NOVEMBER 25 PLANNED",MASTER[Actual (Month) Bucket],"MAY 26")+COUNTIFS(MASTER[ZH],$D8,MASTER[Planned (Month) Bucket],"DECEMBER 25 PLANNED",MASTER[Actual (Month) Bucket],"MAY 26")+COUNTIFS(MASTER[ZH],$D8,MASTER[Planned (Month) Bucket],"FEBRUARY 26 PLANNED",MASTER[Actual (Month) Bucket],"MAY 26")+COUNTIFS(MASTER[ZH],$D8,MASTER[Planned (Month) Bucket],"MARCH 26 PLANNED",MASTER[Actual (Month) Bucket],"MAY 26")+COUNTIFS(MASTER[ZH],$D8,MASTER[Planned (Month) Bucket],"APRIL 26 PLANNED",MASTER[Actual (Month) Bucket],"MAY 26")+COUNTIFS(MASTER[ZH],$D8,MASTER[Planned (Month) Bucket],"MAY 26 PLANNED",MASTER[Actual (Month) Bucket],"MAY 26") -> 19 | BR8: =COUNTIFS(MASTER[EPC Status (Current Week)],BR$4,MASTER[ZH],$D8,MASTER[Planned (Month) Bucket],"MAY 26 PLANNED") -> 7 | BS8: =COUNTIFS(MASTER[EPC Status (Current Week)],BS$4,MASTER[ZH],$D8,MASTER[Planned (Month) Bucket],"MAY 26 PLANNED") -> 0 | BT8: =BQ8 -> 19 | BV8: =COUNTIFS(MASTER[ZH],$D8,MASTER[Planned (Month) Bucket],"JUNE 26 PLANNED") -> 6 | BW8: =COUNTIFS(MASTER[ZH],$D8,MASTER[Planned (Month) Bucket],"JUNE 26 PLANNED",MASTER[Actual (Month) Bucket],"JUNE 26")+COUNTIFS(MASTER[ZH],$D8,MASTER[Planned (Month) Bucket],"MAY 26 PLANNED",MASTER[Actual (Month) Bucket],"JUNE 26")+COUNTIFS(MASTER[ZH],$D8,MASTER[Planned (Month) Bucket],"APRIL 26 PLANNED",MASTER[Actual (Month) Bucket],"JUNE 26")+COUNTIFS(MASTER[ZH],$D8,MASTER[Planned (Month) Bucket],"MARCH 26 PLANNED",MASTER[Actual (Month) Bucket],"JUNE 26")+COUNTIFS(MASTER[ZH],$D8,MASTER[Planned (Month) Bucket],"FEBRUARY 26 PLANNED",MASTER[Actual (Month) Bucket],"JUNE 26") -> 3 | BX8: =COUNTIFS(MASTER[EPC Status (Current Week)],BX$4,MASTER[ZH],$D8,MASTER[Planned (Month) Bucket],"JUNE 26 PLANNED") -> 6 | BY8: =COUNTIFS(MASTER[EPC Status (Current Week)],BY$4,MASTER[ZH],$D8,MASTER[Planned (Month) Bucket],"JUNE 26 PLANNED") -> 0 | BZ8: =BW8 -> 3 | CB8: =COUNTIFS(MASTER[ZH],$D8,MASTER[Planned (Month) Bucket],"JULY 26 PLANNED") -> 0 | CC8: =COUNTIFS(MASTER[ZH],$D8,MASTER[Planned (Month) Bucket],"JULY 26 PLANNED",MASTER[Actual (Month) Bucket],"JULY 26") -> 0 | CD8: =COUNTIFS(MASTER[EPC Status (Current Week)],CD$4,MASTER[ZH],$D8,MASTER[Planned (Month) Bucket],"JULY 26 PLANNED") -> 0 | CE8: =COUNTIFS(MASTER[EPC Status (Current Week)],CE$4,MASTER[ZH],$D8,MASTER[Planned (Month) Bucket],"JULY 26 PLANNED") -> 0 | CF8: =CC8 -> 0 | CH8: =COUNTIFS(MASTER[ZH],$D8,MASTER[Planned (Month) Bucket],"AUGUST 26 PLANNED") -> 0 | CI8: =COUNTIFS(MASTER[ZH],$D8,MASTER[Planned (Month) Bucket],"AUGUST 26 PLANNED",MASTER[Actual (Month) Bucket],"AUG 26") -> 0 | CJ8: =COUNTIFS(MASTER[EPC Status (Current Week)],CJ$4,MASTER[ZH],$D8,MASTER[Planned (Month) Bucket],"AUGUST 26 PLANNED") -> 0 | CK8: =COUNTIFS(MASTER[EPC Status (Current Week)],CK$4,MASTER[ZH],$D8,MASTER[Planned (Month) Bucket],"AUGUST 26 PLANNED") -> 0 | CL8: =CI8 -> 0
D9: TOTAL | F9: =SUM(F6:F8) -> 179 | G9: =SUM(G6:G8) -> 146 | H9: =SUM(H6:H8) -> 78 | I9: =SUM(I6:I8) -> 0 | K9: =SUM(K6:K8) -> 0 | L9: =SUM(L6:L8) -> 0 | M9: =SUM(M6:M8) -> 0 | O9: =SUM(O6:O8) -> 0 | P9: =SUM(P6:P8) -> 0 | Q9: =SUM(Q6:Q8) -> 0 | R9: =SUM(R6:R8) -> 0 | S9: =SUM(S6:S8) -> 0 | T9: =SUM(T6:T8) -> 0 | V9: =SUM(V6:V8) -> 0 | W9: =SUM(W6:W8) -> 0 | X9: =SUM(X6:X8) -> 0 | Y9: =SUM(Y6:Y8) -> 0 | Z9: =SUM(Z6:Z8) -> 0 | AA9: =SUM(AA6:AA8) -> 0 | AB9: =SUM(AB6:AB8) -> 0 | AD9: =SUM(AD6:AD8) -> 0 | AE9: =SUM(AE6:AE8) -> 0 | AF9: =SUM(AF6:AF8) -> 0 | AG9: =SUM(AG6:AG8) -> 0 | AH9: =SUM(AH6:AH8) -> 0 | AI9: =SUM(AI6:AI8) -> 0 | AJ9: =SUM(AJ6:AJ8) -> 0 | AK9: =SUM(AK6:AK8) -> 0 | AM9: =SUM(AM6:AM8) -> 0 | AN9: =SUM(AN6:AN8) -> 0 | AO9: =SUM(AO6:AO8) -> 0 | AP9: =SUM(AP6:AP8) -> 2 | AQ9: =SUM(AQ6:AQ8) -> 0 | AR9: =SUM(AR6:AR8) -> 0 | AS9: =SUM(AS6:AS8) -> 1 | AU9: =SUM(AU6:AU8) -> 0 | AV9: =SUM(AV6:AV8) -> 0 | AW9: =SUM(AW6:AW8) -> 0 | AX9: =SUM(AX6:AX8) -> 3 | AY9: =SUM(AY6:AY8) -> 0 | AZ9: =SUM(AZ6:AZ8) -> 0 | BA9: =SUM(BA6:BA8) -> 1 | BD9: =SUM(BD6:BD8) -> 60 | BE9: =SUM(BE6:BE8) -> 0 | BF9: =SUM(BF6:BF8) -> 1 | BG9: =SUM(BG6:BG8) -> 0 | BH9: =SUM(BH6:BH8) -> 0 | BJ9: =SUM(BJ6:BJ8) -> 33 | BK9: =SUM(BK6:BK8) -> 66 | BL9: =SUM(BL6:BL8) -> 9 | BM9: =SUM(BM6:BM8) -> 0 | BN9: =SUM(BN6:BN8) -> 66 | BP9: =SUM(BP6:BP8) -> 81 | BQ9: =SUM(BQ6:BQ8) -> 74 | BR9: =SUM(BR6:BR8) -> 21 | BS9: =SUM(BS6:BS8) -> 0 | BT9: =SUM(BT6:BT8) -> 74 | BV9: =SUM(BV6:BV8) -> 38 | BW9: =SUM(BW6:BW8) -> 6 | BX9: =SUM(BX6:BX8) -> 38 | BY9: =SUM(BY6:BY8) -> 0 | BZ9: =SUM(BZ6:BZ8) -> 6 | CB9: =SUM(CB6:CB8) -> 7 | CC9: =SUM(CC6:CC8) -> 0 | CD9: =SUM(CD6:CD8) -> 7 | CE9: =SUM(CE6:CE8) -> 0 | CF9: =SUM(CF6:CF8) -> 0 | CH9: =SUM(CH6:CH8) -> 0 | CI9: =SUM(CI6:CI8) -> 0 | CJ9: =SUM(CJ6:CJ8) -> 0 | CK9: =SUM(CK6:CK8) -> 0 | CL9: =SUM(CL6:CL8) -> 0
C10: SOUTH EAST | D10: SZ FO | F10: =SUM(L10,Q10,Y10,AH10,AP10,AX10,BD10,BJ10,BP10) -> 253 | G10: =SUM(S10,AA10,AJ10,AR10,AZ10,BH10,BN10,BT10,BZ10) -> 157 | H10: =SUM(T10,AB10,AK10,AS10,BA10,BF10,BL10,BR10,BX10,CD10,CJ10) -> 147 | I10: =SUM(BG10,BM10,BS10,BY10,CE10,CK10) -> 0 | K10: =COUNTIFS(MASTER[ZH],$D10,MASTER[Planned (Month) Bucket],"March 25 PLANNED",MASTER[Actual (Month) Bucket],"April 25") -> 0 | L10: =COUNTIFS(MASTER[ZH],$D10,MASTER[Planned (Month) Bucket],"April 25 PLANNED") -> 0 | M10: =COUNTIFS(MASTER[ZH],$D10,MASTER[Planned (Month) Bucket],"April 25 PLANNED",MASTER[Actual (Month) Bucket],"April 25") -> 0 | O10: =COUNTIFS(MASTER[ZH],$D10,MASTER[Planned (Month) Bucket],"AUGUST 25 PLANNED",MASTER[Actual (Month) Bucket],"OCTOBER 25") -> 0 | P10: =COUNTIFS(MASTER[ZH],$D10,MASTER[Planned (Month) Bucket],"SEPTEMBER 25 PLANNED",MASTER[Actual (Month) Bucket],"OCTOBER 25") -> 0 | Q10: =COUNTIFS(MASTER[ZH],$D10,MASTER[Planned (Month) Bucket],"OCTOBER 25 PLANNED") -> 0 | R10: =COUNTIFS(MASTER[ZH],$D10,MASTER[Planned (Month) Bucket],"OCTOBER 25 PLANNED",MASTER[Actual (Month) Bucket],"OCTOBER 25") -> 0 | S10: =O10+P10+R10 -> 0 | T10: =COUNTIFS(MASTER[EPC Status (Current Week)],T$4,MASTER[ZH],$D10,MASTER[Planned (Month) Bucket],"OCTOBER 25 PLANNED") -> 0 | V10: =COUNTIFS(MASTER[ZH],$D10,MASTER[Planned (Month) Bucket],"AUGUST 25 PLANNED",MASTER[Actual (Month) Bucket],"NOVEMBER 25") -> 0 | W10: =COUNTIFS(MASTER[ZH],$D10,MASTER[Planned (Month) Bucket],"SEPTEMBER 25 PLANNED",MASTER[Actual (Month) Bucket],"NOVEMBER 25") -> 0 | X10: =COUNTIFS(MASTER[ZH],$D10,MASTER[Planned (Month) Bucket],"OCTOBER 25 PLANNED",MASTER[Actual (Month) Bucket],"NOVEMBER 25") -> 0 | Y10: =COUNTIFS(MASTER[ZH],$D10,MASTER[Planned (Month) Bucket],"NOVEMBER 25 PLANNED") -> 0 | Z10: =COUNTIFS(MASTER[ZH],$D10,MASTER[Planned (Month) Bucket],"NOVEMBER 25 PLANNED",MASTER[Actual (Month) Bucket],"NOVEMBER 25") -> 0 | AA10: =V10+W10+X10+Z10 -> 0 | AB10: =COUNTIFS(MASTER[EPC Status (Current Week)],AB$4,MASTER[ZH],$D10,MASTER[Planned (Month) Bucket],"NOVEMBER 25 PLANNED") -> 0 | AD10: =COUNTIFS(MASTER[ZH],$D10,MASTER[Planned (Month) Bucket],"AUGUST 25 PLANNED",MASTER[Actual (Month) Bucket],"DECEMBER 25") -> 0 | AE10: =COUNTIFS(MASTER[ZH],$D10,MASTER[Planned (Month) Bucket],"SEPTEMBER 25 PLANNED",MASTER[Actual (Month) Bucket],"DECEMBER 25") -> 0 | AF10: =COUNTIFS(MASTER[ZH],$D10,MASTER[Planned (Month) Bucket],"OCTOBER 25 PLANNED",MASTER[Actual (Month) Bucket],"DECEMBER 25") -> 0 | AG10: =COUNTIFS(MASTER[ZH],$D10,MASTER[Planned (Month) Bucket],"NOVEMBER 25 PLANNED",MASTER[Actual (Month) Bucket],"DECEMBER 25") -> 0 | AH10: =COUNTIFS(MASTER[ZH],$D10,MASTER[Planned (Month) Bucket],"DECEMBER 25 PLANNED") -> 0 | AI10: =COUNTIFS(MASTER[ZH],$D10,MASTER[Planned (Month) Bucket],"DECEMBER 25 PLANNED",MASTER[Actual (Month) Bucket],"DECEMBER 25") -> 0 | AJ10: =SUM(AD10,AE10,AF10,AG10,AI10) -> 0 | AK10: =COUNTIFS(MASTER[EPC Status (Current Week)],AK$4,MASTER[ZH],$D10,MASTER[Planned (Month) Bucket],"DECEMBER 25 PLANNED") -> 0 | AM10: =COUNTIFS(MASTER[ZH],$D10,MASTER[Planned (Month) Bucket],"OCTOBER 25 PLANNED",MASTER[Actual (Month) Bucket],"JANUARY 26") -> 0 | AN10: =COUNTIFS(MASTER[ZH],$D10,MASTER[Planned (Month) Bucket],"NOVEMBER 25 PLANNED",MASTER[Actual (Month) Bucket],"JANUARY 26") -> 0 | AO10: =COUNTIFS(MASTER[ZH],$D10,MASTER[Planned (Month) Bucket],"DECEMBER 25 PLANNED",MASTER[Actual (Month) Bucket],"JANUARY 26") -> 0 | AP10: =COUNTIFS(MASTER[ZH],$D10,MASTER[Planned (Month) Bucket],"JANUARY 26 PLANNED") -> 0 | AQ10: =COUNTIFS(MASTER[ZH],$D10,MASTER[Planned (Month) Bucket],"JANUARY 26 PLANNED",MASTER[Actual (Month) Bucket],"JANUARY 26") -> 0 | AR10: =SUM(AM10,AN10,AO10,AQ10) -> 0 | AS10: =COUNTIFS(MASTER[EPC Status (Current Week)],AS$4,MASTER[ZH],$D10,MASTER[Planned (Month) Bucket],"JANUARY 26 PLANNED") -> 0 | AU10: =COUNTIFS(MASTER[ZH],$D10,MASTER[Planned (Month) Bucket],"NOVEMBER 25 PLANNED",MASTER[Actual (Month) Bucket],"FEBRUARY 26") -> 0 | AV10: =COUNTIFS(MASTER[ZH],$D10,MASTER[Planned (Month) Bucket],"DECEMBER 25 PLANNED",MASTER[Actual (Month) Bucket],"FEBRUARY 26") -> 0 | AW10: =COUNTIFS(MASTER[ZH],$D10,MASTER[Planned (Month) Bucket],"JANUARY 26 PLANNED",MASTER[Actual (Month) Bucket],"FEBRUARY 26") -> 0 | AX10: =COUNTIFS(MASTER[ZH],$D10,MASTER[Planned (Month) Bucket],"FEBRUARY 26 PLANNED") -> 13 | AY10: =COUNTIFS(MASTER[ZH],$D10,MASTER[Planned (Month) Bucket],"FEBRUARY 26 PLANNED",MASTER[Actual (Month) Bucket],"FEBRUARY 26") -> 0 | AZ10: =SUM(AU10,AV10,AW10,AY10) -> 0 | BA10: =COUNTIFS(MASTER[EPC Status (Current Week)],BA$4,MASTER[ZH],$D10,MASTER[Planned (Month) Bucket],"FEBRUARY 26 PLANNED") -> 5 | BD10: =COUNTIFS(MASTER[ZH],$D10,MASTER[Planned (Month) Bucket],"MARCH 26 PLANNED") -> 30 | BE10: =COUNTIFS(MASTER[ZH],$D10,MASTER[Planned (Month) Bucket],"MARCH 26 PLANNED",MASTER[Actual (Month) Bucket],"MARCH 26")+COUNTIFS(MASTER[ZH],$D10,MASTER[Planned (Month) Bucket],"FEBRUARY 26 PLANNED",MASTER[Actual (Month) Bucket],"MARCH 26")+COUNTIFS(MASTER[ZH],$D10,MASTER[Planned (Month) Bucket],"JANUARY 26 PLANNED",MASTER[Actual (Month) Bucket],"MARCH 26") -> 0 | BF10: =COUNTIFS(MASTER[EPC Status (Current Week)],BF$4,MASTER[ZH],$D10,MASTER[Planned (Month) Bucket],"MARCH 26 PLANNED") -> 6 | BG10: =COUNTIFS(MASTER[EPC Status (Current Week)],BG$4,MASTER[ZH],$D10,MASTER[Planned (Month) Bucket],"MARCH 26 PLANNED") -> 0 | BH10: =BE10 -> 0 | BJ10: =COUNTIFS(MASTER[ZH],$D10,MASTER[Planned (Month) Bucket],"APRIL 26 PLANNED") -> 154 | BK10: =COUNTIFS(MASTER[ZH],$D10,MASTER[Planned (Month) Bucket],"APRIL 26 PLANNED",MASTER[Actual (Month) Bucket],"APRIL 26")+COUNTIFS(MASTER[ZH],$D10,MASTER[Planned (Month) Bucket],"MARCH 26 PLANNED",MASTER[Actual (Month) Bucket],"APRIL 26")+COUNTIFS(MASTER[ZH],$D10,MASTER[Planned (Month) Bucket],"FEBRUARY 26 PLANNED",MASTER[Actual (Month) Bucket],"APRIL 26")+COUNTIFS(MASTER[ZH],$D10,MASTER[Planned (Month) Bucket],"JANUARY 26 PLANNED",MASTER[Actual (Month) Bucket],"APRIL 26")+COUNTIFS(MASTER[ZH],$D10,MASTER[Planned (Month) Bucket],"MAY 26 PLANNED",MASTER[Actual (Month) Bucket],"APRIL 26") -> 41 | BL10: =COUNTIFS(MASTER[EPC Status (Current Week)],BL$4,MASTER[ZH],$D10,MASTER[Planned (Month) Bucket],"APRIL 26 PLANNED") -> 66 | BM10: =COUNTIFS(MASTER[EPC Status (Current Week)],BM$4,MASTER[ZH],$D10,MASTER[Planned (Month) Bucket],"APRIL 26 PLANNED") -> 0 | BN10: =BK10 -> 41 | BP10: =COUNTIFS(MASTER[ZH],$D10,MASTER[Planned (Month) Bucket],"MAY 26 PLANNED") -> 56 | BQ10: =COUNTIFS(MASTER[ZH],$D10,MASTER[Planned (Month) Bucket],"NOVEMBER 25 PLANNED",MASTER[Actual (Month) Bucket],"MAY 26")+COUNTIFS(MASTER[ZH],$D10,MASTER[Planned (Month) Bucket],"DECEMBER 25 PLANNED",MASTER[Actual (Month) Bucket],"MAY 26")+COUNTIFS(MASTER[ZH],$D10,MASTER[Planned (Month) Bucket],"FEBRUARY 26 PLANNED",MASTER[Actual (Month) Bucket],"MAY 26")+COUNTIFS(MASTER[ZH],$D10,MASTER[Planned (Month) Bucket],"MARCH 26 PLANNED",MASTER[Actual (Month) Bucket],"MAY 26")+COUNTIFS(MASTER[ZH],$D10,MASTER[Planned (Month) Bucket],"APRIL 26 PLANNED",MASTER[Actual (Month) Bucket],"MAY 26")+COUNTIFS(MASTER[ZH],$D10,MASTER[Planned (Month) Bucket],"MAY 26 PLANNED",MASTER[Actual (Month) Bucket],"MAY 26") -> 102 | BR10: =COUNTIFS(MASTER[EPC Status (Current Week)],BR$4,MASTER[ZH],$D10,MASTER[Planned (Month) Bucket],"MAY 26 PLANNED") -> 26 | BS10: =COUNTIFS(MASTER[EPC Status (Current Week)],BS$4,MASTER[ZH],$D10,MASTER[Planned (Month) Bucket],"MAY 26 PLANNED") -> 0 | BT10: =BQ10 -> 102 | BV10: =COUNTIFS(MASTER[ZH],$D10,MASTER[Planned (Month) Bucket],"JUNE 26 PLANNED") -> 49 | BW10: =COUNTIFS(MASTER[ZH],$D10,MASTER[Planned (Month) Bucket],"JUNE 26 PLANNED",MASTER[Actual (Month) Bucket],"JUNE 26")+COUNTIFS(MASTER[ZH],$D10,MASTER[Planned (Month) Bucket],"MAY 26 PLANNED",MASTER[Actual (Month) Bucket],"JUNE 26")+COUNTIFS(MASTER[ZH],$D10,MASTER[Planned (Month) Bucket],"APRIL 26 PLANNED",MASTER[Actual (Month) Bucket],"JUNE 26")+COUNTIFS(MASTER[ZH],$D10,MASTER[Planned (Month) Bucket],"MARCH 26 PLANNED",MASTER[Actual (Month) Bucket],"JUNE 26")+COUNTIFS(MASTER[ZH],$D10,MASTER[Planned (Month) Bucket],"FEBRUARY 26 PLANNED",MASTER[Actual (Month) Bucket],"JUNE 26") -> 14 | BX10: =COUNTIFS(MASTER[EPC Status (Current Week)],BX$4,MASTER[ZH],$D10,MASTER[Planned (Month) Bucket],"JUNE 26 PLANNED") -> 42 | BY10: =COUNTIFS(MASTER[EPC Status (Current Week)],BY$4,MASTER[ZH],$D10,MASTER[Planned (Month) Bucket],"JUNE 26 PLANNED") -> 0 | BZ10: =BW10 -> 14 | CB10: =COUNTIFS(MASTER[ZH],$D10,MASTER[Planned (Month) Bucket],"JULY 26 PLANNED") -> 2 | CC10: =COUNTIFS(MASTER[ZH],$D10,MASTER[Planned (Month) Bucket],"JULY 26 PLANNED",MASTER[Actual (Month) Bucket],"JULY 26") -> 0 | CD10: =COUNTIFS(MASTER[EPC Status (Current Week)],CD$4,MASTER[ZH],$D10,MASTER[Planned (Month) Bucket],"JULY 26 PLANNED") -> 2 | CE10: =COUNTIFS(MASTER[EPC Status (Current Week)],CE$4,MASTER[ZH],$D10,MASTER[Planned (Month) Bucket],"JULY 26 PLANNED") -> 0 | CF10: =CC10 -> 0 | CH10: =COUNTIFS(MASTER[ZH],$D10,MASTER[Planned (Month) Bucket],"AUGUST 26 PLANNED") -> 0 | CI10: =COUNTIFS(MASTER[ZH],$D10,MASTER[Planned (Month) Bucket],"AUGUST 26 PLANNED",MASTER[Actual (Month) Bucket],"AUG 26") -> 0 | CJ10: =COUNTIFS(MASTER[EPC Status (Current Week)],CJ$4,MASTER[ZH],$D10,MASTER[Planned (Month) Bucket],"AUGUST 26 PLANNED") -> 0 | CK10: =COUNTIFS(MASTER[EPC Status (Current Week)],CK$4,MASTER[ZH],$D10,MASTER[Planned (Month) Bucket],"AUGUST 26 PLANNED") -> 0 | CL10: =CI10 -> 0
D11: SD | F11: =SUM(L11,Q11,Y11,AH11,AP11,AX11,BD11,BJ11,BP11) -> 391 | G11: =SUM(S11,AA11,AJ11,AR11,AZ11,BH11,BN11,BT11,BZ11) -> 352 | H11: =SUM(T11,AB11,AK11,AS11,BA11,BF11,BL11,BR11,BX11,CD11,CJ11) -> 105 | I11: =SUM(BG11,BM11,BS11,BY11,CE11,CK11) -> 0 | K11: =COUNTIFS(MASTER[ZH],$D11,MASTER[Planned (Month) Bucket],"March 25 PLANNED",MASTER[Actual (Month) Bucket],"April 25") -> 0 | L11: =COUNTIFS(MASTER[ZH],$D11,MASTER[Planned (Month) Bucket],"April 25 PLANNED") -> 0 | M11: =COUNTIFS(MASTER[ZH],$D11,MASTER[Planned (Month) Bucket],"April 25 PLANNED",MASTER[Actual (Month) Bucket],"April 25") -> 0 | O11: =COUNTIFS(MASTER[ZH],$D11,MASTER[Planned (Month) Bucket],"AUGUST 25 PLANNED",MASTER[Actual (Month) Bucket],"OCTOBER 25") -> 0 | P11: =COUNTIFS(MASTER[ZH],$D11,MASTER[Planned (Month) Bucket],"SEPTEMBER 25 PLANNED",MASTER[Actual (Month) Bucket],"OCTOBER 25") -> 0 | Q11: =COUNTIFS(MASTER[ZH],$D11,MASTER[Planned (Month) Bucket],"OCTOBER 25 PLANNED") -> 0 | R11: =COUNTIFS(MASTER[ZH],$D11,MASTER[Planned (Month) Bucket],"OCTOBER 25 PLANNED",MASTER[Actual (Month) Bucket],"OCTOBER 25") -> 0 | S11: =O11+P11+R11 -> 0 | T11: =COUNTIFS(MASTER[EPC Status (Current Week)],T$4,MASTER[ZH],$D11,MASTER[Planned (Month) Bucket],"OCTOBER 25 PLANNED") -> 0 | V11: =COUNTIFS(MASTER[ZH],$D11,MASTER[Planned (Month) Bucket],"AUGUST 25 PLANNED",MASTER[Actual (Month) Bucket],"NOVEMBER 25") -> 0 | W11: =COUNTIFS(MASTER[ZH],$D11,MASTER[Planned (Month) Bucket],"SEPTEMBER 25 PLANNED",MASTER[Actual (Month) Bucket],"NOVEMBER 25") -> 0 | X11: =COUNTIFS(MASTER[ZH],$D11,MASTER[Planned (Month) Bucket],"OCTOBER 25 PLANNED",MASTER[Actual (Month) Bucket],"NOVEMBER 25") -> 0 | Y11: =COUNTIFS(MASTER[ZH],$D11,MASTER[Planned (Month) Bucket],"NOVEMBER 25 PLANNED") -> 0 | Z11: =COUNTIFS(MASTER[ZH],$D11,MASTER[Planned (Month) Bucket],"NOVEMBER 25 PLANNED",MASTER[Actual (Month) Bucket],"NOVEMBER 25") -> 0 | AA11: =V11+W11+X11+Z11 -> 0 | AB11: =COUNTIFS(MASTER[EPC Status (Current Week)],AB$4,MASTER[ZH],$D11,MASTER[Planned (Month) Bucket],"NOVEMBER 25 PLANNED") -> 0 | AD11: =COUNTIFS(MASTER[ZH],$D11,MASTER[Planned (Month) Bucket],"AUGUST 25 PLANNED",MASTER[Actual (Month) Bucket],"DECEMBER 25") -> 0 | AE11: =COUNTIFS(MASTER[ZH],$D11,MASTER[Planned (Month) Bucket],"SEPTEMBER 25 PLANNED",MASTER[Actual (Month) Bucket],"DECEMBER 25") -> 0 | AF11: =COUNTIFS(MASTER[ZH],$D11,MASTER[Planned (Month) Bucket],"OCTOBER 25 PLANNED",MASTER[Actual (Month) Bucket],"DECEMBER 25") -> 0 | AG11: =COUNTIFS(MASTER[ZH],$D11,MASTER[Planned (Month) Bucket],"NOVEMBER 25 PLANNED",MASTER[Actual (Month) Bucket],"DECEMBER 25") -> 0 | AH11: =COUNTIFS(MASTER[ZH],$D11,MASTER[Planned (Month) Bucket],"DECEMBER 25 PLANNED") -> 0 | AI11: =COUNTIFS(MASTER[ZH],$D11,MASTER[Planned (Month) Bucket],"DECEMBER 25 PLANNED",MASTER[Actual (Month) Bucket],"DECEMBER 25") -> 0 | AJ11: =SUM(AD11,AE11,AF11,AG11,AI11) -> 0 | AK11: =COUNTIFS(MASTER[EPC Status (Current Week)],AK$4,MASTER[ZH],$D11,MASTER[Planned (Month) Bucket],"DECEMBER 25 PLANNED") -> 0 | AM11: =COUNTIFS(MASTER[ZH],$D11,MASTER[Planned (Month) Bucket],"OCTOBER 25 PLANNED",MASTER[Actual (Month) Bucket],"JANUARY 26") -> 0 | AN11: =COUNTIFS(MASTER[ZH],$D11,MASTER[Planned (Month) Bucket],"NOVEMBER 25 PLANNED",MASTER[Actual (Month) Bucket],"JANUARY 26") -> 0 | AO11: =COUNTIFS(MASTER[ZH],$D11,MASTER[Planned (Month) Bucket],"DECEMBER 25 PLANNED",MASTER[Actual (Month) Bucket],"JANUARY 26") -> 0 | AP11: =COUNTIFS(MASTER[ZH],$D11,MASTER[Planned (Month) Bucket],"JANUARY 26 PLANNED") -> 0 | AQ11: =COUNTIFS(MASTER[ZH],$D11,MASTER[Planned (Month) Bucket],"JANUARY 26 PLANNED",MASTER[Actual (Month) Bucket],"JANUARY 26") -> 0 | AR11: =SUM(AM11,AN11,AO11,AQ11) -> 0 | AS11: =COUNTIFS(MASTER[EPC Status (Current Week)],AS$4,MASTER[ZH],$D11,MASTER[Planned (Month) Bucket],"JANUARY 26 PLANNED") -> 0 | AU11: =COUNTIFS(MASTER[ZH],$D11,MASTER[Planned (Month) Bucket],"NOVEMBER 25 PLANNED",MASTER[Actual (Month) Bucket],"FEBRUARY 26") -> 0 | AV11: =COUNTIFS(MASTER[ZH],$D11,MASTER[Planned (Month) Bucket],"DECEMBER 25 PLANNED",MASTER[Actual (Month) Bucket],"FEBRUARY 26") -> 0 | AW11: =COUNTIFS(MASTER[ZH],$D11,MASTER[Planned (Month) Bucket],"JANUARY 26 PLANNED",MASTER[Actual (Month) Bucket],"FEBRUARY 26") -> 0 | AX11: =COUNTIFS(MASTER[ZH],$D11,MASTER[Planned (Month) Bucket],"FEBRUARY 26 PLANNED") -> 13 | AY11: =COUNTIFS(MASTER[ZH],$D11,MASTER[Planned (Month) Bucket],"FEBRUARY 26 PLANNED",MASTER[Actual (Month) Bucket],"FEBRUARY 26") -> 0 | AZ11: =SUM(AU11,AV11,AW11,AY11) -> 0 | BA11: =COUNTIFS(MASTER[EPC Status (Current Week)],BA$4,MASTER[ZH],$D11,MASTER[Planned (Month) Bucket],"FEBRUARY 26 PLANNED") -> 0 | BD11: =COUNTIFS(MASTER[ZH],$D11,MASTER[Planned (Month) Bucket],"MARCH 26 PLANNED") -> 137 | BE11: =COUNTIFS(MASTER[ZH],$D11,MASTER[Planned (Month) Bucket],"MARCH 26 PLANNED",MASTER[Actual (Month) Bucket],"MARCH 26")+COUNTIFS(MASTER[ZH],$D11,MASTER[Planned (Month) Bucket],"FEBRUARY 26 PLANNED",MASTER[Actual (Month) Bucket],"MARCH 26")+COUNTIFS(MASTER[ZH],$D11,MASTER[Planned (Month) Bucket],"JANUARY 26 PLANNED",MASTER[Actual (Month) Bucket],"MARCH 26") -> 0 | BF11: =COUNTIFS(MASTER[EPC Status (Current Week)],BF$4,MASTER[ZH],$D11,MASTER[Planned (Month) Bucket],"MARCH 26 PLANNED") -> 7 | BG11: =COUNTIFS(MASTER[EPC Status (Current Week)],BG$4,MASTER[ZH],$D11,MASTER[Planned (Month) Bucket],"MARCH 26 PLANNED") -> 0 | BH11: =BE11 -> 0 | BJ11: =COUNTIFS(MASTER[ZH],$D11,MASTER[Planned (Month) Bucket],"APRIL 26 PLANNED") -> 103 | BK11: =COUNTIFS(MASTER[ZH],$D11,MASTER[Planned (Month) Bucket],"APRIL 26 PLANNED",MASTER[Actual (Month) Bucket],"APRIL 26")+COUNTIFS(MASTER[ZH],$D11,MASTER[Planned (Month) Bucket],"MARCH 26 PLANNED",MASTER[Actual (Month) Bucket],"APRIL 26")+COUNTIFS(MASTER[ZH],$D11,MASTER[Planned (Month) Bucket],"FEBRUARY 26 PLANNED",MASTER[Actual (Month) Bucket],"APRIL 26")+COUNTIFS(MASTER[ZH],$D11,MASTER[Planned (Month) Bucket],"JANUARY 26 PLANNED",MASTER[Actual (Month) Bucket],"APRIL 26")+COUNTIFS(MASTER[ZH],$D11,MASTER[Planned (Month) Bucket],"MAY 26 PLANNED",MASTER[Actual (Month) Bucket],"APRIL 26") -> 157 | BL11: =COUNTIFS(MASTER[EPC Status (Current Week)],BL$4,MASTER[ZH],$D11,MASTER[Planned (Month) Bucket],"APRIL 26 PLANNED") -> 10 | BM11: =COUNTIFS(MASTER[EPC Status (Current Week)],BM$4,MASTER[ZH],$D11,MASTER[Planned (Month) Bucket],"APRIL 26 PLANNED") -> 0 | BN11: =BK11 -> 157 | BP11: =COUNTIFS(MASTER[ZH],$D11,MASTER[Planned (Month) Bucket],"MAY 26 PLANNED") -> 138 | BQ11: =COUNTIFS(MASTER[ZH],$D11,MASTER[Planned (Month) Bucket],"NOVEMBER 25 PLANNED",MASTER[Actual (Month) Bucket],"MAY 26")+COUNTIFS(MASTER[ZH],$D11,MASTER[Planned (Month) Bucket],"DECEMBER 25 PLANNED",MASTER[Actual (Month) Bucket],"MAY 26")+COUNTIFS(MASTER[ZH],$D11,MASTER[Planned (Month) Bucket],"FEBRUARY 26 PLANNED",MASTER[Actual (Month) Bucket],"MAY 26")+COUNTIFS(MASTER[ZH],$D11,MASTER[Planned (Month) Bucket],"MARCH 26 PLANNED",MASTER[Actual (Month) Bucket],"MAY 26")+COUNTIFS(MASTER[ZH],$D11,MASTER[Planned (Month) Bucket],"APRIL 26 PLANNED",MASTER[Actual (Month) Bucket],"MAY 26")+COUNTIFS(MASTER[ZH],$D11,MASTER[Planned (Month) Bucket],"MAY 26 PLANNED",MASTER[Actual (Month) Bucket],"MAY 26") -> 187 | BR11: =COUNTIFS(MASTER[EPC Status (Current Week)],BR$4,MASTER[ZH],$D11,MASTER[Planned (Month) Bucket],"MAY 26 PLANNED") -> 23 | BS11: =COUNTIFS(MASTER[EPC Status (Current Week)],BS$4,MASTER[ZH],$D11,MASTER[Planned (Month) Bucket],"MAY 26 PLANNED") -> 0 | BT11: =BQ11 -> 187 | BV11: =COUNTIFS(MASTER[ZH],$D11,MASTER[Planned (Month) Bucket],"JUNE 26 PLANNED") -> 61 | BW11: =COUNTIFS(MASTER[ZH],$D11,MASTER[Planned (Month) Bucket],"JUNE 26 PLANNED",MASTER[Actual (Month) Bucket],"JUNE 26")+COUNTIFS(MASTER[ZH],$D11,MASTER[Planned (Month) Bucket],"MAY 26 PLANNED",MASTER[Actual (Month) Bucket],"JUNE 26")+COUNTIFS(MASTER[ZH],$D11,MASTER[Planned (Month) Bucket],"APRIL 26 PLANNED",MASTER[Actual (Month) Bucket],"JUNE 26")+COUNTIFS(MASTER[ZH],$D11,MASTER[Planned (Month) Bucket],"MARCH 26 PLANNED",MASTER[Actual (Month) Bucket],"JUNE 26")+COUNTIFS(MASTER[ZH],$D11,MASTER[Planned (Month) Bucket],"FEBRUARY 26 PLANNED",MASTER[Actual (Month) Bucket],"JUNE 26") -> 8 | BX11: =COUNTIFS(MASTER[EPC Status (Current Week)],BX$4,MASTER[ZH],$D11,MASTER[Planned (Month) Bucket],"JUNE 26 PLANNED") -> 60 | BY11: =COUNTIFS(MASTER[EPC Status (Current Week)],BY$4,MASTER[ZH],$D11,MASTER[Planned (Month) Bucket],"JUNE 26 PLANNED") -> 0 | BZ11: =BW11 -> 8 | CB11: =COUNTIFS(MASTER[ZH],$D11,MASTER[Planned (Month) Bucket],"JULY 26 PLANNED") -> 5 | CC11: =COUNTIFS(MASTER[ZH],$D11,MASTER[Planned (Month) Bucket],"JULY 26 PLANNED",MASTER[Actual (Month) Bucket],"JULY 26") -> 0 | CD11: =COUNTIFS(MASTER[EPC Status (Current Week)],CD$4,MASTER[ZH],$D11,MASTER[Planned (Month) Bucket],"JULY 26 PLANNED") -> 5 | CE11: =COUNTIFS(MASTER[EPC Status (Current Week)],CE$4,MASTER[ZH],$D11,MASTER[Planned (Month) Bucket],"JULY 26 PLANNED") -> 0 | CF11: =CC11 -> 0 | CH11: =COUNTIFS(MASTER[ZH],$D11,MASTER[Planned (Month) Bucket],"AUGUST 26 PLANNED") -> 0 | CI11: =COUNTIFS(MASTER[ZH],$D11,MASTER[Planned (Month) Bucket],"AUGUST 26 PLANNED",MASTER[Actual (Month) Bucket],"AUG 26") -> 0 | CJ11: =COUNTIFS(MASTER[EPC Status (Current Week)],CJ$4,MASTER[ZH],$D11,MASTER[Planned (Month) Bucket],"AUGUST 26 PLANNED") -> 0 | CK11: =COUNTIFS(MASTER[EPC Status (Current Week)],CK$4,MASTER[ZH],$D11,MASTER[Planned (Month) Bucket],"AUGUST 26 PLANNED") -> 0 | CL11: =CI11 -> 0
D12: AK | F12: =SUM(L12,Q12,Y12,AH12,AP12,AX12,BD12,BJ12,BP12) -> 99 | G12: =SUM(S12,AA12,AJ12,AR12,AZ12,BH12,BN12,BT12,BZ12) -> 58 | H12: =SUM(T12,AB12,AK12,AS12,BA12,BF12,BL12,BR12,BX12,CD12,CJ12) -> 52 | I12: =SUM(BG12,BM12,BS12,BY12,CE12,CK12) -> 2 | K12: =COUNTIFS(MASTER[ZH],$D12,MASTER[Planned (Month) Bucket],"March 25 PLANNED",MASTER[Actual (Month) Bucket],"April 25") -> 0 | L12: =COUNTIFS(MASTER[ZH],$D12,MASTER[Planned (Month) Bucket],"April 25 PLANNED") -> 0 | M12: =COUNTIFS(MASTER[ZH],$D12,MASTER[Planned (Month) Bucket],"April 25 PLANNED",MASTER[Actual (Month) Bucket],"April 25") -> 0 | O12: =COUNTIFS(MASTER[ZH],$D12,MASTER[Planned (Month) Bucket],"AUGUST 25 PLANNED",MASTER[Actual (Month) Bucket],"OCTOBER 25") -> 0 | P12: =COUNTIFS(MASTER[ZH],$D12,MASTER[Planned (Month) Bucket],"SEPTEMBER 25 PLANNED",MASTER[Actual (Month) Bucket],"OCTOBER 25") -> 0 | Q12: =COUNTIFS(MASTER[ZH],$D12,MASTER[Planned (Month) Bucket],"OCTOBER 25 PLANNED") -> 0 | R12: =COUNTIFS(MASTER[ZH],$D12,MASTER[Planned (Month) Bucket],"OCTOBER 25 PLANNED",MASTER[Actual (Month) Bucket],"OCTOBER 25") -> 0 | S12: =O12+P12+R12 -> 0 | T12: =COUNTIFS(MASTER[EPC Status (Current Week)],T$4,MASTER[ZH],$D12,MASTER[Planned (Month) Bucket],"OCTOBER 25 PLANNED") -> 0 | V12: =COUNTIFS(MASTER[ZH],$D12,MASTER[Planned (Month) Bucket],"AUGUST 25 PLANNED",MASTER[Actual (Month) Bucket],"NOVEMBER 25") -> 0 | W12: =COUNTIFS(MASTER[ZH],$D12,MASTER[Planned (Month) Bucket],"SEPTEMBER 25 PLANNED",MASTER[Actual (Month) Bucket],"NOVEMBER 25") -> 0 | X12: =COUNTIFS(MASTER[ZH],$D12,MASTER[Planned (Month) Bucket],"OCTOBER 25 PLANNED",MASTER[Actual (Month) Bucket],"NOVEMBER 25") -> 0 | Y12: =COUNTIFS(MASTER[ZH],$D12,MASTER[Planned (Month) Bucket],"NOVEMBER 25 PLANNED") -> 1 | Z12: =COUNTIFS(MASTER[ZH],$D12,MASTER[Planned (Month) Bucket],"NOVEMBER 25 PLANNED",MASTER[Actual (Month) Bucket],"NOVEMBER 25") -> 0 | AA12: =V12+W12+X12+Z12 -> 0 | AB12: =COUNTIFS(MASTER[EPC Status (Current Week)],AB$4,MASTER[ZH],$D12,MASTER[Planned (Month) Bucket],"NOVEMBER 25 PLANNED") -> 0 | AD12: =COUNTIFS(MASTER[ZH],$D12,MASTER[Planned (Month) Bucket],"AUGUST 25 PLANNED",MASTER[Actual (Month) Bucket],"DECEMBER 25") -> 0 | AE12: =COUNTIFS(MASTER[ZH],$D12,MASTER[Planned (Month) Bucket],"SEPTEMBER 25 PLANNED",MASTER[Actual (Month) Bucket],"DECEMBER 25") -> 0 | AF12: =COUNTIFS(MASTER[ZH],$D12,MASTER[Planned (Month) Bucket],"OCTOBER 25 PLANNED",MASTER[Actual (Month) Bucket],"DECEMBER 25") -> 0 | AG12: =COUNTIFS(MASTER[ZH],$D12,MASTER[Planned (Month) Bucket],"NOVEMBER 25 PLANNED",MASTER[Actual (Month) Bucket],"DECEMBER 25") -> 0 | AH12: =COUNTIFS(MASTER[ZH],$D12,MASTER[Planned (Month) Bucket],"DECEMBER 25 PLANNED") -> 1 | AI12: =COUNTIFS(MASTER[ZH],$D12,MASTER[Planned (Month) Bucket],"DECEMBER 25 PLANNED",MASTER[Actual (Month) Bucket],"DECEMBER 25") -> 0 | AJ12: =SUM(AD12,AE12,AF12,AG12,AI12) -> 0 | AK12: =COUNTIFS(MASTER[EPC Status (Current Week)],AK$4,MASTER[ZH],$D12,MASTER[Planned (Month) Bucket],"DECEMBER 25 PLANNED") -> 0 | AM12: =COUNTIFS(MASTER[ZH],$D12,MASTER[Planned (Month) Bucket],"OCTOBER 25 PLANNED",MASTER[Actual (Month) Bucket],"JANUARY 26") -> 0 | AN12: =COUNTIFS(MASTER[ZH],$D12,MASTER[Planned (Month) Bucket],"NOVEMBER 25 PLANNED",MASTER[Actual (Month) Bucket],"JANUARY 26") -> 0 | AO12: =COUNTIFS(MASTER[ZH],$D12,MASTER[Planned (Month) Bucket],"DECEMBER 25 PLANNED",MASTER[Actual (Month) Bucket],"JANUARY 26") -> 0 | AP12: =COUNTIFS(MASTER[ZH],$D12,MASTER[Planned (Month) Bucket],"JANUARY 26 PLANNED") -> 2 | AQ12: =COUNTIFS(MASTER[ZH],$D12,MASTER[Planned (Month) Bucket],"JANUARY 26 PLANNED",MASTER[Actual (Month) Bucket],"JANUARY 26") -> 0 | AR12: =SUM(AM12,AN12,AO12,AQ12) -> 0 | AS12: =COUNTIFS(MASTER[EPC Status (Current Week)],AS$4,MASTER[ZH],$D12,MASTER[Planned (Month) Bucket],"JANUARY 26 PLANNED") -> 2 | AU12: =COUNTIFS(MASTER[ZH],$D12,MASTER[Planned (Month) Bucket],"NOVEMBER 25 PLANNED",MASTER[Actual (Month) Bucket],"FEBRUARY 26") -> 0 | AV12: =COUNTIFS(MASTER[ZH],$D12,MASTER[Planned (Month) Bucket],"DECEMBER 25 PLANNED",MASTER[Actual (Month) Bucket],"FEBRUARY 26") -> 0 | AW12: =COUNTIFS(MASTER[ZH],$D12,MASTER[Planned (Month) Bucket],"JANUARY 26 PLANNED",MASTER[Actual (Month) Bucket],"FEBRUARY 26") -> 0 | AX12: =COUNTIFS(MASTER[ZH],$D12,MASTER[Planned (Month) Bucket],"FEBRUARY 26 PLANNED") -> 6 | AY12: =COUNTIFS(MASTER[ZH],$D12,MASTER[Planned (Month) Bucket],"FEBRUARY 26 PLANNED",MASTER[Actual (Month) Bucket],"FEBRUARY 26") -> 0 | AZ12: =SUM(AU12,AV12,AW12,AY12) -> 0 | BA12: =COUNTIFS(MASTER[EPC Status (Current Week)],BA$4,MASTER[ZH],$D12,MASTER[Planned (Month) Bucket],"FEBRUARY 26 PLANNED") -> 1 | BD12: =COUNTIFS(MASTER[ZH],$D12,MASTER[Planned (Month) Bucket],"MARCH 26 PLANNED") -> 23 | BE12: =COUNTIFS(MASTER[ZH],$D12,MASTER[Planned (Month) Bucket],"MARCH 26 PLANNED",MASTER[Actual (Month) Bucket],"MARCH 26")+COUNTIFS(MASTER[ZH],$D12,MASTER[Planned (Month) Bucket],"FEBRUARY 26 PLANNED",MASTER[Actual (Month) Bucket],"MARCH 26")+COUNTIFS(MASTER[ZH],$D12,MASTER[Planned (Month) Bucket],"JANUARY 26 PLANNED",MASTER[Actual (Month) Bucket],"MARCH 26")++COUNTIFS(MASTER[ZH],$D12,MASTER[Planned (Month) Bucket],"NOVEMBER 25 PLANNED",MASTER[Actual (Month) Bucket],"MARCH 26") -> 0 | BF12: =COUNTIFS(MASTER[EPC Status (Current Week)],BF$4,MASTER[ZH],$D12,MASTER[Planned (Month) Bucket],"MARCH 26 PLANNED") -> 10 | BG12: =COUNTIFS(MASTER[EPC Status (Current Week)],BG$4,MASTER[ZH],$D12,MASTER[Planned (Month) Bucket],"MARCH 26 PLANNED") -> 0 | BH12: =BE12 -> 0 | BJ12: =COUNTIFS(MASTER[ZH],$D12,MASTER[Planned (Month) Bucket],"APRIL 26 PLANNED") -> 47 | BK12: =COUNTIFS(MASTER[ZH],$D12,MASTER[Planned (Month) Bucket],"APRIL 26 PLANNED",MASTER[Actual (Month) Bucket],"APRIL 26")+COUNTIFS(MASTER[ZH],$D12,MASTER[Planned (Month) Bucket],"MARCH 26 PLANNED",MASTER[Actual (Month) Bucket],"APRIL 26")+COUNTIFS(MASTER[ZH],$D12,MASTER[Planned (Month) Bucket],"FEBRUARY 26 PLANNED",MASTER[Actual (Month) Bucket],"APRIL 26")+COUNTIFS(MASTER[ZH],$D12,MASTER[Planned (Month) Bucket],"JANUARY 26 PLANNED",MASTER[Actual (Month) Bucket],"APRIL 26")+COUNTIFS(MASTER[ZH],$D12,MASTER[Planned (Month) Bucket],"MAY 26 PLANNED",MASTER[Actual (Month) Bucket],"APRIL 26") -> 11 | BL12: =COUNTIFS(MASTER[EPC Status (Current Week)],BL$4,MASTER[ZH],$D12,MASTER[Planned (Month) Bucket],"APRIL 26 PLANNED") -> 23 | BM12: =COUNTIFS(MASTER[EPC Status (Current Week)],BM$4,MASTER[ZH],$D12,MASTER[Planned (Month) Bucket],"APRIL 26 PLANNED") -> 0 | BN12: =BK12 -> 11 | BP12: =COUNTIFS(MASTER[ZH],$D12,MASTER[Planned (Month) Bucket],"MAY 26 PLANNED") -> 19 | BQ12: =COUNTIFS(MASTER[ZH],$D12,MASTER[Planned (Month) Bucket],"NOVEMBER 25 PLANNED",MASTER[Actual (Month) Bucket],"MAY 26")+COUNTIFS(MASTER[ZH],$D12,MASTER[Planned (Month) Bucket],"DECEMBER 25 PLANNED",MASTER[Actual (Month) Bucket],"MAY 26")+COUNTIFS(MASTER[ZH],$D12,MASTER[Planned (Month) Bucket],"FEBRUARY 26 PLANNED",MASTER[Actual (Month) Bucket],"MAY 26")+COUNTIFS(MASTER[ZH],$D12,MASTER[Planned (Month) Bucket],"MARCH 26 PLANNED",MASTER[Actual (Month) Bucket],"MAY 26")+COUNTIFS(MASTER[ZH],$D12,MASTER[Planned (Month) Bucket],"APRIL 26 PLANNED",MASTER[Actual (Month) Bucket],"MAY 26")+COUNTIFS(MASTER[ZH],$D12,MASTER[Planned (Month) Bucket],"MAY 26 PLANNED",MASTER[Actual (Month) Bucket],"MAY 26") -> 45 | BR12: =COUNTIFS(MASTER[EPC Status (Current Week)],BR$4,MASTER[ZH],$D12,MASTER[Planned (Month) Bucket],"MAY 26 PLANNED") -> 5 | BS12: =COUNTIFS(MASTER[EPC Status (Current Week)],BS$4,MASTER[ZH],$D12,MASTER[Planned (Month) Bucket],"MAY 26 PLANNED") -> 0 | BT12: =BQ12 -> 45 | BV12: =COUNTIFS(MASTER[ZH],$D12,MASTER[Planned (Month) Bucket],"JUNE 26 PLANNED") -> 8 | BW12: =COUNTIFS(MASTER[ZH],$D12,MASTER[Planned (Month) Bucket],"JUNE 26 PLANNED",MASTER[Actual (Month) Bucket],"JUNE 26")+COUNTIFS(MASTER[ZH],$D12,MASTER[Planned (Month) Bucket],"MAY 26 PLANNED",MASTER[Actual (Month) Bucket],"JUNE 26")+COUNTIFS(MASTER[ZH],$D12,MASTER[Planned (Month) Bucket],"APRIL 26 PLANNED",MASTER[Actual (Month) Bucket],"JUNE 26")+COUNTIFS(MASTER[ZH],$D12,MASTER[Planned (Month) Bucket],"MARCH 26 PLANNED",MASTER[Actual (Month) Bucket],"JUNE 26")+COUNTIFS(MASTER[ZH],$D12,MASTER[Planned (Month) Bucket],"FEBRUARY 26 PLANNED",MASTER[Actual (Month) Bucket],"JUNE 26") -> 2 | BX12: =COUNTIFS(MASTER[EPC Status (Current Week)],BX$4,MASTER[ZH],$D12,MASTER[Planned (Month) Bucket],"JUNE 26 PLANNED") -> 7 | BY12: =COUNTIFS(MASTER[EPC Status (Current Week)],BY$4,MASTER[ZH],$D12,MASTER[Planned (Month) Bucket],"JUNE 26 PLANNED") -> 1 | BZ12: =BW12 -> 2 | CB12: =COUNTIFS(MASTER[ZH],$D12,MASTER[Planned (Month) Bucket],"JULY 26 PLANNED") -> 4 | CC12: =COUNTIFS(MASTER[ZH],$D12,MASTER[Planned (Month) Bucket],"JULY 26 PLANNED",MASTER[Actual (Month) Bucket],"JULY 26") -> 0 | CD12: =COUNTIFS(MASTER[EPC Status (Current Week)],CD$4,MASTER[ZH],$D12,MASTER[Planned (Month) Bucket],"JULY 26 PLANNED") -> 3 | CE12: =COUNTIFS(MASTER[EPC Status (Current Week)],CE$4,MASTER[ZH],$D12,MASTER[Planned (Month) Bucket],"JULY 26 PLANNED") -> 1 | CF12: =CC12 -> 0 | CH12: =COUNTIFS(MASTER[ZH],$D12,MASTER[Planned (Month) Bucket],"AUGUST 26 PLANNED") -> 1 | CI12: =COUNTIFS(MASTER[ZH],$D12,MASTER[Planned (Month) Bucket],"AUGUST 26 PLANNED",MASTER[Actual (Month) Bucket],"AUG 26") -> 0 | CJ12: =COUNTIFS(MASTER[EPC Status (Current Week)],CJ$4,MASTER[ZH],$D12,MASTER[Planned (Month) Bucket],"AUGUST 26 PLANNED") -> 1 | CK12: =COUNTIFS(MASTER[EPC Status (Current Week)],CK$4,MASTER[ZH],$D12,MASTER[Planned (Month) Bucket],"AUGUST 26 PLANNED") -> 0 | CL12: =CI12 -> 0
D13: TOTAL | F13: =SUM(F10:F12) -> 743 | G13: =SUM(G10:G12) -> 567 | H13: =SUM(H10:H12) -> 304 | I13: =SUM(I10:I12) -> 2 | K13: =SUM(K10:K12) -> 0 | L13: =SUM(L10:L12) -> 0 | M13: =SUM(M10:M12) -> 0 | O13: =SUM(O10:O12) -> 0 | P13: =SUM(P10:P12) -> 0 | Q13: =SUM(Q10:Q12) -> 0 | R13: =SUM(R10:R12) -> 0 | S13: =SUM(S10:S12) -> 0 | T13: =SUM(T10:T12) -> 0 | V13: =SUM(V10:V12) -> 0 | W13: =SUM(W10:W12) -> 0 | X13: =SUM(X10:X12) -> 0 | Y13: =SUM(Y10:Y12) -> 1 | Z13: =SUM(Z10:Z12) -> 0 | AA13: =SUM(AA10:AA12) -> 0 | AB13: =SUM(AB10:AB12) -> 0 | AD13: =SUM(AD10:AD12) -> 0 | AE13: =SUM(AE10:AE12) -> 0 | AF13: =SUM(AF10:AF12) -> 0 | AG13: =SUM(AG10:AG12) -> 0 | AH13: =SUM(AH10:AH12) -> 1 | AI13: =SUM(AI10:AI12) -> 0 | AJ13: =SUM(AJ10:AJ12) -> 0 | AK13: =SUM(AK10:AK12) -> 0 | AM13: =SUM(AM10:AM12) -> 0 | AN13: =SUM(AN10:AN12) -> 0 | AO13: =SUM(AO10:AO12) -> 0 | AP13: =SUM(AP10:AP12) -> 2 | AQ13: =SUM(AQ10:AQ12) -> 0 | AR13: =SUM(AR10:AR12) -> 0 | AS13: =SUM(AS10:AS12) -> 2 | AU13: =SUM(AU10:AU12) -> 0 | AV13: =SUM(AV10:AV12) -> 0 | AW13: =SUM(AW10:AW12) -> 0 | AX13: =SUM(AX10:AX12) -> 32 | AY13: =SUM(AY10:AY12) -> 0 | AZ13: =SUM(AZ10:AZ12) -> 0 | BA13: =SUM(BA10:BA12) -> 6 | BD13: =SUM(BD10:BD12) -> 190 | BE13: =SUM(BE10:BE12) -> 0 | BF13: =SUM(BF10:BF12) -> 23 | BG13: =SUM(BG10:BG12) -> 0 | BH13: =SUM(BH10:BH12) -> 0 | BJ13: =SUM(BJ10:BJ12) -> 304 | BK13: =SUM(BK10:BK12) -> 209 | BL13: =SUM(BL10:BL12) -> 99 | BM13: =SUM(BM10:BM12) -> 0 | BN13: =SUM(BN10:BN12) -> 209 | BP13: =SUM(BP10:BP12) -> 213 | BQ13: =SUM(BQ10:BQ12) -> 334 | BR13: =SUM(BR10:BR12) -> 54 | BS13: =SUM(BS10:BS12) -> 0 | BT13: =SUM(BT10:BT12) -> 334 | BV13: =SUM(BV10:BV12) -> 118 | BW13: =SUM(BW10:BW12) -> 24 | BX13: =SUM(BX10:BX12) -> 109 | BY13: =SUM(BY10:BY12) -> 1 | BZ13: =SUM(BZ10:BZ12) -> 24 | CB13: =SUM(CB10:CB12) -> 11 | CC13: =SUM(CC10:CC12) -> 0 | CD13: =SUM(CD10:CD12) -> 10 | CE13: =SUM(CE10:CE12) -> 1 | CF13: =SUM(CF10:CF12) -> 0 | CH13: =SUM(CH10:CH12) -> 1 | CI13: =SUM(CI10:CI12) -> 0 | CJ13: =SUM(CJ10:CJ12) -> 1 | CK13: =SUM(CK10:CK12) -> 0 | CL13: =SUM(CL10:CL12) -> 0
C14: Grand Total | F14: =F9+F13 -> 922 | G14: =G9+G13 -> 713 | H14: =H9+H13 -> 382 | I14: =I9+I13 -> 2 | K14: =K9+K13 -> 0 | L14: =L9+L13 -> 0 | M14: =M9+M13 -> 0 | O14: =O9+O13 -> 0 | P14: =P9+P13 -> 0 | Q14: =Q9+Q13 -> 0 | R14: =R9+R13 -> 0 | S14: =S9+S13 -> 0 | T14: =T9+T13 -> 0 | V14: =V9+V13 -> 0 | W14: =W9+W13 -> 0 | X14: =X9+X13 -> 0 | Y14: =Y9+Y13 -> 1 | Z14: =Z9+Z13 -> 0 | AA14: =AA9+AA13 -> 0 | AB14: =AB9+AB13 -> 0 | AD14: =AD9+AD13 -> 0 | AE14: =AE9+AE13 -> 0 | AF14: =AF9+AF13 -> 0 | AG14: =AG9+AG13 -> 0 | AH14: =AH9+AH13 -> 1 | AI14: =AI9+AI13 -> 0 | AJ14: =AJ9+AJ13 -> 0 | AK14: =AK9+AK13 -> 0 | AM14: =AM9+AM13 -> 0 | AN14: =AN9+AN13 -> 0 | AO14: =AO9+AO13 -> 0 | AP14: =AP9+AP13 -> 4 | AQ14: =AQ9+AQ13 -> 0 | AR14: =AR9+AR13 -> 0 | AS14: =AS9+AS13 -> 3 | AU14: =AU9+AU13 -> 0 | AV14: =AV9+AV13 -> 0 | AW14: =AW9+AW13 -> 0 | AX14: =AX9+AX13 -> 35 | AY14: =AY9+AY13 -> 0 | AZ14: =AZ9+AZ13 -> 0 | BA14: =BA9+BA13 -> 7 | BD14: =BD9+BD13 -> 250 | BE14: =BE9+BE13 -> 0 | BF14: =BF9+BF13 -> 24 | BG14: =BG9+BG13 -> 0 | BH14: =BH9+BH13 -> 0 | BJ14: =BJ9+BJ13 -> 337 | BK14: =BK9+BK13 -> 275 | BL14: =BL9+BL13 -> 108 | BM14: =BM9+BM13 -> 0 | BN14: =BN9+BN13 -> 275 | BP14: =BP9+BP13 -> 294 | BQ14: =BQ9+BQ13 -> 408 | BR14: =BR9+BR13 -> 75 | BS14: =BS9+BS13 -> 0 | BT14: =BT9+BT13 -> 408 | BV14: =BV9+BV13 -> 156 | BW14: =BW9+BW13 -> 30 | BX14: =BX9+BX13 -> 147 | BY14: =BY9+BY13 -> 1 | BZ14: =BZ9+BZ13 -> 30 | CB14: =CB9+CB13 -> 18 | CC14: =CC9+CC13 -> 0 | CD14: =CD9+CD13 -> 17 | CE14: =CE9+CE13 -> 1 | CF14: =CF9+CF13 -> 0 | CH14: =CH9+CH13 -> 1 | CI14: =CI9+CI13 -> 0 | CJ14: =CJ9+CJ13 -> 1 | CK14: =CK9+CK13 -> 0 | CL14: =CL9+CL13 -> 0

Sheet PAN INDIA Summary
A1: EPC (PAN INDIA) ROLLOUT STATUS AT A GLANCE - FY 2026-27
A2: Sl. No. | B2: Business Format / Sub Format | C2: Site Type | D2: PM Head | E2: AOP FY 2025-26 | F2: Carry Forward | I2: Q1 | M2: Q2 | Q2: Q3 | U2: Q4 | Y2: EPC READY | Z2: LAUNCHED | AA2: YTL | AB2: YTL - Dropped by Business | AC2: TOTAL EPC READY | AD2: TOTAL LAUNCHED | AE2: TOTAL YTL | AF2: TOTAL YTL - Dropped by Business | AG2: WIP | AH2: MARCH 25 BACKLOG BTG | AI2: APRIL 25 BACKLOG BTG | AJ2: MAY 25 BACKLOG BTG | AK2: JUNE 25 BACKLOG BTG | AL2: JULY 25 BACKLOG BTG | AM2: AUGUST 25 BACKLOG BTG | AN2: SEPTEMBER 25 BACKLOG BTG | AO2: OCTOBER 25 BACKLOG BTG | AP2: NOVEMBER 25 BACKLOG BTG | AQ2: MARCH 25 PLANNED | AR2: APRIL 25 PLANNED | AS2: MAY 25 PLANNED | AT2: JUNE 25 PLANNED | AU2: JULY 25 PLANNED | AV2: AUGUST 25 PLANNED | AW2: SEPTEMBER 25 PLANNED | AX2: OCTOBER 25 PLANNED | AY2: NOVEMBER 25 PLANNED | AZ2: DECEMBER 25 PLANNED | BA2: JANUARY 26 PLANNED | BB2: FEBRUARY 26 PLANNED | BC2: MARCH 26 PLANNED | BD2: APRIL 26 PLANNED | BE2: MAY 26 PLANNED | BF2: JUNE 26 PLANNED | BG2: JULY 26 PLANNED | BH2: AUGUST 26 PLANNED | BI2: On Hold | BJ2: Partial WIP | BK2: YTS | BL2: Dropped | BM2: NRFC | BN2: 1 | BO2: 2 | BP2: 3 | BQ2: 4 | BR2: 5 | BS2: 6 | BT2: 7 | BU2: 8
F3: EPC Ready Previous FY | G3: LAUNCHED | H3: YTL | I3: 46113 | J3: 46143 | K3: 46174 | L3: Q1 TOTAL | M3: 46204 | N3: 46235 | O3: 46266 | P3: Q2 TOTAL | Q3: 46296 | R3: 46327 | S3: 46357 | T3: Q3 TOTAL | U3: 46388 | V3: 46419 | W3: 46447 | X3: Q4 TOTAL | BN3: Budget Approved - RFC Awaited | BO3: Budget Submitted - Approval Awaited | BP3: ML Received - Design WIP | BQ3: ML Received - Business Issue | BR3: SDR Done - ML Pending | BS3: SDR - In Progress | BT3: Pre SDR Site | BU3: Pre Budget Dehire Site
E4: 2265 | F4: =F143 -> 34 | G4: =G143 -> 25 | H4: =H143 -> 9 | I4: =I143 -> 275 | J4: =J143 -> 408 | K4: =K143 -> 30 | L4: =L143 -> 713 | M4: =M143 -> 0 | ... AG4: =AG143 -> 382 | AH4: =AQ4 -> 0 | AI4: =AR4 -> 0 | AJ4: =AS4 -> 0 | AK4: =AT4 -> 0 | AL4: =AU4 -> 0 | AM4: =AV4 -> 0 | AN4: =AW4 -> 0 | AO4: =AX4 -> 0 | AP4: =AY4 -> 0 | AQ4: =AQ143 -> 0 | AR4: =AR143 -> 0 | AS4: =AS143 -> 0 | AT4: =AT143 -> 0 | AU4: =AU143 -> 0 | AV4: =AV143 -> 0 | AW4: =AW143 -> 0 | AX4: =AX143 -> 0 | ... BU4: =BU143 -> 5
A5: A | B5: A. Consumer Electronics & Jewels | E5: =SUM(E6:E19) -> 1078 | F5: =SUM(F6:F19) -> 6 | G5: =SUM(G6:G19) -> 3 | H5: =SUM(H6:H19) -> 3 | I5: =SUM(I6:I19) -> 15 | J5: =SUM(J6:J19) -> 6 | K5: =SUM(K6:K19) -> 0 | L5: =SUM(L6:L19) -> 21 | ... BM5: =SUM(BM6:BM19) -> 40 | BN5: =SUM(BN6:BN16) -> 25 | BO5: =SUM(BO6:BO16) -> 0 | BP5: =SUM(BP6:BP16) -> 0 | BQ5: =SUM(BQ6:BQ16) -> 1 | BR5: =SUM(BR6:BR16) -> 14 | BS5: =SUM(BS6:BS16) -> 0 | BT5: =SUM(BT6:BT16) -> 0 | BU5: =SUM(BU6:BU16) -> 0
A6: 1 | B6: Digital Stores | C6: NSO | D6: Amit C | E6: 85 | F6: =COUNTIFS(MASTER[Sub Format],$B6,MASTER[EPC Status (Current Week)],$F$3) -> 4 | G6: =COUNTIFS(MASTER[LAUNCHED / YTL],"LAUNCHED",MASTER[Sub Format],$B6,MASTER[EPC Status (Current Week)],"EPC Ready Previous FY") -> 2 | H6: =COUNTIFS(MASTER[LAUNCHED / YTL],"YTL",MASTER[Sub Format],$B6,MASTER[EPC Status (Current Week)],"EPC Ready Previous FY") -> 2 | I6: =COUNTIFS(MASTER[Sub Format],$B6,MASTER[Actual (Month) Bucket],I$3) -> 5 | J6: =COUNTIFS(MASTER[Sub Format],$B6,MASTER[Actual (Month) Bucket],J$3) -> 2 | K6: =COUNTIFS(MASTER[Sub Format],$B6,MASTER[Actual (Month) Bucket],K$3) -> 0 | L6: =SUM(I6:K6) -> 7 | M6: =COUNTIFS(MASTER[Sub Format],$B6,MASTER[Actual (Month) Bucket],M$3) -> 0 | N6: =COUNTIFS(MASTER[Sub Format],$B6,MASTER[Actual (Month) Bucket],N$3) -> 0 | O6: =COUNTIFS(MASTER[Sub Format],$B6,MASTER[Actual (Month) Bucket],O$3) -> 0 | P6: =SUM(M6:O6) -> 0 | Q6: =COUNTIFS(MASTER[Sub Format],$B6,MASTER[Actual (Month) Bucket],Q$3) -> 0 | R6: =COUNTIFS(MASTER[Sub Format],$B6,MASTER[Actual (Month) Bucket],R$3) -> 0 | S6: =COUNTIFS(MASTER[Sub Format],$B6,MASTER[Actual (Month) Bucket],S$3) -> 0 | T6: =SUM(Q6:S6) -> 0 | U6: =COUNTIFS(MASTER[Sub Format],$B6,MASTER[Actual (Month) Bucket],U$3) -> 0 | V6: =COUNTIFS(MASTER[Sub Format],$B6,MASTER[Actual (Month) Bucket],V$3) -> 0 | W6: =COUNTIFS(MASTER[Sub Format],$B6,MASTER[Actual (Month) Bucket],W$3) -> 0 | X6: =SUM(U6:W6) -> 0 | Y6: =L6+P6+T6+X6 -> 7 | Z6: =COUNTIFS(MASTER[LAUNCHED / YTL],"LAUNCHED",MASTER[Sub Format],$B6,MASTER[EPC Status (Current Week)],"EPC Ready") -> 3 | AA6: =COUNTIFS(MASTER[LAUNCHED / YTL],"YTL",MASTER[Sub Format],$B6,MASTER[EPC Status (Current Week)],"EPC Ready") -> 4 | AB6: =COUNTIFS(MASTER[LAUNCHED / YTL],"YTL - Dropped by Business",MASTER[Sub Format],$B6,MASTER[EPC Status (Current Week)],"EPC Ready") -> 0 | AC6: =COUNTIFS(MASTER[EPC Status (Current Week)],"EPC Ready",MASTER[Sub Format],$B6)+COUNTIFS(MASTER[EPC Status (Current Week)],"EPC Ready Previous FY",MASTER[Sub Format],$B6) -> 11 | AD6: =COUNTIFS(MASTER[LAUNCHED / YTL],"LAUNCHED",MASTER[Sub Format],$B6) -> 5 | AE6: =COUNTIFS(MASTER[LAUNCHED / YTL],"YTL",MASTER[Sub Format],$B6) -> 6 | AF6: =COUNTIFS(MASTER[LAUNCHED / YTL],"YTL - Dropped by Business",MASTER[Sub Format],$B6) -> 0 | AG6: =SUM(AQ6:BH6) -> 12 | AH6: =AQ6 -> 0 | AI6: =AR6 -> 0 | AJ6: =AS6 -> 0 | AK6: =AT6 -> 0 | AL6: =AU6 -> 0 | AM6: =AV6 -> 0 | AN6: =AW6 -> 0 | AO6: =AX6 -> 0 | AP6: =AY6 -> 0 | AQ6: =COUNTIFS(MASTER[Sub Format],$B6,MASTER[Planned (Month) Bucket],AQ$2,MASTER[EPC Status (Current Week)],"WIP") -> 0 | AR6: =COUNTIFS(MASTER[Sub Format],$B6,MASTER[Planned (Month) Bucket],AR$2,MASTER[EPC Status (Current Week)],"WIP") -> 0 | AS6: =COUNTIFS(MASTER[Sub Format],$B6,MASTER[Planned (Month) Bucket],AS$2,MASTER[EPC Status (Current Week)],"WIP") -> 0 | AT6: =COUNTIFS(MASTER[Sub Format],$B6,MASTER[Planned (Month) Bucket],AT$2,MASTER[EPC Status (Current Week)],"WIP") -> 0 | AU6: =COUNTIFS(MASTER[Sub Format],$B6,MASTER[Planned (Month) Bucket],AU$2,MASTER[EPC Status (Current Week)],"WIP") -> 0 | AV6: =COUNTIFS(MASTER[Sub Format],$B6,MASTER[Planned (Month) Bucket],AV$2,MASTER[EPC Status (Current Week)],"WIP") -> 0 | AW6: =COUNTIFS(MASTER[Sub Format],$B6,MASTER[Planned (Month) Bucket],AW$2,MASTER[EPC Status (Current Week)],"WIP") -> 0 | AX6: =COUNTIFS(MASTER[Sub Format],$B6,MASTER[Planned (Month) Bucket],AX$2,MASTER[EPC Status (Current Week)],"WIP") -> 0 | ... BH6: =COUNTIFS(MASTER[Sub Format],$B6,MASTER[Planned (Month) Bucket],BH$2,MASTER[EPC Status (Current Week)],"WIP") -> 0 | BI6: =COUNTIFS(MASTER[Sub Format],$B6,MASTER[EPC Status (Current Week)],BI$2) -> 0 | BJ6: =COUNTIFS(MASTER[Sub Format],$B6,MASTER[EPC Status (Current Week)],BJ$2) -> 0 | BK6: =COUNTIFS(MASTER[Sub Format],$B6,MASTER[EPC Status (Current Week)],BK$2) -> 0 | BL6: =COUNTIFS(MASTER[Sub Format],$B6,MASTER[EPC Status (Current Week)],BL$2) -> 0 | BM6: =SUM(BN6:BU6) -> 24 | BN6: =COUNTIFS(MASTER[Sub Format],$B6,MASTER[EPC Status (Current Week)],BN$3) -> 12 | BO6: =COUNTIFS(MASTER[Sub Format],$B6,MASTER[EPC Status (Current Week)],BO$3) -> 0 | BP6: =COUNTIFS(MASTER[Sub Format],$B6,MASTER[EPC Status (Current Week)],BP$3) -> 0 | BQ6: =COUNTIFS(MASTER[Sub Format],$B6,MASTER[EPC Status (Current Week)],BQ$3) -> 1 | BR6: =COUNTIFS(MASTER[Sub Format],$B6,MASTER[EPC Status (Current Week)],BR$3) -> 11 | BS6: =COUNTIFS(MASTER[Sub Format],$B6,MASTER[EPC Status (Current Week)],BS$3) -> 0 | BT6: =COUNTIFS(MASTER[Sub Format],$B6,MASTER[EPC Status (Current Week)],BT$3) -> 0 | BU6: =COUNTIFS(MASTER[Sub Format],$B6,MASTER[EPC Status (Current Week)],BU$3) -> 0
A7: 2 | B7: My Jio Store | C7: NSO | D7: Amit C | E7: 0 | F7: =COUNTIFS(MASTER[Sub Format],$B7,MASTER[EPC Status (Current Week)],$F$3) -> 0 | G7: =COUNTIFS(MASTER[LAUNCHED / YTL],"LAUNCHED",MASTER[Sub Format],$B7,MASTER[EPC Status (Current Week)],"EPC Ready Previous FY") -> 0 | H7: =COUNTIFS(MASTER[LAUNCHED / YTL],"YTL",MASTER[Sub Format],$B7,MASTER[EPC Status (Current Week)],"EPC Ready Previous FY") -> 0 | I7: =COUNTIFS(MASTER[Sub Format],$B7,MASTER[Actual (Month) Bucket],I$3) -> 0 | J7: =COUNTIFS(MASTER[Sub Format],$B7,MASTER[Actual (Month) Bucket],J$3) -> 0 | K7: =COUNTIFS(MASTER[Sub Format],$B7,MASTER[Actual (Month) Bucket],K$3) -> 0 | L7: =SUM(I7:K7) -> 0 | M7: =COUNTIFS(MASTER[Sub Format],$B7,MASTER[Actual (Month) Bucket],M$3) -> 0 | N7: =COUNTIFS(MASTER[Sub Format],$B7,MASTER[Actual (Month) Bucket],N$3) -> 0 | O7: =COUNTIFS(MASTER[Sub Format],$B7,MASTER[Actual (Month) Bucket],O$3) -> 0 | P7: =SUM(M7:O7) -> 0 | Q7: =COUNTIFS(MASTER[Sub Format],$B7,MASTER[Actual (Month) Bucket],Q$3) -> 0 | R7: =COUNTIFS(MASTER[Sub Format],$B7,MASTER[Actual (Month) Bucket],R$3) -> 0 | S7: =COUNTIFS(MASTER[Sub Format],$B7,MASTER[Actual (Month) Bucket],S$3) -> 0 | T7: =SUM(Q7:S7) -> 0 | U7: =COUNTIFS(MASTER[Sub Format],$B7,MASTER[Actual (Month) Bucket],U$3) -> 0 | V7: =COUNTIFS(MASTER[Sub Format],$B7,MASTER[Actual (Month) Bucket],V$3) -> 0 | W7: =COUNTIFS(MASTER[Sub Format],$B7,MASTER[Actual (Month) Bucket],W$3) -> 0 | X7: =SUM(U7:W7) -> 0 | Y7: =L7+P7+T7+X7 -> 0 | Z7: =COUNTIFS(MASTER[LAUNCHED / YTL],"LAUNCHED",MASTER[Sub Format],$B7,MASTER[EPC Status (Current Week)],"EPC Ready") -> 0 | AA7: =COUNTIFS(MASTER[LAUNCHED / YTL],"YTL",MASTER[Sub Format],$B7,MASTER[EPC Status (Current Week)],"EPC Ready") -> 0 | AB7: =COUNTIFS(MASTER[LAUNCHED / YTL],"YTL - Dropped by Business",MASTER[Sub Format],$B7,MASTER[EPC Status (Current Week)],"EPC Ready") -> 0 | AC7: =COUNTIFS(MASTER[EPC Status (Current Week)],"EPC Ready",MASTER[Sub Format],$B7)+COUNTIFS(MASTER[EPC Status (Current Week)],"EPC Ready Previous FY",MASTER[Sub Format],$B7) -> 0 | AD7: =COUNTIFS(MASTER[LAUNCHED / YTL],"LAUNCHED",MASTER[Sub Format],$B7) -> 0 | AE7: =COUNTIFS(MASTER[LAUNCHED / YTL],"YTL",MASTER[Sub Format],$B7) -> 0 | AF7: =COUNTIFS(MASTER[LAUNCHED / YTL],"YTL - Dropped by Business",MASTER[Sub Format],$B7) -> 0 | AG7: =SUM(AQ7:BH7) -> 0 | AH7: =AQ7 -> 0 | AI7: =AR7 -> 0 | AJ7: =AS7 -> 0 | AK7: =AT7 -> 0 | AL7: =AU7 -> 0 | AM7: =AV7 -> 0 | AN7: =AW7 -> 0 | AO7: =AX7 -> 0 | AP7: =AY7 -> 0 | AQ7: =COUNTIFS(MASTER[Sub Format],$B7,MASTER[Planned (Month) Bucket],AQ$2,MASTER[EPC Status (Current Week)],"WIP") -> 0 | AR7: =COUNTIFS(MASTER[Sub Format],$B7,MASTER[Planned (Month) Bucket],AR$2,MASTER[EPC Status (Current Week)],"WIP") -> 0 | AS7: =COUNTIFS(MASTER[Sub Format],$B7,MASTER[Planned (Month) Bucket],AS$2,MASTER[EPC Status (Current Week)],"WIP") -> 0 | AT7: =COUNTIFS(MASTER[Sub Format],$B7,MASTER[Planned (Month) Bucket],AT$2,MASTER[EPC Status (Current Week)],"WIP") -> 0 | AU7: =COUNTIFS(MASTER[Sub Format],$B7,MASTER[Planned (Month) Bucket],AU$2,MASTER[EPC Status (Current Week)],"WIP") -> 0 | AV7: =COUNTIFS(MASTER[Sub Format],$B7,MASTER[Planned (Month) Bucket],AV$2,MASTER[EPC Status (Current Week)],"WIP") -> 0 | AW7: =COUNTIFS(MASTER[Sub Format],$B7,MASTER[Planned (Month) Bucket],AW$2,MASTER[EPC Status (Current Week)],"WIP") -> 0 | AX7: =COUNTIFS(MASTER[Sub Format],$B7,MASTER[Planned (Month) Bucket],AX$2,MASTER[EPC Status (Current Week)],"WIP") -> 0 | ... BH7: =COUNTIFS(MASTER[Sub Format],$B7,MASTER[Planned (Month) Bucket],BH$2,MASTER[EPC Status (Current Week)],"WIP") -> 0 | BI7: =COUNTIFS(MASTER[Sub Format],$B7,MASTER[EPC Status (Current Week)],BI$2) -> 0 | BJ7: =COUNTIFS(MASTER[Sub Format],$B7,MASTER[EPC Status (Current Week)],BJ$2) -> 0 | BK7: =COUNTIFS(MASTER[Sub Format],$B7,MASTER[EPC Status (Current Week)],BK$2) -> 0 | BL7: =COUNTIFS(MASTER[Sub Format],$B7,MASTER[EPC Status (Current Week)],BL$2) -> 0 | BM7: =SUM(BN7:BU7) -> 0 | BN7: =COUNTIFS(MASTER[Sub Format],$B7,MASTER[EPC Status (Current Week)],BN$3) -> 0 | BO7: =COUNTIFS(MASTER[Sub Format],$B7,MASTER[EPC Status (Current Week)],BO$3) -> 0 | BP7: =COUNTIFS(MASTER[Sub Format],$B7,MASTER[EPC Status (Current Week)],BP$3) -> 0 | BQ7: =COUNTIFS(MASTER[Sub Format],$B7,MASTER[EPC Status (Current Week)],BQ$3) -> 0 | BR7: =COUNTIFS(MASTER[Sub Format],$B7,MASTER[EPC Status (Current Week)],BR$3) -> 0 | BS7: =COUNTIFS(MASTER[Sub Format],$B7,MASTER[EPC Status (Current Week)],BS$3) -> 0 | BT7: =COUNTIFS(MASTER[Sub Format],$B7,MASTER[EPC Status (Current Week)],BT$3) -> 0 | BU7: =COUNTIFS(MASTER[Sub Format],$B7,MASTER[EPC Status (Current Week)],BU$3) -> 0
A8: 3 | B8: Compact Digital | C8: NSO | D8: Amit C | E8: 0 | F8: =COUNTIFS(MASTER[Sub Format],$B8,MASTER[EPC Status (Current Week)],$F$3) -> 0 | G8: =COUNTIFS(MASTER[LAUNCHED / YTL],"LAUNCHED",MASTER[Sub Format],$B8,MASTER[EPC Status (Current Week)],"EPC Ready Previous FY") -> 0 | H8: =COUNTIFS(MASTER[LAUNCHED / YTL],"YTL",MASTER[Sub Format],$B8,MASTER[EPC Status (Current Week)],"EPC Ready Previous FY") -> 0 | I8: =COUNTIFS(MASTER[Sub Format],$B8,MASTER[Actual (Month) Bucket],I$3) -> 0 | J8: =COUNTIFS(MASTER[Sub Format],$B8,MASTER[Actual (Month) Bucket],J$3) -> 0 | K8: =COUNTIFS(MASTER[Sub Format],$B8,MASTER[Actual (Month) Bucket],K$3) -> 0 | L8: =SUM(I8:K8) -> 0 | M8: =COUNTIFS(MASTER[Sub Format],$B8,MASTER[Actual (Month) Bucket],M$3) -> 0 | N8: =COUNTIFS(MASTER[Sub Format],$B8,MASTER[Actual (Month) Bucket],N$3) -> 0 | O8: =COUNTIFS(MASTER[Sub Format],$B8,MASTER[Actual (Month) Bucket],O$3) -> 0 | P8: =SUM(M8:O8) -> 0 | Q8: =COUNTIFS(MASTER[Sub Format],$B8,MASTER[Actual (Month) Bucket],Q$3) -> 0 | R8: =COUNTIFS(MASTER[Sub Format],$B8,MASTER[Actual (Month) Bucket],R$3) -> 0 | S8: =COUNTIFS(MASTER[Sub Format],$B8,MASTER[Actual (Month) Bucket],S$3) -> 0 | T8: =SUM(Q8:S8) -> 0 | U8: =COUNTIFS(MASTER[Sub Format],$B8,MASTER[Actual (Month) Bucket],U$3) -> 0 | V8: =COUNTIFS(MASTER[Sub Format],$B8,MASTER[Actual (Month) Bucket],V$3) -> 0 | W8: =COUNTIFS(MASTER[Sub Format],$B8,MASTER[Actual (Month) Bucket],W$3) -> 0 | X8: =SUM(U8:W8) -> 0 | Y8: =L8+P8+T8+X8 -> 0 | Z8: =COUNTIFS(MASTER[LAUNCHED / YTL],"LAUNCHED",MASTER[Sub Format],$B8,MASTER[EPC Status (Current Week)],"EPC Ready") -> 0 | AA8: =COUNTIFS(MASTER[LAUNCHED / YTL],"YTL",MASTER[Sub Format],$B8,MASTER[EPC Status (Current Week)],"EPC Ready") -> 0 | AB8: =COUNTIFS(MASTER[LAUNCHED / YTL],"YTL - Dropped by Business",MASTER[Sub Format],$B8,MASTER[EPC Status (Current Week)],"EPC Ready") -> 0 | AC8: =COUNTIFS(MASTER[EPC Status (Current Week)],"EPC Ready",MASTER[Sub Format],$B8)+COUNTIFS(MASTER[EPC Status (Current Week)],"EPC Ready Previous FY",MASTER[Sub Format],$B8) -> 0 | AD8: =COUNTIFS(MASTER[LAUNCHED / YTL],"LAUNCHED",MASTER[Sub Format],$B8) -> 0 | AE8: =COUNTIFS(MASTER[LAUNCHED / YTL],"YTL",MASTER[Sub Format],$B8) -> 0 | AF8: =COUNTIFS(MASTER[LAUNCHED / YTL],"YTL - Dropped by Business",MASTER[Sub Format],$B8) -> 0 | AG8: =SUM(AQ8:BH8) -> 1 | AH8: =AQ8 -> 0 | AI8: =AR8 -> 0 | AJ8: =AS8 -> 0 | AK8: =AT8 -> 0 | AL8: =AU8 -> 0 | AM8: =AV8 -> 0 | AN8: =AW8 -> 0 | AO8: =AX8 -> 0 | AP8: =AY8 -> 0 | AQ8: =COUNTIFS(MASTER[Sub Format],$B8,MASTER[Planned (Month) Bucket],AQ$2,MASTER[EPC Status (Current Week)],"WIP") -> 0 | AR8: =COUNTIFS(MASTER[Sub Format],$B8,MASTER[Planned (Month) Bucket],AR$2,MASTER[EPC Status (Current Week)],"WIP") -> 0 | AS8: =COUNTIFS(MASTER[Sub Format],$B8,MASTER[Planned (Month) Bucket],AS$2,MASTER[EPC Status (Current Week)],"WIP") -> 0 | AT8: =COUNTIFS(MASTER[Sub Format],$B8,MASTER[Planned (Month) Bucket],AT$2,MASTER[EPC Status (Current Week)],"WIP") -> 0 | AU8: =COUNTIFS(MASTER[Sub Format],$B8,MASTER[Planned (Month) Bucket],AU$2,MASTER[EPC Status (Current Week)],"WIP") -> 0 | AV8: =COUNTIFS(MASTER[Sub Format],$B8,MASTER[Planned (Month) Bucket],AV$2,MASTER[EPC Status (Current Week)],"WIP") -> 0 | AW8: =COUNTIFS(MASTER[Sub Format],$B8,MASTER[Planned (Month) Bucket],AW$2,MASTER[EPC Status (Current Week)],"WIP") -> 0 | AX8: =COUNTIFS(MASTER[Sub Format],$B8,MASTER[Planned (Month) Bucket],AX$2,MASTER[EPC Status (Current Week)],"WIP") -> 0 | ... BH8: =COUNTIFS(MASTER[Sub Format],$B8,MASTER[Planned (Month) Bucket],BH$2,MASTER[EPC Status (Current Week)],"WIP") -> 0 | BI8: =COUNTIFS(MASTER[Sub Format],$B8,MASTER[EPC Status (Current Week)],BI$2) -> 0 | BJ8: =COUNTIFS(MASTER[Sub Format],$B8,MASTER[EPC Status (Current Week)],BJ$2) -> 0 | BK8: =COUNTIFS(MASTER[Sub Format],$B8,MASTER[EPC Status (Current Week)],BK$2) -> 0 | BL8: =COUNTIFS(MASTER[Sub Format],$B8,MASTER[EPC Status (Current Week)],BL$2) -> 0 | BM8: =SUM(BN8:BU8) -> 4 | BN8: =COUNTIFS(MASTER[Sub Format],$B8,MASTER[EPC Status (Current Week)],BN$3) -> 2 | BO8: =COUNTIFS(MASTER[Sub Format],$B8,MASTER[EPC Status (Current Week)],BO$3) -> 0 | BP8: =COUNTIFS(MASTER[Sub Format],$B8,MASTER[EPC Status (Current Week)],BP$3) -> 0 | BQ8: =COUNTIFS(MASTER[Sub Format],$B8,MASTER[EPC Status (Current Week)],BQ$3) -> 0 | BR8: =COUNTIFS(MASTER[Sub Format],$B8,MASTER[EPC Status (Current Week)],BR$3) -> 2 | BS8: =COUNTIFS(MASTER[Sub Format],$B8,MASTER[EPC Status (Current Week)],BS$3) -> 0 | BT8: =COUNTIFS(MASTER[Sub Format],$B8,MASTER[EPC Status (Current Week)],BT$3) -> 0 | BU8: =COUNTIFS(MASTER[Sub Format],$B8,MASTER[EPC Status (Current Week)],BU$3) -> 0
A9: 4 | B9: DMS | E9: 150 | F9: =COUNTIFS(MASTER[Sub Format],$B9,MASTER[EPC Status (Current Week)],$F$3) -> 0 | G9: =COUNTIFS(MASTER[LAUNCHED / YTL],"LAUNCHED",MASTER[Sub Format],$B9,MASTER[EPC Status (Current Week)],"EPC Ready Previous FY") -> 0 | H9: =COUNTIFS(MASTER[LAUNCHED / YTL],"YTL",MASTER[Sub Format],$B9,MASTER[EPC Status (Current Week)],"EPC Ready Previous FY") -> 0 | I9: =COUNTIFS(MASTER[Sub Format],$B9,MASTER[Actual (Month) Bucket],I$3) -> 2 | J9: =COUNTIFS(MASTER[Sub Format],$B9,MASTER[Actual (Month) Bucket],J$3) -> 2 | K9: =COUNTIFS(MASTER[Sub Format],$B9,MASTER[Actual (Month) Bucket],K$3) -> 0 | L9: =SUM(I9:K9) -> 4 | M9: =COUNTIFS(MASTER[Sub Format],$B9,MASTER[Actual (Month) Bucket],M$3) -> 0 | N9: =COUNTIFS(MASTER[Sub Format],$B9,MASTER[Actual (Month) Bucket],N$3) -> 0 | O9: =COUNTIFS(MASTER[Sub Format],$B9,MASTER[Actual (Month) Bucket],O$3) -> 0 | P9: =SUM(M9:O9) -> 0 | Q9: =COUNTIFS(MASTER[Sub Format],$B9,MASTER[Actual (Month) Bucket],Q$3) -> 0 | R9: =COUNTIFS(MASTER[Sub Format],$B9,MASTER[Actual (Month) Bucket],R$3) -> 0 | S9: =COUNTIFS(MASTER[Sub Format],$B9,MASTER[Actual (Month) Bucket],S$3) -> 0 | T9: =SUM(Q9:S9) -> 0 | U9: =COUNTIFS(MASTER[Sub Format],$B9,MASTER[Actual (Month) Bucket],U$3) -> 0 | V9: =COUNTIFS(MASTER[Sub Format],$B9,MASTER[Actual (Month) Bucket],V$3) -> 0 | W9: =COUNTIFS(MASTER[Sub Format],$B9,MASTER[Actual (Month) Bucket],W$3) -> 0 | X9: =SUM(U9:W9) -> 0 | Y9: =L9+P9+T9+X9 -> 4 | Z9: =COUNTIFS(MASTER[LAUNCHED / YTL],"LAUNCHED",MASTER[Sub Format],$B9,MASTER[EPC Status (Current Week)],"EPC Ready") -> 1 | AA9: =COUNTIFS(MASTER[LAUNCHED / YTL],"YTL",MASTER[Sub Format],$B9,MASTER[EPC Status (Current Week)],"EPC Ready") -> 3 | AB9: =COUNTIFS(MASTER[LAUNCHED / YTL],"YTL - Dropped by Business",MASTER[Sub Format],$B9,MASTER[EPC Status (Current Week)],"EPC Ready") -> 0 | AC9: =COUNTIFS(MASTER[EPC Status (Current Week)],"EPC Ready",MASTER[Sub Format],$B9)+COUNTIFS(MASTER[EPC Status (Current Week)],"EPC Ready Previous FY",MASTER[Sub Format],$B9) -> 4 | AD9: =COUNTIFS(MASTER[LAUNCHED / YTL],"LAUNCHED",MASTER[Sub Format],$B9) -> 1 | AE9: =COUNTIFS(MASTER[LAUNCHED / YTL],"YTL",MASTER[Sub Format],$B9) -> 3 | AF9: =COUNTIFS(MASTER[LAUNCHED / YTL],"YTL - Dropped by Business",MASTER[Sub Format],$B9) -> 0 | AG9: =SUM(AQ9:BH9) -> 1 | AH9: =AQ9 -> 0 | AI9: =AR9 -> 0 | AJ9: =AS9 -> 0 | AK9: =AT9 -> 0 | AL9: =AU9 -> 0 | AM9: =AV9 -> 0 | AN9: =AW9 -> 0 | AO9: =AX9 -> 0 | AP9: =AY9 -> 0 | AQ9: =COUNTIFS(MASTER[Sub Format],$B9,MASTER[Planned (Month) Bucket],AQ$2,MASTER[EPC Status (Current Week)],"WIP") -> 0 | AR9: =COUNTIFS(MASTER[Sub Format],$B9,MASTER[Planned (Month) Bucket],AR$2,MASTER[EPC Status (Current Week)],"WIP") -> 0 | AS9: =COUNTIFS(MASTER[Sub Format],$B9,MASTER[Planned (Month) Bucket],AS$2,MASTER[EPC Status (Current Week)],"WIP") -> 0 | AT9: =COUNTIFS(MASTER[Sub Format],$B9,MASTER[Planned (Month) Bucket],AT$2,MASTER[EPC Status (Current Week)],"WIP") -> 0 | AU9: =COUNTIFS(MASTER[Sub Format],$B9,MASTER[Planned (Month) Bucket],AU$2,MASTER[EPC Status (Current Week)],"WIP") -> 0 | AV9: =COUNTIFS(MASTER[Sub Format],$B9,MASTER[Planned (Month) Bucket],AV$2,MASTER[EPC Status (Current Week)],"WIP") -> 0 | AW9: =COUNTIFS(MASTER[Sub Format],$B9,MASTER[Planned (Month) Bucket],AW$2,MASTER[EPC Status (Current Week)],"WIP") -> 0 | AX9: =COUNTIFS(MASTER[Sub Format],$B9,MASTER[Planned (Month) Bucket],AX$2,MASTER[EPC Status (Current Week)],"WIP") -> 0 | ... BH9: =COUNTIFS(MASTER[Sub Format],$B9,MASTER[Planned (Month) Bucket],BH$2,MASTER[EPC Status (Current Week)],"WIP") -> 0 | BI9: =COUNTIFS(MASTER[Sub Format],$B9,MASTER[EPC Status (Current Week)],BI$2) -> 0 | BJ9: =COUNTIFS(MASTER[Sub Format],$B9,MASTER[EPC Status (Current Week)],BJ$2) -> 0 | BK9: =COUNTIFS(MASTER[Sub Format],$B9,MASTER[EPC Status (Current Week)],BK$2) -> 0 | BL9: =COUNTIFS(MASTER[Sub Format],$B9,MASTER[EPC Status (Current Week)],BL$2) -> 0 | BM9: =SUM(BN9:BU9) -> 1 | BN9: =COUNTIFS(MASTER[Sub Format],$B9,MASTER[EPC Status (Current Week)],BN$3) -> 1 | BO9: =COUNTIFS(MASTER[Sub Format],$B9,MASTER[EPC Status (Current Week)],BO$3) -> 0 | BP9: =COUNTIFS(MASTER[Sub Format],$B9,MASTER[EPC Status (Current Week)],BP$3) -> 0 | BQ9: =COUNTIFS(MASTER[Sub Format],$B9,MASTER[EPC Status (Current Week)],BQ$3) -> 0 | BR9: =COUNTIFS(MASTER[Sub Format],$B9,MASTER[EPC Status (Current Week)],BR$3) -> 0 | BS9: =COUNTIFS(MASTER[Sub Format],$B9,MASTER[EPC Status (Current Week)],BS$3) -> 0 | BT9: =COUNTIFS(MASTER[Sub Format],$B9,MASTER[EPC Status (Current Week)],BT$3) -> 0 | BU9: =COUNTIFS(MASTER[Sub Format],$B9,MASTER[EPC Status (Current Week)],BU$3) -> 0
A10: 5 | B10: Digital Bismi | E10: 10 | F10: =COUNTIFS(MASTER[Sub Format],$B10,MASTER[EPC Status (Current Week)],$F$3) -> 0 | G10: =COUNTIFS(MASTER[LAUNCHED / YTL],"LAUNCHED",MASTER[Sub Format],$B10,MASTER[EPC Status (Current Week)],"EPC Ready Previous FY") -> 0 | H10: =COUNTIFS(MASTER[LAUNCHED / YTL],"YTL",MASTER[Sub Format],$B10,MASTER[EPC Status (Current Week)],"EPC Ready Previous FY") -> 0 | I10: =COUNTIFS(MASTER[Sub Format],$B10,MASTER[Actual (Month) Bucket],I$3) -> 0 | J10: =COUNTIFS(MASTER[Sub Format],$B10,MASTER[Actual (Month) Bucket],J$3) -> 0 | K10: =COUNTIFS(MASTER[Sub Format],$B10,MASTER[Actual (Month) Bucket],K$3) -> 0 | L10: =SUM(I10:K10) -> 0 | M10: =COUNTIFS(MASTER[Sub Format],$B10,MASTER[Actual (Month) Bucket],M$3) -> 0 | N10: =COUNTIFS(MASTER[Sub Format],$B10,MASTER[Actual (Month) Bucket],N$3) -> 0 | O10: =COUNTIFS(MASTER[Sub Format],$B10,MASTER[Actual (Month) Bucket],O$3) -> 0 | P10: =SUM(M10:O10) -> 0 | Q10: =COUNTIFS(MASTER[Sub Format],$B10,MASTER[Actual (Month) Bucket],Q$3) -> 0 | R10: =COUNTIFS(MASTER[Sub Format],$B10,MASTER[Actual (Month) Bucket],R$3) -> 0 | S10: =COUNTIFS(MASTER[Sub Format],$B10,MASTER[Actual (Month) Bucket],S$3) -> 0 | T10: =SUM(Q10:S10) -> 0 | U10: =COUNTIFS(MASTER[Sub Format],$B10,MASTER[Actual (Month) Bucket],U$3) -> 0 | V10: =COUNTIFS(MASTER[Sub Format],$B10,MASTER[Actual (Month) Bucket],V$3) -> 0 | W10: =COUNTIFS(MASTER[Sub Format],$B10,MASTER[Actual (Month) Bucket],W$3) -> 0 | X10: =SUM(U10:W10) -> 0 | Y10: =L10+P10+T10+X10 -> 0 | Z10: =COUNTIFS(MASTER[LAUNCHED / YTL],"LAUNCHED",MASTER[Sub Format],$B10,MASTER[EPC Status (Current Week)],"EPC Ready") -> 0 | AA10: =COUNTIFS(MASTER[LAUNCHED / YTL],"YTL",MASTER[Sub Format],$B10,MASTER[EPC Status (Current Week)],"EPC Ready") -> 0 | AB10: =COUNTIFS(MASTER[LAUNCHED / YTL],"YTL - Dropped by Business",MASTER[Sub Format],$B10,MASTER[EPC Status (Current Week)],"EPC Ready") -> 0 | AC10: =COUNTIFS(MASTER[EPC Status (Current Week)],"EPC Ready",MASTER[Sub Format],$B10)+COUNTIFS(MASTER[EPC Status (Current Week)],"EPC Ready Previous FY",MASTER[Sub Format],$B10) -> 0 | AD10: =COUNTIFS(MASTER[LAUNCHED / YTL],"LAUNCHED",MASTER[Sub Format],$B10) -> 0 | AE10: =COUNTIFS(MASTER[LAUNCHED / YTL],"YTL",MASTER[Sub Format],$B10) -> 0 | AF10: =COUNTIFS(MASTER[LAUNCHED / YTL],"YTL - Dropped by Business",MASTER[Sub Format],$B10) -> 0 | AG10: =SUM(AQ10:BH10) -> 1 | AH10: =AQ10 -> 0 | AI10: =AR10 -> 0 | AJ10: =AS10 -> 0 | AK10: =AT10 -> 0 | AL10: =AU10 -> 0 | AM10: =AV10 -> 0 | AN10: =AW10 -> 0 | AO10: =AX10 -> 0 | AP10: =AY10 -> 0 | AQ10: =COUNTIFS(MASTER[Sub Format],$B10,MASTER[Planned (Month) Bucket],AQ$2,MASTER[EPC Status (Current Week)],"WIP") -> 0 | AR10: =COUNTIFS(MASTER[Sub Format],$B10,MASTER[Planned (Month) Bucket],AR$2,MASTER[EPC Status (Current Week)],"WIP") -> 0 | AS10: =COUNTIFS(MASTER[Sub Format],$B10,MASTER[Planned (Month) Bucket],AS$2,MASTER[EPC Status (Current Week)],"WIP") -> 0 | AT10: =COUNTIFS(MASTER[Sub Format],$B10,MASTER[Planned (Month) Bucket],AT$2,MASTER[EPC Status (Current Week)],"WIP") -> 0 | AU10: =COUNTIFS(MASTER[Sub Format],$B10,MASTER[Planned (Month) Bucket],AU$2,MASTER[EPC Status (Current Week)],"WIP") -> 0 | AV10: =COUNTIFS(MASTER[Sub Format],$B10,MASTER[Planned (Month) Bucket],AV$2,MASTER[EPC Status (Current Week)],"WIP") -> 0 | AW10: =COUNTIFS(MASTER[Sub Format],$B10,MASTER[Planned (Month) Bucket],AW$2,MASTER[EPC Status (Current Week)],"WIP") -> 0 | AX10: =COUNTIFS(MASTER[Sub Format],$B10,MASTER[Planned (Month) Bucket],AX$2,MASTER[EPC Status (Current Week)],"WIP") -> 0 | ... BH10: =COUNTIFS(MASTER[Sub Format],$B10,MASTER[Planned (Month) Bucket],BH$2,MASTER[EPC Status (Current Week)],"WIP") -> 0 | BI10: =COUNTIFS(MASTER[Sub Format],$B10,MASTER[EPC Status (Current Week)],BI$2) -> 0 | BJ10: =COUNTIFS(MASTER[Sub Format],$B10,MASTER[EPC Status (Current Week)],BJ$2) -> 0 | BK10: =COUNTIFS(MASTER[Sub Format],$B10,MASTER[EPC Status (Current Week)],BK$2) -> 0 | BL10: =COUNTIFS(MASTER[Sub Format],$B10,MASTER[EPC Status (Current Week)],BL$2) -> 0 | BM10: =SUM(BN10:BU10) -> 0 | BN10: =COUNTIFS(MASTER[Sub Format],$B10,MASTER[EPC Status (Current Week)],BN$3) -> 0 | BO10: =COUNTIFS(MASTER[Sub Format],$B10,MASTER[EPC Status (Current Week)],BO$3) -> 0 | BP10: =COUNTIFS(MASTER[Sub Format],$B10,MASTER[EPC Status (Current Week)],BP$3) -> 0 | BQ10: =COUNTIFS(MASTER[Sub Format],$B10,MASTER[EPC Status (Current Week)],BQ$3) -> 0 | BR10: =COUNTIFS(MASTER[Sub Format],$B10,MASTER[EPC Status (Current Week)],BR$3) -> 0 | BS10: =COUNTIFS(MASTER[Sub Format],$B10,MASTER[EPC Status (Current Week)],BS$3) -> 0 | BT10: =COUNTIFS(MASTER[Sub Format],$B10,MASTER[EPC Status (Current Week)],BT$3) -> 0 | BU10: =COUNTIFS(MASTER[Sub Format],$B10,MASTER[EPC Status (Current Week)],BU$3) -> 0
A11: 6 | B11: Digital 3K | C11: NSO | D11: Amit C | E11: 0 | F11: =COUNTIFS(MASTER[Sub Format],$B11,MASTER[EPC Status (Current Week)],$F$3) -> 0 | G11: =COUNTIFS(MASTER[LAUNCHED / YTL],"LAUNCHED",MASTER[Sub Format],$B11,MASTER[EPC Status (Current Week)],"EPC Ready Previous FY") -> 0 | H11: =COUNTIFS(MASTER[LAUNCHED / YTL],"YTL",MASTER[Sub Format],$B11,MASTER[EPC Status (Current Week)],"EPC Ready Previous FY") -> 0 | I11: =COUNTIFS(MASTER[Sub Format],$B11,MASTER[Actual (Month) Bucket],I$3) -> 0 | J11: =COUNTIFS(MASTER[Sub Format],$B11,MASTER[Actual (Month) Bucket],J$3) -> 0 | K11: =COUNTIFS(MASTER[Sub Format],$B11,MASTER[Actual (Month) Bucket],K$3) -> 0 | L11: =SUM(I11:K11) -> 0 | M11: =COUNTIFS(MASTER[Sub Format],$B11,MASTER[Actual (Month) Bucket],M$3) -> 0 | N11: =COUNTIFS(MASTER[Sub Format],$B11,MASTER[Actual (Month) Bucket],N$3) -> 0 | O11: =COUNTIFS(MASTER[Sub Format],$B11,MASTER[Actual (Month) Bucket],O$3) -> 0 | P11: =SUM(M11:O11) -> 0 | Q11: =COUNTIFS(MASTER[Sub Format],$B11,MASTER[Actual (Month) Bucket],Q$3) -> 0 | R11: =COUNTIFS(MASTER[Sub Format],$B11,MASTER[Actual (Month) Bucket],R$3) -> 0 | S11: =COUNTIFS(MASTER[Sub Format],$B11,MASTER[Actual (Month) Bucket],S$3) -> 0 | T11: =SUM(Q11:S11) -> 0 | U11: =COUNTIFS(MASTER[Sub Format],$B11,MASTER[Actual (Month) Bucket],U$3) -> 0 | V11: =COUNTIFS(MASTER[Sub Format],$B11,MASTER[Actual (Month) Bucket],V$3) -> 0 | W11: =COUNTIFS(MASTER[Sub Format],$B11,MASTER[Actual (Month) Bucket],W$3) -> 0 | X11: =SUM(U11:W11) -> 0 | Y11: =L11+P11+T11+X11 -> 0 | Z11: =COUNTIFS(MASTER[LAUNCHED / YTL],"LAUNCHED",MASTER[Sub Format],$B11,MASTER[EPC Status (Current Week)],"EPC Ready") -> 0 | AA11: =COUNTIFS(MASTER[LAUNCHED / YTL],"YTL",MASTER[Sub Format],$B11,MASTER[EPC Status (Current Week)],"EPC Ready") -> 0 | AB11: =COUNTIFS(MASTER[LAUNCHED / YTL],"YTL - Dropped by Business",MASTER[Sub Format],$B11,MASTER[EPC Status (Current Week)],"EPC Ready") -> 0 | AC11: =COUNTIFS(MASTER[EPC Status (Current Week)],"EPC Ready",MASTER[Sub Format],$B11)+COUNTIFS(MASTER[EPC Status (Current Week)],"EPC Ready Previous FY",MASTER[Sub Format],$B11) -> 0 | AD11: =COUNTIFS(MASTER[LAUNCHED / YTL],"LAUNCHED",MASTER[Sub Format],$B11) -> 0 | AE11: =COUNTIFS(MASTER[LAUNCHED / YTL],"YTL",MASTER[Sub Format],$B11) -> 0 | AF11: =COUNTIFS(MASTER[LAUNCHED / YTL],"YTL - Dropped by Business",MASTER[Sub Format],$B11) -> 0 | AG11: =SUM(AQ11:BH11) -> 0 | AH11: =AQ11 -> 0 | AI11: =AR11 -> 0 | AJ11: =AS11 -> 0 | AK11: =AT11 -> 0 | AL11: =AU11 -> 0 | AM11: =AV11 -> 0 | AN11: =AW11 -> 0 | AO11: =AX11 -> 0 | AP11: =AY11 -> 0 | AQ11: =COUNTIFS(MASTER[Sub Format],$B11,MASTER[Planned (Month) Bucket],AQ$2,MASTER[EPC Status (Current Week)],"WIP") -> 0 | AR11: =COUNTIFS(MASTER[Sub Format],$B11,MASTER[Planned (Month) Bucket],AR$2,MASTER[EPC Status (Current Week)],"WIP") -> 0 | AS11: =COUNTIFS(MASTER[Sub Format],$B11,MASTER[Planned (Month) Bucket],AS$2,MASTER[EPC Status (Current Week)],"WIP") -> 0 | AT11: =COUNTIFS(MASTER[Sub Format],$B11,MASTER[Planned (Month) Bucket],AT$2,MASTER[EPC Status (Current Week)],"WIP") -> 0 | AU11: =COUNTIFS(MASTER[Sub Format],$B11,MASTER[Planned (Month) Bucket],AU$2,MASTER[EPC Status (Current Week)],"WIP") -> 0 | AV11: =COUNTIFS(MASTER[Sub Format],$B11,MASTER[Planned (Month) Bucket],AV$2,MASTER[EPC Status (Current Week)],"WIP") -> 0 | AW11: =COUNTIFS(MASTER[Sub Format],$B11,MASTER[Planned (Month) Bucket],AW$2,MASTER[EPC Status (Current Week)],"WIP") -> 0 | AX11: =COUNTIFS(MASTER[Sub Format],$B11,MASTER[Planned (Month) Bucket],AX$2,MASTER[EPC Status (Current Week)],"WIP") -> 0 | ... BH11: =COUNTIFS(MASTER[Sub Format],$B11,MASTER[Planned (Month) Bucket],BH$2,MASTER[EPC Status (Current Week)],"WIP") -> 0 | BI11: =COUNTIFS(MASTER[Sub Format],$B11,MASTER[EPC Status (Current Week)],BI$2) -> 0 | BJ11: =COUNTIFS(MASTER[Sub Format],$B11,MASTER[EPC Status (Current Week)],BJ$2) -> 0 | BK11: =COUNTIFS(MASTER[Sub Format],$B11,MASTER[EPC Status (Current Week)],BK$2) -> 0 | BL11: =COUNTIFS(MASTER[Sub Format],$B11,MASTER[EPC Status (Current Week)],BL$2) -> 0 | BM11: =SUM(BN11:BU11) -> 1 | BN11: =COUNTIFS(MASTER[Sub Format],$B11,MASTER[EPC Status (Current Week)],BN$3) -> 0 | BO11: =COUNTIFS(MASTER[Sub Format],$B11,MASTER[EPC Status (Current Week)],BO$3) -> 0 | BP11: =COUNTIFS(MASTER[Sub Format],$B11,MASTER[EPC Status (Current Week)],BP$3) -> 0 | BQ11: =COUNTIFS(MASTER[Sub Format],$B11,MASTER[EPC Status (Current Week)],BQ$3) -> 0 | BR11: =COUNTIFS(MASTER[Sub Format],$B11,MASTER[EPC Status (Current Week)],BR$3) -> 1 | BS11: =COUNTIFS(MASTER[Sub Format],$B11,MASTER[EPC Status (Current Week)],BS$3) -> 0 | BT11: =COUNTIFS(MASTER[Sub Format],$B11,MASTER[EPC Status (Current Week)],BT$3) -> 0 | BU11: =COUNTIFS(MASTER[Sub Format],$B11,MASTER[EPC Status (Current Week)],BU$3) -> 0
A12: 7 | B12: Maintenance & Service Location (MSL) | C12: NSO | D12: Amit C | E12: 0 | F12: =COUNTIFS(MASTER[Sub Format],$B12,MASTER[EPC Status (Current Week)],$F$3) -> 0 | G12: =COUNTIFS(MASTER[LAUNCHED / YTL],"LAUNCHED",MASTER[Sub Format],$B12,MASTER[EPC Status (Current Week)],"EPC Ready Previous FY") -> 0 | H12: =COUNTIFS(MASTER[LAUNCHED / YTL],"YTL",MASTER[Sub Format],$B12,MASTER[EPC Status (Current Week)],"EPC Ready Previous FY") -> 0 | I12: =COUNTIFS(MASTER[Sub Format],$B12,MASTER[Actual (Month) Bucket],I$3) -> 0 | J12: =COUNTIFS(MASTER[Sub Format],$B12,MASTER[Actual (Month) Bucket],J$3) -> 0 | K12: =COUNTIFS(MASTER[Sub Format],$B12,MASTER[Actual (Month) Bucket],K$3) -> 0 | L12: =SUM(I12:K12) -> 0 | M12: =COUNTIFS(MASTER[Sub Format],$B12,MASTER[Actual (Month) Bucket],M$3) -> 0 | N12: =COUNTIFS(MASTER[Sub Format],$B12,MASTER[Actual (Month) Bucket],N$3) -> 0 | O12: =COUNTIFS(MASTER[Sub Format],$B12,MASTER[Actual (Month) Bucket],O$3) -> 0 | P12: =SUM(M12:O12) -> 0 | Q12: =COUNTIFS(MASTER[Sub Format],$B12,MASTER[Actual (Month) Bucket],Q$3) -> 0 | R12: =COUNTIFS(MASTER[Sub Format],$B12,MASTER[Actual (Month) Bucket],R$3) -> 0 | S12: =COUNTIFS(MASTER[Sub Format],$B12,MASTER[Actual (Month) Bucket],S$3) -> 0 | T12: =SUM(Q12:S12) -> 0 | U12: =COUNTIFS(MASTER[Sub Format],$B12,MASTER[Actual (Month) Bucket],U$3) -> 0 | V12: =COUNTIFS(MASTER[Sub Format],$B12,MASTER[Actual (Month) Bucket],V$3) -> 0 | W12: =COUNTIFS(MASTER[Sub Format],$B12,MASTER[Actual (Month) Bucket],W$3) -> 0 | X12: =SUM(U12:W12) -> 0 | Y12: =L12+P12+T12+X12 -> 0 | Z12: =COUNTIFS(MASTER[LAUNCHED / YTL],"LAUNCHED",MASTER[Sub Format],$B12,MASTER[EPC Status (Current Week)],"EPC Ready") -> 0 | AA12: =COUNTIFS(MASTER[LAUNCHED / YTL],"YTL",MASTER[Sub Format],$B12,MASTER[EPC Status (Current Week)],"EPC Ready") -> 0 | AB12: =COUNTIFS(MASTER[LAUNCHED / YTL],"YTL - Dropped by Business",MASTER[Sub Format],$B12,MASTER[EPC Status (Current Week)],"EPC Ready") -> 0 | AC12: =COUNTIFS(MASTER[EPC Status (Current Week)],"EPC Ready",MASTER[Sub Format],$B12)+COUNTIFS(MASTER[EPC Status (Current Week)],"EPC Ready Previous FY",MASTER[Sub Format],$B12) -> 0 | AD12: =COUNTIFS(MASTER[LAUNCHED / YTL],"LAUNCHED",MASTER[Sub Format],$B12) -> 0 | AE12: =COUNTIFS(MASTER[LAUNCHED / YTL],"YTL",MASTER[Sub Format],$B12) -> 0 | AF12: =COUNTIFS(MASTER[LAUNCHED / YTL],"YTL - Dropped by Business",MASTER[Sub Format],$B12) -> 0 | AG12: =SUM(AQ12:BH12) -> 0 | AH12: =AQ12 -> 0 | AI12: =AR12 -> 0 | AJ12: =AS12 -> 0 | AK12: =AT12 -> 0 | AL12: =AU12 -> 0 | AM12: =AV12 -> 0 | AN12: =AW12 -> 0 | AO12: =AX12 -> 0 | AP12: =AY12 -> 0 | AQ12: =COUNTIFS(MASTER[Sub Format],$B12,MASTER[Planned (Month) Bucket],AQ$2,MASTER[EPC Status (Current Week)],"WIP") -> 0 | AR12: =COUNTIFS(MASTER[Sub Format],$B12,MASTER[Planned (Month) Bucket],AR$2,MASTER[EPC Status (Current Week)],"WIP") -> 0 | AS12: =COUNTIFS(MASTER[Sub Format],$B12,MASTER[Planned (Month) Bucket],AS$2,MASTER[EPC Status (Current Week)],"WIP") -> 0 | AT12: =COUNTIFS(MASTER[Sub Format],$B12,MASTER[Planned (Month) Bucket],AT$2,MASTER[EPC Status (Current Week)],"WIP") -> 0 | AU12: =COUNTIFS(MASTER[Sub Format],$B12,MASTER[Planned (Month) Bucket],AU$2,MASTER[EPC Status (Current Week)],"WIP") -> 0 | AV12: =COUNTIFS(MASTER[Sub Format],$B12,MASTER[Planned (Month) Bucket],AV$2,MASTER[EPC Status (Current Week)],"WIP") -> 0 | AW12: =COUNTIFS(MASTER[Sub Format],$B12,MASTER[Planned (Month) Bucket],AW$2,MASTER[EPC Status (Current Week)],"WIP") -> 0 | AX12: =COUNTIFS(MASTER[Sub Format],$B12,MASTER[Planned (Month) Bucket],AX$2,MASTER[EPC Status (Current Week)],"WIP") -> 0 | ... BH12: =COUNTIFS(MASTER[Sub Format],$B12,MASTER[Planned (Month) Bucket],BH$2,MASTER[EPC Status (Current Week)],"WIP") -> 0 | BI12: =COUNTIFS(MASTER[Sub Format],$B12,MASTER[EPC Status (Current Week)],BI$2) -> 0 | BJ12: =COUNTIFS(MASTER[Sub Format],$B12,MASTER[EPC Status (Current Week)],BJ$2) -> 0 | BK12: =COUNTIFS(MASTER[Sub Format],$B12,MASTER[EPC Status (Current Week)],BK$2) -> 0 | BL12: =COUNTIFS(MASTER[Sub Format],$B12,MASTER[EPC Status (Current Week)],BL$2) -> 0 | BM12: =SUM(BN12:BU12) -> 0 | BN12: =COUNTIFS(MASTER[Sub Format],$B12,MASTER[EPC Status (Current Week)],BN$3) -> 0 | BO12: =COUNTIFS(MASTER[Sub Format],$B12,MASTER[EPC Status (Current Week)],BO$3) -> 0 | BP12: =COUNTIFS(MASTER[Sub Format],$B12,MASTER[EPC Status (Current Week)],BP$3) -> 0 | BQ12: =COUNTIFS(MASTER[Sub Format],$B12,MASTER[EPC Status (Current Week)],BQ$3) -> 0 | BR12: =COUNTIFS(MASTER[Sub Format],$B12,MASTER[EPC Status (Current Week)],BR$3) -> 0 | BS12: =COUNTIFS(MASTER[Sub Format],$B12,MASTER[EPC Status (Current Week)],BS$3) -> 0 | BT12: =COUNTIFS(MASTER[Sub Format],$B12,MASTER[EPC Status (Current Week)],BT$3) -> 0 | BU12: =COUNTIFS(MASTER[Sub Format],$B12,MASTER[EPC Status (Current Week)],BU$3) -> 0
A13: 8 | B13: RESQ | E13: 0 | F13: =COUNTIFS(MASTER[Sub Format],$B13,MASTER[EPC Status (Current Week)],$F$3) -> 0 | G13: =COUNTIFS(MASTER[LAUNCHED / YTL],"LAUNCHED",MASTER[Sub Format],$B13,MASTER[EPC Status (Current Week)],"EPC Ready Previous FY") -> 0 | H13: =COUNTIFS(MASTER[LAUNCHED / YTL],"YTL",MASTER[Sub Format],$B13,MASTER[EPC Status (Current Week)],"EPC Ready Previous FY") -> 0 | I13: =COUNTIFS(MASTER[Sub Format],$B13,MASTER[Actual (Month) Bucket],I$3) -> 1 | J13: =COUNTIFS(MASTER[Sub Format],$B13,MASTER[Actual (Month) Bucket],J$3) -> 0 | K13: =COUNTIFS(MASTER[Sub Format],$B13,MASTER[Actual (Month) Bucket],K$3) -> 0 | L13: =SUM(I13:K13) -> 1 | M13: =COUNTIFS(MASTER[Sub Format],$B13,MASTER[Actual (Month) Bucket],M$3) -> 0 | N13: =COUNTIFS(MASTER[Sub Format],$B13,MASTER[Actual (Month) Bucket],N$3) -> 0 | O13: =COUNTIFS(MASTER[Sub Format],$B13,MASTER[Actual (Month) Bucket],O$3) -> 0 | P13: =SUM(M13:O13) -> 0 | Q13: =COUNTIFS(MASTER[Sub Format],$B13,MASTER[Actual (Month) Bucket],Q$3) -> 0 | R13: =COUNTIFS(MASTER[Sub Format],$B13,MASTER[Actual (Month) Bucket],R$3) -> 0 | S13: =COUNTIFS(MASTER[Sub Format],$B13,MASTER[Actual (Month) Bucket],S$3) -> 0 | T13: =SUM(Q13:S13) -> 0 | U13: =COUNTIFS(MASTER[Sub Format],$B13,MASTER[Actual (Month) Bucket],U$3) -> 0 | V13: =COUNTIFS(MASTER[Sub Format],$B13,MASTER[Actual (Month) Bucket],V$3) -> 0 | W13: =COUNTIFS(MASTER[Sub Format],$B13,MASTER[Actual (Month) Bucket],W$3) -> 0 | X13: =SUM(U13:W13) -> 0 | Y13: =L13+P13+T13+X13 -> 1 | Z13: =COUNTIFS(MASTER[LAUNCHED / YTL],"LAUNCHED",MASTER[Sub Format],$B13,MASTER[EPC Status (Current Week)],"EPC Ready") -> 0 | AA13: =COUNTIFS(MASTER[LAUNCHED / YTL],"YTL",MASTER[Sub Format],$B13,MASTER[EPC Status (Current Week)],"EPC Ready") -> 1 | AB13: =COUNTIFS(MASTER[LAUNCHED / YTL],"YTL - Dropped by Business",MASTER[Sub Format],$B13,MASTER[EPC Status (Current Week)],"EPC Ready") -> 0 | AC13: =COUNTIFS(MASTER[EPC Status (Current Week)],"EPC Ready",MASTER[Sub Format],$B13)+COUNTIFS(MASTER[EPC Status (Current Week)],"EPC Ready Previous FY",MASTER[Sub Format],$B13) -> 1 | AD13: =COUNTIFS(MASTER[LAUNCHED / YTL],"LAUNCHED",MASTER[Sub Format],$B13) -> 0 | AE13: =COUNTIFS(MASTER[LAUNCHED / YTL],"YTL",MASTER[Sub Format],$B13) -> 1 | AF13: =COUNTIFS(MASTER[LAUNCHED / YTL],"YTL - Dropped by Business",MASTER[Sub Format],$B13) -> 0 | AG13: =SUM(AQ13:BH13) -> 0 | AH13: =AQ13 -> 0 | AI13: =AR13 -> 0 | AJ13: =AS13 -> 0 | AK13: =AT13 -> 0 | AL13: =AU13 -> 0 | AM13: =AV13 -> 0 | AN13: =AW13 -> 0 | AO13: =AX13 -> 0 | AP13: =AY13 -> 0 | AQ13: =COUNTIFS(MASTER[Sub Format],$B13,MASTER[Planned (Month) Bucket],AQ$2,MASTER[EPC Status (Current Week)],"WIP") -> 0 | AR13: =COUNTIFS(MASTER[Sub Format],$B13,MASTER[Planned (Month) Bucket],AR$2,MASTER[EPC Status (Current Week)],"WIP") -> 0 | AS13: =COUNTIFS(MASTER[Sub Format],$B13,MASTER[Planned (Month) Bucket],AS$2,MASTER[EPC Status (Current Week)],"WIP") -> 0 | AT13: =COUNTIFS(MASTER[Sub Format],$B13,MASTER[Planned (Month) Bucket],AT$2,MASTER[EPC Status (Current Week)],"WIP") -> 0 | AU13: =COUNTIFS(MASTER[Sub Format],$B13,MASTER[Planned (Month) Bucket],AU$2,MASTER[EPC Status (Current Week)],"WIP") -> 0 | AV13: =COUNTIFS(MASTER[Sub Format],$B13,MASTER[Planned (Month) Bucket],AV$2,MASTER[EPC Status (Current Week)],"WIP") -> 0 | AW13: =COUNTIFS(MASTER[Sub Format],$B13,MASTER[Planned (Month) Bucket],AW$2,MASTER[EPC Status (Current Week)],"WIP") -> 0 | AX13: =COUNTIFS(MASTER[Sub Format],$B13,MASTER[Planned (Month) Bucket],AX$2,MASTER[EPC Status (Current Week)],"WIP") -> 0 | ... BH13: =COUNTIFS(MASTER[Sub Format],$B13,MASTER[Planned (Month) Bucket],BH$2,MASTER[EPC Status (Current Week)],"WIP") -> 0 | BI13: =COUNTIFS(MASTER[Sub Format],$B13,MASTER[EPC Status (Current Week)],BI$2) -> 0 | BJ13: =COUNTIFS(MASTER[Sub Format],$B13,MASTER[EPC Status (Current Week)],BJ$2) -> 0 | BK13: =COUNTIFS(MASTER[Sub Format],$B13,MASTER[EPC Status (Current Week)],BK$2) -> 0 | BL13: =COUNTIFS(MASTER[Sub Format],$B13,MASTER[EPC Status (Current Week)],BL$2) -> 0 | BM13: =SUM(BN13:BU13) -> 0 | BN13: =COUNTIFS(MASTER[Sub Format],$B13,MASTER[EPC Status (Current Week)],BN$3) -> 0 | BO13: =COUNTIFS(MASTER[Sub Format],$B13,MASTER[EPC Status (Current Week)],BO$3) -> 0 | BP13: =COUNTIFS(MASTER[Sub Format],$B13,MASTER[EPC Status (Current Week)],BP$3) -> 0 | BQ13: =COUNTIFS(MASTER[Sub Format],$B13,MASTER[EPC Status (Current Week)],BQ$3) -> 0 | BR13: =COUNTIFS(MASTER[Sub Format],$B13,MASTER[EPC Status (Current Week)],BR$3) -> 0 | BS13: =COUNTIFS(MASTER[Sub Format],$B13,MASTER[EPC Status (Current Week)],BS$3) -> 0 | BT13: =COUNTIFS(MASTER[Sub Format],$B13,MASTER[EPC Status (Current Week)],BT$3) -> 0 | BU13: =COUNTIFS(MASTER[Sub Format],$B13,MASTER[EPC Status (Current Week)],BU$3) -> 0
A14: 8 | B14: Digital - Refit | C14: Refit | D14: Amit C | E14: 89 | F14: =COUNTIFS(MASTER[Sub Format],$B14,MASTER[EPC Status (Current Week)],$F$3) -> 2 | G14: =COUNTIFS(MASTER[LAUNCHED / YTL],"LAUNCHED",MASTER[Sub Format],$B14,MASTER[EPC Status (Current Week)],"EPC Ready Previous FY") -> 1 | H14: =COUNTIFS(MASTER[LAUNCHED / YTL],"YTL",MASTER[Sub Format],$B14,MASTER[EPC Status (Current Week)],"EPC Ready Previous FY") -> 1 | I14: =COUNTIFS(MASTER[Sub Format],$B14,MASTER[Actual (Month) Bucket],I$3) -> 5 | J14: =COUNTIFS(MASTER[Sub Format],$B14,MASTER[Actual (Month) Bucket],J$3) -> 1 | K14: =COUNTIFS(MASTER[Sub Format],$B14,MASTER[Actual (Month) Bucket],K$3) -> 0 | L14: =SUM(I14:K14) -> 6 | M14: =COUNTIFS(MASTER[Sub Format],$B14,MASTER[Actual (Month) Bucket],M$3) -> 0 | N14: =COUNTIFS(MASTER[Sub Format],$B14,MASTER[Actual (Month) Bucket],N$3) -> 0 | O14: =COUNTIFS(MASTER[Sub Format],$B14,MASTER[Actual (Month) Bucket],O$3) -> 0 | P14: =SUM(M14:O14) -> 0 | Q14: =COUNTIFS(MASTER[Sub Format],$B14,MASTER[Actual (Month) Bucket],Q$3) -> 0 | R14: =COUNTIFS(MASTER[Sub Format],$B14,MASTER[Actual (Month) Bucket],R$3) -> 0 | S14: =COUNTIFS(MASTER[Sub Format],$B14,MASTER[Actual (Month) Bucket],S$3) -> 0 | T14: =SUM(Q14:S14) -> 0 | U14: =COUNTIFS(MASTER[Sub Format],$B14,MASTER[Actual (Month) Bucket],U$3) -> 0 | V14: =COUNTIFS(MASTER[Sub Format],$B14,MASTER[Actual (Month) Bucket],V$3) -> 0 | W14: =COUNTIFS(MASTER[Sub Format],$B14,MASTER[Actual (Month) Bucket],W$3) -> 0 | X14: =SUM(U14:W14) -> 0 | Y14: =L14+P14+T14+X14 -> 6 | Z14: =COUNTIFS(MASTER[LAUNCHED / YTL],"LAUNCHED",MASTER[Sub Format],$B14,MASTER[EPC Status (Current Week)],"EPC Ready") -> 2 | AA14: =COUNTIFS(MASTER[LAUNCHED / YTL],"YTL",MASTER[Sub Format],$B14,MASTER[EPC Status (Current Week)],"EPC Ready") -> 4 | AB14: =COUNTIFS(MASTER[LAUNCHED / YTL],"YTL - Dropped by Business",MASTER[Sub Format],$B14,MASTER[EPC Status (Current Week)],"EPC Ready") -> 0 | AC14: =COUNTIFS(MASTER[EPC Status (Current Week)],"EPC Ready",MASTER[Sub Format],$B14)+COUNTIFS(MASTER[EPC Status (Current Week)],"EPC Ready Previous FY",MASTER[Sub Format],$B14) -> 8 | AD14: =COUNTIFS(MASTER[LAUNCHED / YTL],"LAUNCHED",MASTER[Sub Format],$B14) -> 3 | AE14: =COUNTIFS(MASTER[LAUNCHED / YTL],"YTL",MASTER[Sub Format],$B14) -> 5 | AF14: =COUNTIFS(MASTER[LAUNCHED / YTL],"YTL - Dropped by Business",MASTER[Sub Format],$B14) -> 0 | AG14: =SUM(AQ14:BH14) -> 4 | AH14: =AQ14 -> 0 | AI14: =AR14 -> 0 | AJ14: =AS14 -> 0 | AK14: =AT14 -> 0 | AL14: =AU14 -> 0 | AM14: =AV14 -> 0 | AN14: =AW14 -> 0 | AO14: =AX14 -> 0 | AP14: =AY14 -> 0 | AQ14: =COUNTIFS(MASTER[Sub Format],$B14,MASTER[Planned (Month) Bucket],AQ$2,MASTER[EPC Status (Current Week)],"WIP") -> 0 | AR14: =COUNTIFS(MASTER[Sub Format],$B14,MASTER[Planned (Month) Bucket],AR$2,MASTER[EPC Status (Current Week)],"WIP") -> 0 | AS14: =COUNTIFS(MASTER[Sub Format],$B14,MASTER[Planned (Month) Bucket],AS$2,MASTER[EPC Status (Current Week)],"WIP") -> 0 | AT14: =COUNTIFS(MASTER[Sub Format],$B14,MASTER[Planned (Month) Bucket],AT$2,MASTER[EPC Status (Current Week)],"WIP") -> 0 | AU14: =COUNTIFS(MASTER[Sub Format],$B14,MASTER[Planned (Month) Bucket],AU$2,MASTER[EPC Status (Current Week)],"WIP") -> 0 | AV14: =COUNTIFS(MASTER[Sub Format],$B14,MASTER[Planned (Month) Bucket],AV$2,MASTER[EPC Status (Current Week)],"WIP") -> 0 | AW14: =COUNTIFS(MASTER[Sub Format],$B14,MASTER[Planned (Month) Bucket],AW$2,MASTER[EPC Status (Current Week)],"WIP") -> 0 | AX14: =COUNTIFS(MASTER[Sub Format],$B14,MASTER[Planned (Month) Bucket],AX$2,MASTER[EPC Status (Current Week)],"WIP") -> 0 | ... BH14: =COUNTIFS(MASTER[Sub Format],$B14,MASTER[Planned (Month) Bucket],BH$2,MASTER[EPC Status (Current Week)],"WIP") -> 0 | BI14: =COUNTIFS(MASTER[Sub Format],$B14,MASTER[EPC Status (Current Week)],BI$2) -> 0 | BJ14: =COUNTIFS(MASTER[Sub Format],$B14,MASTER[EPC Status (Current Week)],BJ$2) -> 0 | BK14: =COUNTIFS(MASTER[Sub Format],$B14,MASTER[EPC Status (Current Week)],BK$2) -> 0 | BL14: =COUNTIFS(MASTER[Sub Format],$B14,MASTER[EPC Status (Current Week)],BL$2) -> 0 | BM14: =SUM(BN14:BU14) -> 4 | BN14: =COUNTIFS(MASTER[Sub Format],$B14,MASTER[EPC Status (Current Week)],BN$3) -> 4 | BO14: =COUNTIFS(MASTER[Sub Format],$B14,MASTER[EPC Status (Current Week)],BO$3) -> 0 | BP14: =COUNTIFS(MASTER[Sub Format],$B14,MASTER[EPC Status (Current Week)],BP$3) -> 0 | BQ14: =COUNTIFS(MASTER[Sub Format],$B14,MASTER[EPC Status (Current Week)],BQ$3) -> 0 | BR14: =COUNTIFS(MASTER[Sub Format],$B14,MASTER[EPC Status (Current Week)],BR$3) -> 0 | BS14: =COUNTIFS(MASTER[Sub Format],$B14,MASTER[EPC Status (Current Week)],BS$3) -> 0 | BT14: =COUNTIFS(MASTER[Sub Format],$B14,MASTER[EPC Status (Current Week)],BT$3) -> 0 | BU14: =COUNTIFS(MASTER[Sub Format],$B14,MASTER[EPC Status (Current Week)],BU$3) -> 0
A15: 9 | B15: MJS to DMS Refit | C15: Refit | D15: Amit C | E15: 700 | F15: =COUNTIFS(MASTER[Sub Format],$B15,MASTER[EPC Status (Current Week)],$F$3) -> 0 | G15: =COUNTIFS(MASTER[LAUNCHED / YTL],"LAUNCHED",MASTER[Sub Format],$B15,MASTER[EPC Status (Current Week)],"EPC Ready Previous FY") -> 0 | H15: =COUNTIFS(MASTER[LAUNCHED / YTL],"YTL",MASTER[Sub Format],$B15,MASTER[EPC Status (Current Week)],"EPC Ready Previous FY") -> 0 | I15: =COUNTIFS(MASTER[Sub Format],$B15,MASTER[Actual (Month) Bucket],I$3) -> 0 | J15: =COUNTIFS(MASTER[Sub Format],$B15,MASTER[Actual (Month) Bucket],J$3) -> 0 | K15: =COUNTIFS(MASTER[Sub Format],$B15,MASTER[Actual (Month) Bucket],K$3) -> 0 | L15: =SUM(I15:K15) -> 0 | M15: =COUNTIFS(MASTER[Sub Format],$B15,MASTER[Actual (Month) Bucket],M$3) -> 0 | N15: =COUNTIFS(MASTER[Sub Format],$B15,MASTER[Actual (Month) Bucket],N$3) -> 0 | O15: =COUNTIFS(MASTER[Sub Format],$B15,MASTER[Actual (Month) Bucket],O$3) -> 0 | P15: =SUM(M15:O15) -> 0 | Q15: =COUNTIFS(MASTER[Sub Format],$B15,MASTER[Actual (Month) Bucket],Q$3) -> 0 | R15: =COUNTIFS(MASTER[Sub Format],$B15,MASTER[Actual (Month) Bucket],R$3) -> 0 | S15: =COUNTIFS(MASTER[Sub Format],$B15,MASTER[Actual (Month) Bucket],S$3) -> 0 | T15: =SUM(Q15:S15) -> 0 | U15: =COUNTIFS(MASTER[Sub Format],$B15,MASTER[Actual (Month) Bucket],U$3) -> 0 | V15: =COUNTIFS(MASTER[Sub Format],$B15,MASTER[Actual (Month) Bucket],V$3) -> 0 | W15: =COUNTIFS(MASTER[Sub Format],$B15,MASTER[Actual (Month) Bucket],W$3) -> 0 | X15: =SUM(U15:W15) -> 0 | Y15: =L15+P15+T15+X15 -> 0 | Z15: =COUNTIFS(MASTER[LAUNCHED / YTL],"LAUNCHED",MASTER[Sub Format],$B15,MASTER[EPC Status (Current Week)],"EPC Ready") -> 0 | AA15: =COUNTIFS(MASTER[LAUNCHED / YTL],"YTL",MASTER[Sub Format],$B15,MASTER[EPC Status (Current Week)],"EPC Ready") -> 0 | AB15: =COUNTIFS(MASTER[LAUNCHED / YTL],"YTL - Dropped by Business",MASTER[Sub Format],$B15,MASTER[EPC Status (Current Week)],"EPC Ready") -> 0 | AC15: =COUNTIFS(MASTER[EPC Status (Current Week)],"EPC Ready",MASTER[Sub Format],$B15)+COUNTIFS(MASTER[EPC Status (Current Week)],"EPC Ready Previous FY",MASTER[Sub Format],$B15) -> 0 | AD15: =COUNTIFS(MASTER[LAUNCHED / YTL],"LAUNCHED",MASTER[Sub Format],$B15) -> 0 | AE15: =COUNTIFS(MASTER[LAUNCHED / YTL],"YTL",MASTER[Sub Format],$B15) -> 0 | AF15: =COUNTIFS(MASTER[LAUNCHED / YTL],"YTL - Dropped by Business",MASTER[Sub Format],$B15) -> 0 | AG15: =SUM(AQ15:BH15) -> 0 | AH15: =AQ15 -> 0 | AI15: =AR15 -> 0 | AJ15: =AS15 -> 0 | AK15: =AT15 -> 0 | AL15: =AU15 -> 0 | AM15: =AV15 -> 0 | AN15: =AW15 -> 0 | AO15: =AX15 -> 0 | AP15: =AY15 -> 0 | AQ15: =COUNTIFS(MASTER[Sub Format],$B15,MASTER[Planned (Month) Bucket],AQ$2,MASTER[EPC Status (Current Week)],"WIP") -> 0 | AR15: =COUNTIFS(MASTER[Sub Format],$B15,MASTER[Planned (Month) Bucket],AR$2,MASTER[EPC Status (Current Week)],"WIP") -> 0 | AS15: =COUNTIFS(MASTER[Sub Format],$B15,MASTER[Planned (Month) Bucket],AS$2,MASTER[EPC Status (Current Week)],"WIP") -> 0 | AT15: =COUNTIFS(MASTER[Sub Format],$B15,MASTER[Planned (Month) Bucket],AT$2,MASTER[EPC Status (Current Week)],"WIP") -> 0 | AU15: =COUNTIFS(MASTER[Sub Format],$B15,MASTER[Planned (Month) Bucket],AU$2,MASTER[EPC Status (Current Week)],"WIP") -> 0 | AV15: =COUNTIFS(MASTER[Sub Format],$B15,MASTER[Planned (Month) Bucket],AV$2,MASTER[EPC Status (Current Week)],"WIP") -> 0 | AW15: =COUNTIFS(MASTER[Sub Format],$B15,MASTER[Planned (Month) Bucket],AW$2,MASTER[EPC Status (Current Week)],"WIP") -> 0 | AX15: =COUNTIFS(MASTER[Sub Format],$B15,MASTER[Planned (Month) Bucket],AX$2,MASTER[EPC Status (Current Week)],"WIP") -> 0 | ... BH15: =COUNTIFS(MASTER[Sub Format],$B15,MASTER[Planned (Month) Bucket],BH$2,MASTER[EPC Status (Current Week)],"WIP") -> 0 | BI15: =COUNTIFS(MASTER[Sub Format],$B15,MASTER[EPC Status (Current Week)],BI$2) -> 0 | BJ15: =COUNTIFS(MASTER[Sub Format],$B15,MASTER[EPC Status (Current Week)],BJ$2) -> 0 | BK15: =COUNTIFS(MASTER[Sub Format],$B15,MASTER[EPC Status (Current Week)],BK$2) -> 0 | BL15: =COUNTIFS(MASTER[Sub Format],$B15,MASTER[EPC Status (Current Week)],BL$2) -> 0 | BM15: =SUM(BN15:BU15) -> 0 | BN15: =COUNTIFS(MASTER[Sub Format],$B15,MASTER[EPC Status (Current Week)],BN$3) -> 0 | BO15: =COUNTIFS(MASTER[Sub Format],$B15,MASTER[EPC Status (Current Week)],BO$3) -> 0 | BP15: =COUNTIFS(MASTER[Sub Format],$B15,MASTER[EPC Status (Current Week)],BP$3) -> 0 | BQ15: =COUNTIFS(MASTER[Sub Format],$B15,MASTER[EPC Status (Current Week)],BQ$3) -> 0 | BR15: =COUNTIFS(MASTER[Sub Format],$B15,MASTER[EPC Status (Current Week)],BR$3) -> 0 | BS15: =COUNTIFS(MASTER[Sub Format],$B15,MASTER[EPC Status (Current Week)],BS$3) -> 0 | BT15: =COUNTIFS(MASTER[Sub Format],$B15,MASTER[EPC Status (Current Week)],BT$3) -> 0 | BU15: =COUNTIFS(MASTER[Sub Format],$B15,MASTER[EPC Status (Current Week)],BU$3) -> 0
A16: 10 | B16: Consumer Electronics - Dehire | C16: Dehire | D16: Amit C | E16: 10 | F16: =COUNTIFS(MASTER[Sub Format],$B16,MASTER[EPC Status (Current Week)],$F$3) -> 0 | G16: =COUNTIFS(MASTER[LAUNCHED / YTL],"LAUNCHED",MASTER[Sub Format],$B16,MASTER[EPC Status (Current Week)],"EPC Ready Previous FY") -> 0 | H16: =COUNTIFS(MASTER[LAUNCHED / YTL],"YTL",MASTER[Sub Format],$B16,MASTER[EPC Status (Current Week)],"EPC Ready Previous FY") -> 0 | I16: =COUNTIFS(MASTER[Sub Format],$B16,MASTER[Actual (Month) Bucket],I$3) -> 2 | J16: =COUNTIFS(MASTER[Sub Format],$B16,MASTER[Actual (Month) Bucket],J$3) -> 0 | K16: =COUNTIFS(MASTER[Sub Format],$B16,MASTER[Actual (Month) Bucket],K$3) -> 0 | L16: =SUM(I16:K16) -> 2 | M16: =COUNTIFS(MASTER[Sub Format],$B16,MASTER[Actual (Month) Bucket],M$3) -> 0 | N16: =COUNTIFS(MASTER[Sub Format],$B16,MASTER[Actual (Month) Bucket],N$3) -> 0 | O16: =COUNTIFS(MASTER[Sub Format],$B16,MASTER[Actual (Month) Bucket],O$3) -> 0 | P16: =SUM(M16:O16) -> 0 | Q16: =COUNTIFS(MASTER[Sub Format],$B16,MASTER[Actual (Month) Bucket],Q$3) -> 0 | R16: =COUNTIFS(MASTER[Sub Format],$B16,MASTER[Actual (Month) Bucket],R$3) -> 0 | S16: =COUNTIFS(MASTER[Sub Format],$B16,MASTER[Actual (Month) Bucket],S$3) -> 0 | T16: =SUM(Q16:S16) -> 0 | U16: =COUNTIFS(MASTER[Sub Format],$B16,MASTER[Actual (Month) Bucket],U$3) -> 0 | V16: =COUNTIFS(MASTER[Sub Format],$B16,MASTER[Actual (Month) Bucket],V$3) -> 0 | W16: =COUNTIFS(MASTER[Sub Format],$B16,MASTER[Actual (Month) Bucket],W$3) -> 0 | X16: =SUM(U16:W16) -> 0 | Y16: =L16+P16+T16+X16 -> 2 | Z16: =COUNTIFS(MASTER[LAUNCHED / YTL],"LAUNCHED",MASTER[Sub Format],$B16,MASTER[EPC Status (Current Week)],"EPC Ready") -> 2 | AA16: =COUNTIFS(MASTER[LAUNCHED / YTL],"YTL",MASTER[Sub Format],$B16,MASTER[EPC Status (Current Week)],"EPC Ready") -> 0 | AB16: =COUNTIFS(MASTER[LAUNCHED / YTL],"YTL - Dropped by Business",MASTER[Sub Format],$B16,MASTER[EPC Status (Current Week)],"EPC Ready") -> 0 | AC16: =COUNTIFS(MASTER[EPC Status (Current Week)],"EPC Ready",MASTER[Sub Format],$B16)+COUNTIFS(MASTER[EPC Status (Current Week)],"EPC Ready Previous FY",MASTER[Sub Format],$B16) -> 2 | AD16: =COUNTIFS(MASTER[LAUNCHED / YTL],"LAUNCHED",MASTER[Sub Format],$B16) -> 2 | AE16: =COUNTIFS(MASTER[LAUNCHED / YTL],"YTL",MASTER[Sub Format],$B16) -> 0 | AF16: =COUNTIFS(MASTER[LAUNCHED / YTL],"YTL - Dropped by Business",MASTER[Sub Format],$B16) -> 0 | AG16: =SUM(AQ16:BH16) -> 2 | AH16: =AQ16 -> 0 | AI16: =AR16 -> 0 | AJ16: =AS16 -> 0 | AK16: =AT16 -> 0 | AL16: =AU16 -> 0 | AM16: =AV16 -> 0 | AN16: =AW16 -> 0 | AO16: =AX16 -> 0 | AP16: =AY16 -> 0 | AQ16: =COUNTIFS(MASTER[Sub Format],$B16,MASTER[Planned (Month) Bucket],AQ$2,MASTER[EPC Status (Current Week)],"WIP") -> 0 | AR16: =COUNTIFS(MASTER[Sub Format],$B16,MASTER[Planned (Month) Bucket],AR$2,MASTER[EPC Status (Current Week)],"WIP") -> 0 | AS16: =COUNTIFS(MASTER[Sub Format],$B16,MASTER[Planned (Month) Bucket],AS$2,MASTER[EPC Status (Current Week)],"WIP") -> 0 | AT16: =COUNTIFS(MASTER[Sub Format],$B16,MASTER[Planned (Month) Bucket],AT$2,MASTER[EPC Status (Current Week)],"WIP") -> 0 | AU16: =COUNTIFS(MASTER[Sub Format],$B16,MASTER[Planned (Month) Bucket],AU$2,MASTER[EPC Status (Current Week)],"WIP") -> 0 | AV16: =COUNTIFS(MASTER[Sub Format],$B16,MASTER[Planned (Month) Bucket],AV$2,MASTER[EPC Status (Current Week)],"WIP") -> 0 | AW16: =COUNTIFS(MASTER[Sub Format],$B16,MASTER[Planned (Month) Bucket],AW$2,MASTER[EPC Status (Current Week)],"WIP") -> 0 | AX16: =COUNTIFS(MASTER[Sub Format],$B16,MASTER[Planned (Month) Bucket],AX$2,MASTER[EPC Status (Current Week)],"WIP") -> 0 | ... BH16: =COUNTIFS(MASTER[Sub Format],$B16,MASTER[Planned (Month) Bucket],BH$2,MASTER[EPC Status (Current Week)],"WIP") -> 0 | BI16: =COUNTIFS(MASTER[Sub Format],$B16,MASTER[EPC Status (Current Week)],BI$2) -> 0 | BJ16: =COUNTIFS(MASTER[Sub Format],$B16,MASTER[EPC Status (Current Week)],BJ$2) -> 0 | BK16: =COUNTIFS(MASTER[Sub Format],$B16,MASTER[EPC Status (Current Week)],BK$2) -> 0 | BL16: =COUNTIFS(MASTER[Sub Format],$B16,MASTER[EPC Status (Current Week)],BL$2) -> 0 | BM16: =SUM(BN16:BU16) -> 6 | BN16: =COUNTIFS(MASTER[Sub Format],$B16,MASTER[EPC Status (Current Week)],BN$3) -> 6 | BO16: =COUNTIFS(MASTER[Sub Format],$B16,MASTER[EPC Status (Current Week)],BO$3) -> 0 | BP16: =COUNTIFS(MASTER[Sub Format],$B16,MASTER[EPC Status (Current Week)],BP$3) -> 0 | BQ16: =COUNTIFS(MASTER[Sub Format],$B16,MASTER[EPC Status (Current Week)],BQ$3) -> 0 | BR16: =COUNTIFS(MASTER[Sub Format],$B16,MASTER[EPC Status (Current Week)],BR$3) -> 0 | BS16: =COUNTIFS(MASTER[Sub Format],$B16,MASTER[EPC Status (Current Week)],BS$3) -> 0 | BT16: =COUNTIFS(MASTER[Sub Format],$B16,MASTER[EPC Status (Current Week)],BT$3) -> 0 | BU16: =COUNTIFS(MASTER[Sub Format],$B16,MASTER[EPC Status (Current Week)],BU$3) -> 0
A17: 11 | B17: Jewels SAS | C17: NSO | D17: Amit C | E17: 22 | F17: =COUNTIFS(MASTER[Sub Format],$B17,MASTER[EPC Status (Current Week)],$F$3) -> 0 | G17: =COUNTIFS(MASTER[LAUNCHED / YTL],"LAUNCHED",MASTER[Sub Format],$B17,MASTER[EPC Status (Current Week)],"EPC Ready Previous FY") -> 0 | H17: =COUNTIFS(MASTER[LAUNCHED / YTL],"YTL",MASTER[Sub Format],$B17,MASTER[EPC Status (Current Week)],"EPC Ready Previous FY") -> 0 | I17: =COUNTIFS(MASTER[Sub Format],$B17,MASTER[Actual (Month) Bucket],I$3) -> 0 | J17: =COUNTIFS(MASTER[Sub Format],$B17,MASTER[Actual (Month) Bucket],J$3) -> 1 | K17: =COUNTIFS(MASTER[Sub Format],$B17,MASTER[Actual (Month) Bucket],K$3) -> 0 | L17: =SUM(I17:K17) -> 1 | M17: =COUNTIFS(MASTER[Sub Format],$B17,MASTER[Actual (Month) Bucket],M$3) -> 0 | N17: =COUNTIFS(MASTER[Sub Format],$B17,MASTER[Actual (Month) Bucket],N$3) -> 0 | O17: =COUNTIFS(MASTER[Sub Format],$B17,MASTER[Actual (Month) Bucket],O$3) -> 0 | P17: =SUM(M17:O17) -> 0 | Q17: =COUNTIFS(MASTER[Sub Format],$B17,MASTER[Actual (Month) Bucket],Q$3) -> 0 | R17: =COUNTIFS(MASTER[Sub Format],$B17,MASTER[Actual (Month) Bucket],R$3) -> 0 | S17: =COUNTIFS(MASTER[Sub Format],$B17,MASTER[Actual (Month) Bucket],S$3) -> 0 | T17: =SUM(Q17:S17) -> 0 | U17: =COUNTIFS(MASTER[Sub Format],$B17,MASTER[Actual (Month) Bucket],U$3) -> 0 | V17: =COUNTIFS(MASTER[Sub Format],$B17,MASTER[Actual (Month) Bucket],V$3) -> 0 | W17: =COUNTIFS(MASTER[Sub Format],$B17,MASTER[Actual (Month) Bucket],W$3) -> 0 | X17: =SUM(U17:W17) -> 0 | Y17: =L17+P17+T17+X17 -> 1 | Z17: =COUNTIFS(MASTER[LAUNCHED / YTL],"LAUNCHED",MASTER[Sub Format],$B17,MASTER[EPC Status (Current Week)],"EPC Ready") -> 0 | AA17: =COUNTIFS(MASTER[LAUNCHED / YTL],"YTL",MASTER[Sub Format],$B17,MASTER[EPC Status (Current Week)],"EPC Ready") -> 1 | AB17: =COUNTIFS(MASTER[LAUNCHED / YTL],"YTL - Dropped by Business",MASTER[Sub Format],$B17,MASTER[EPC Status (Current Week)],"EPC Ready") -> 0 | AC17: =COUNTIFS(MASTER[EPC Status (Current Week)],"EPC Ready",MASTER[Sub Format],$B17)+COUNTIFS(MASTER[EPC Status (Current Week)],"EPC Ready Previous FY",MASTER[Sub Format],$B17) -> 1 | AD17: =COUNTIFS(MASTER[LAUNCHED / YTL],"LAUNCHED",MASTER[Sub Format],$B17) -> 0 | AE17: =COUNTIFS(MASTER[LAUNCHED / YTL],"YTL",MASTER[Sub Format],$B17) -> 1 | AF17: =COUNTIFS(MASTER[LAUNCHED / YTL],"YTL - Dropped by Business",MASTER[Sub Format],$B17) -> 0 | AG17: =SUM(AQ17:BH17) -> 1 | AH17: =AQ17 -> 0 | AI17: =AR17 -> 0 | AJ17: =AS17 -> 0 | AK17: =AT17 -> 0 | AL17: =AU17 -> 0 | AM17: =AV17 -> 0 | AN17: =AW17 -> 0 | AO17: =AX17 -> 0 | AP17: =AY17 -> 0 | AQ17: =COUNTIFS(MASTER[Sub Format],$B17,MASTER[Planned (Month) Bucket],AQ$2,MASTER[EPC Status (Current Week)],"WIP") -> 0 | AR17: =COUNTIFS(MASTER[Sub Format],$B17,MASTER[Planned (Month) Bucket],AR$2,MASTER[EPC Status (Current Week)],"WIP") -> 0 | AS17: =COUNTIFS(MASTER[Sub Format],$B17,MASTER[Planned (Month) Bucket],AS$2,MASTER[EPC Status (Current Week)],"WIP") -> 0 | AT17: =COUNTIFS(MASTER[Sub Format],$B17,MASTER[Planned (Month) Bucket],AT$2,MASTER[EPC Status (Current Week)],"WIP") -> 0 | AU17: =COUNTIFS(MASTER[Sub Format],$B17,MASTER[Planned (Month) Bucket],AU$2,MASTER[EPC Status (Current Week)],"WIP") -> 0 | AV17: =COUNTIFS(MASTER[Sub Format],$B17,MASTER[Planned (Month) Bucket],AV$2,MASTER[EPC Status (Current Week)],"WIP") -> 0 | AW17: =COUNTIFS(MASTER[Sub Format],$B17,MASTER[Planned (Month) Bucket],AW$2,MASTER[EPC Status (Current Week)],"WIP") -> 0 | AX17: =COUNTIFS(MASTER[Sub Format],$B17,MASTER[Planned (Month) Bucket],AX$2,MASTER[EPC Status (Current Week)],"WIP") -> 0 | ... BH17: =COUNTIFS(MASTER[Sub Format],$B17,MASTER[Planned (Month) Bucket],BH$2,MASTER[EPC Status (Current Week)],"WIP") -> 0 | BI17: =COUNTIFS(MASTER[Sub Format],$B17,MASTER[EPC Status (Current Week)],BI$2) -> 0 | BJ17: =COUNTIFS(MASTER[Sub Format],$B17,MASTER[EPC Status (Current Week)],BJ$2) -> 0 | BK17: =COUNTIFS(MASTER[Sub Format],$B17,MASTER[EPC Status (Current Week)],BK$2) -> 0 | BL17: =COUNTIFS(MASTER[Sub Format],$B17,MASTER[EPC Status (Current Week)],BL$2) -> 0 | BM17: =SUM(BN17:BU17) -> 0
A18: 12 | B18: Jewels - Refit | C18: Refit | D18: Amit C | E18: 0 | F18: =COUNTIFS(MASTER[Sub Format],$B18,MASTER[EPC Status (Current Week)],$F$3) -> 0 | G18: =COUNTIFS(MASTER[LAUNCHED / YTL],"LAUNCHED",MASTER[Sub Format],$B18,MASTER[EPC Status (Current Week)],"EPC Ready Previous FY") -> 0 | H18: =COUNTIFS(MASTER[LAUNCHED / YTL],"YTL",MASTER[Sub Format],$B18,MASTER[EPC Status (Current Week)],"EPC Ready Previous FY") -> 0 | I18: =COUNTIFS(MASTER[Sub Format],$B18,MASTER[Actual (Month) Bucket],I$3) -> 0 | J18: =COUNTIFS(MASTER[Sub Format],$B18,MASTER[Actual (Month) Bucket],J$3) -> 0 | K18: =COUNTIFS(MASTER[Sub Format],$B18,MASTER[Actual (Month) Bucket],K$3) -> 0 | L18: =SUM(I18:K18) -> 0 | M18: =COUNTIFS(MASTER[Sub Format],$B18,MASTER[Actual (Month) Bucket],M$3) -> 0 | N18: =COUNTIFS(MASTER[Sub Format],$B18,MASTER[Actual (Month) Bucket],N$3) -> 0 | O18: =COUNTIFS(MASTER[Sub Format],$B18,MASTER[Actual (Month) Bucket],O$3) -> 0 | P18: =SUM(M18:O18) -> 0 | Q18: =COUNTIFS(MASTER[Sub Format],$B18,MASTER[Actual (Month) Bucket],Q$3) -> 0 | R18: =COUNTIFS(MASTER[Sub Format],$B18,MASTER[Actual (Month) Bucket],R$3) -> 0 | S18: =COUNTIFS(MASTER[Sub Format],$B18,MASTER[Actual (Month) Bucket],S$3) -> 0 | T18: =SUM(Q18:S18) -> 0 | U18: =COUNTIFS(MASTER[Sub Format],$B18,MASTER[Actual (Month) Bucket],U$3) -> 0 | V18: =COUNTIFS(MASTER[Sub Format],$B18,MASTER[Actual (Month) Bucket],V$3) -> 0 | W18: =COUNTIFS(MASTER[Sub Format],$B18,MASTER[Actual (Month) Bucket],W$3) -> 0 | X18: =SUM(U18:W18) -> 0 | Y18: =L18+P18+T18+X18 -> 0 | Z18: =COUNTIFS(MASTER[LAUNCHED / YTL],"LAUNCHED",MASTER[Sub Format],$B18,MASTER[EPC Status (Current Week)],"EPC Ready") -> 0 | AA18: =COUNTIFS(MASTER[LAUNCHED / YTL],"YTL",MASTER[Sub Format],$B18,MASTER[EPC Status (Current Week)],"EPC Ready") -> 0 | AB18: =COUNTIFS(MASTER[LAUNCHED / YTL],"YTL - Dropped by Business",MASTER[Sub Format],$B18,MASTER[EPC Status (Current Week)],"EPC Ready") -> 0 | AC18: =COUNTIFS(MASTER[EPC Status (Current Week)],"EPC Ready",MASTER[Sub Format],$B18)+COUNTIFS(MASTER[EPC Status (Current Week)],"EPC Ready Previous FY",MASTER[Sub Format],$B18) -> 0 | AD18: =COUNTIFS(MASTER[LAUNCHED / YTL],"LAUNCHED",MASTER[Sub Format],$B18) -> 0 | AE18: =COUNTIFS(MASTER[LAUNCHED / YTL],"YTL",MASTER[Sub Format],$B18) -> 0 | AF18: =COUNTIFS(MASTER[LAUNCHED / YTL],"YTL - Dropped by Business",MASTER[Sub Format],$B18) -> 0 | AG18: =SUM(AQ18:BH18) -> 0 | AH18: =AQ18 -> 0 | AI18: =AR18 -> 0 | AJ18: =AS18 -> 0 | AK18: =AT18 -> 0 | AL18: =AU18 -> 0 | AM18: =AV18 -> 0 | AN18: =AW18 -> 0 | AO18: =AX18 -> 0 | AP18: =AY18 -> 0 | AQ18: =COUNTIFS(MASTER[Sub Format],$B18,MASTER[Planned (Month) Bucket],AQ$2,MASTER[EPC Status (Current Week)],"WIP") -> 0 | AR18: =COUNTIFS(MASTER[Sub Format],$B18,MASTER[Planned (Month) Bucket],AR$2,MASTER[EPC Status (Current Week)],"WIP") -> 0 | AS18: =COUNTIFS(MASTER[Sub Format],$B18,MASTER[Planned (Month) Bucket],AS$2,MASTER[EPC Status (Current Week)],"WIP") -> 0 | AT18: =COUNTIFS(MASTER[Sub Format],$B18,MASTER[Planned (Month) Bucket],AT$2,MASTER[EPC Status (Current Week)],"WIP") -> 0 | AU18: =COUNTIFS(MASTER[Sub Format],$B18,MASTER[Planned (Month) Bucket],AU$2,MASTER[EPC Status (Current Week)],"WIP") -> 0 | AV18: =COUNTIFS(MASTER[Sub Format],$B18,MASTER[Planned (Month) Bucket],AV$2,MASTER[EPC Status (Current Week)],"WIP") -> 0 | AW18: =COUNTIFS(MASTER[Sub Format],$B18,MASTER[Planned (Month) Bucket],AW$2,MASTER[EPC Status (Current Week)],"WIP") -> 0 | AX18: =COUNTIFS(MASTER[Sub Format],$B18,MASTER[Planned (Month) Bucket],AX$2,MASTER[EPC Status (Current Week)],"WIP") -> 0 | ... BH18: =COUNTIFS(MASTER[Sub Format],$B18,MASTER[Planned (Month) Bucket],BH$2,MASTER[EPC Status (Current Week)],"WIP") -> 0 | BI18: =COUNTIFS(MASTER[Sub Format],$B18,MASTER[EPC Status (Current Week)],BI$2) -> 0 | BJ18: =COUNTIFS(MASTER[Sub Format],$B18,MASTER[EPC Status (Current Week)],BJ$2) -> 0 | BK18: =COUNTIFS(MASTER[Sub Format],$B18,MASTER[EPC Status (Current Week)],BK$2) -> 0 | BL18: =COUNTIFS(MASTER[Sub Format],$B18,MASTER[EPC Status (Current Week)],BL$2) -> 0 | BM18: =SUM(BN18:BU18) -> 0
A19: 13 | B19: Jewels - Dehire | C19: Dehire | D19: Amit C | E19: 12 | F19: =COUNTIFS(MASTER[Sub Format],$B19,MASTER[EPC Status (Current Week)],$F$3) -> 0 | G19: =COUNTIFS(MASTER[LAUNCHED / YTL],"LAUNCHED",MASTER[Sub Format],$B19,MASTER[EPC Status (Current Week)],"EPC Ready Previous FY") -> 0 | H19: =COUNTIFS(MASTER[LAUNCHED / YTL],"YTL",MASTER[Sub Format],$B19,MASTER[EPC Status (Current Week)],"EPC Ready Previous FY") -> 0 | I19: =COUNTIFS(MASTER[Sub Format],$B19,MASTER[Actual (Month) Bucket],I$3) -> 0 | J19: =COUNTIFS(MASTER[Sub Format],$B19,MASTER[Actual (Month) Bucket],J$3) -> 0 | K19: =COUNTIFS(MASTER[Sub Format],$B19,MASTER[Actual (Month) Bucket],K$3) -> 0 | L19: =SUM(I19:K19) -> 0 | M19: =COUNTIFS(MASTER[Sub Format],$B19,MASTER[Actual (Month) Bucket],M$3) -> 0 | N19: =COUNTIFS(MASTER[Sub Format],$B19,MASTER[Actual (Month) Bucket],N$3) -> 0 | O19: =COUNTIFS(MASTER[Sub Format],$B19,MASTER[Actual (Month) Bucket],O$3) -> 0 | P19: =SUM(M19:O19) -> 0 | Q19: =COUNTIFS(MASTER[Sub Format],$B19,MASTER[Actual (Month) Bucket],Q$3) -> 0 | R19: =COUNTIFS(MASTER[Sub Format],$B19,MASTER[Actual (Month) Bucket],R$3) -> 0 | S19: =COUNTIFS(MASTER[Sub Format],$B19,MASTER[Actual (Month) Bucket],S$3) -> 0 | T19: =SUM(Q19:S19) -> 0 | U19: =COUNTIFS(MASTER[Sub Format],$B19,MASTER[Actual (Month) Bucket],U$3) -> 0 | V19: =COUNTIFS(MASTER[Sub Format],$B19,MASTER[Actual (Month) Bucket],V$3) -> 0 | W19: =COUNTIFS(MASTER[Sub Format],$B19,MASTER[Actual (Month) Bucket],W$3) -> 0 | X19: =SUM(U19:W19) -> 0 | Y19: =L19+P19+T19+X19 -> 0 | Z19: =COUNTIFS(MASTER[LAUNCHED / YTL],"LAUNCHED",MASTER[Sub Format],$B19,MASTER[EPC Status (Current Week)],"EPC Ready") -> 0 | AA19: =COUNTIFS(MASTER[LAUNCHED / YTL],"YTL",MASTER[Sub Format],$B19,MASTER[EPC Status (Current Week)],"EPC Ready") -> 0 | AB19: =COUNTIFS(MASTER[LAUNCHED / YTL],"YTL - Dropped by Business",MASTER[Sub Format],$B19,MASTER[EPC Status (Current Week)],"EPC Ready") -> 0 | AC19: =COUNTIFS(MASTER[EPC Status (Current Week)],"EPC Ready",MASTER[Sub Format],$B19)+COUNTIFS(MASTER[EPC Status (Current Week)],"EPC Ready Previous FY",MASTER[Sub Format],$B19) -> 0 | AD19: =COUNTIFS(MASTER[LAUNCHED / YTL],"LAUNCHED",MASTER[Sub Format],$B19) -> 0 | AE19: =COUNTIFS(MASTER[LAUNCHED / YTL],"YTL",MASTER[Sub Format],$B19) -> 0 | AF19: =COUNTIFS(MASTER[LAUNCHED / YTL],"YTL - Dropped by Business",MASTER[Sub Format],$B19) -> 0 | AG19: =SUM(AQ19:BH19) -> 0 | AH19: =AQ19 -> 0 | AI19: =AR19 -> 0 | AJ19: =AS19 -> 0 | AK19: =AT19 -> 0 | AL19: =AU19 -> 0 | AM19: =AV19 -> 0 | AN19: =AW19 -> 0 | AO19: =AX19 -> 0 | AP19: =AY19 -> 0 | AQ19: =COUNTIFS(MASTER[Sub Format],$B19,MASTER[Planned (Month) Bucket],AQ$2,MASTER[EPC Status (Current Week)],"WIP") -> 0 | AR19: =COUNTIFS(MASTER[Sub Format],$B19,MASTER[Planned (Month) Bucket],AR$2,MASTER[EPC Status (Current Week)],"WIP") -> 0 | AS19: =COUNTIFS(MASTER[Sub Format],$B19,MASTER[Planned (Month) Bucket],AS$2,MASTER[EPC Status (Current Week)],"WIP") -> 0 | AT19: =COUNTIFS(MASTER[Sub Format],$B19,MASTER[Planned (Month) Bucket],AT$2,MASTER[EPC Status (Current Week)],"WIP") -> 0 | AU19: =COUNTIFS(MASTER[Sub Format],$B19,MASTER[Planned (Month) Bucket],AU$2,MASTER[EPC Status (Current Week)],"WIP") -> 0 | AV19: =COUNTIFS(MASTER[Sub Format],$B19,MASTER[Planned (Month) Bucket],AV$2,MASTER[EPC Status (Current Week)],"WIP") -> 0 | AW19: =COUNTIFS(MASTER[Sub Format],$B19,MASTER[Planned (Month) Bucket],AW$2,MASTER[EPC Status (Current Week)],"WIP") -> 0 | AX19: =COUNTIFS(MASTER[Sub Format],$B19,MASTER[Planned (Month) Bucket],AX$2,MASTER[EPC Status (Current Week)],"WIP") -> 0 | ... BH19: =COUNTIFS(MASTER[Sub Format],$B19,MASTER[Planned (Month) Bucket],BH$2,MASTER[EPC Status (Current Week)],"WIP") -> 0 | BI19: =COUNTIFS(MASTER[Sub Format],$B19,MASTER[EPC Status (Current Week)],BI$2) -> 0 | BJ19: =COUNTIFS(MASTER[Sub Format],$B19,MASTER[EPC Status (Current Week)],BJ$2) -> 0 | BK19: =COUNTIFS(MASTER[Sub Format],$B19,MASTER[EPC Status (Current Week)],BK$2) -> 0 | BL19: =COUNTIFS(MASTER[Sub Format],$B19,MASTER[EPC Status (Current Week)],BL$2) -> 0 | BM19: =SUM(BN19:BU19) -> 0
A20: B | B20: B. Fashion & Lifestyle | E20: =SUM(E21,E25,E28,E31,E34,E37:E66) -> 1270 | F20: =SUM(F21,F25,F28,F31,F34,F37:F66) -> 2 | G20: =SUM(G21,G25,G28,G31,G34,G37:G66) -> 2 | H20: =SUM(H21,H25,H28,H31,H34,H37:H66) -> 0 | I20: =SUM(I21,I25,I28,I31,I34,I37:I66) -> 234 | J20: =SUM(J21,J25,J28,J31,J34,J37:J66) -> 353 | K20: =SUM(K21,K25,K28,K31,K34,K37:K66) -> 23 | L20: =SUM(L21,L25,L28,L31,L34,L37:L66) -> 610 | ... BU20: =SUM(BU21,BU25,BU28,BU31,BU34,BU37:BU66) -> 0
A21: 1 | B21: Trends (Trends + Trends 3.0) | C21: NSO | D21: Srinivas P | E21: 50 | F21: =SUM(F22:F24) -> 0 | G21: =SUM(G22:G24) -> 0 | H21: =SUM(H22:H24) -> 0 | I21: =SUM(I22:I24) -> 0 | J21: =SUM(J22:J24) -> 3 | K21: =SUM(K22:K24) -> 0 | L21: =SUM(L22:L24) -> 3 | M21: =SUM(M22:M24) -> 0 | ... BK21: =SUM(BK22:BK24) -> 0 | BL21: =SUM(BL22:BL23) -> 0 | BM21: =SUM(BM22:BM23) -> 20 | BN21: =SUM(BN22:BN23) -> 4 | BO21: =SUM(BO22:BO23) -> 2 | BP21: =SUM(BP22:BP23) -> 0 | BQ21: =SUM(BQ22:BQ23) -> 0 | BR21: =SUM(BR22:BR23) -> 14 | BS21: =SUM(BS22:BS23) -> 0 | ... BU21: =SUM(BU22:BU23) -> 0
A22: 1.1 | B22: Trends | C22: NSO | D22: Srinivas P | E22: 50 | F22: =COUNTIFS(MASTER[Sub Format],$B22,MASTER[EPC Status (Current Week)],$F$3) -> 0 | G22: =COUNTIFS(MASTER[LAUNCHED / YTL],"LAUNCHED",MASTER[Sub Format],$B22,MASTER[EPC Status (Current Week)],"EPC Ready Previous FY") -> 0 | H22: =COUNTIFS(MASTER[LAUNCHED / YTL],"YTL",MASTER[Sub Format],$B22,MASTER[EPC Status (Current Week)],"EPC Ready Previous FY") -> 0 | I22: =COUNTIFS(MASTER[Sub Format],$B22,MASTER[Actual (Month) Bucket],I$3) -> 0 | J22: =COUNTIFS(MASTER[Sub Format],$B22,MASTER[Actual (Month) Bucket],J$3) -> 0 | K22: =COUNTIFS(MASTER[Sub Format],$B22,MASTER[Actual (Month) Bucket],K$3) -> 0 | L22: =SUM(I22:K22) -> 0 | M22: =COUNTIFS(MASTER[Sub Format],$B22,MASTER[Actual (Month) Bucket],M$3) -> 0 | N22: =COUNTIFS(MASTER[Sub Format],$B22,MASTER[Actual (Month) Bucket],N$3) -> 0 | O22: =COUNTIFS(MASTER[Sub Format],$B22,MASTER[Actual (Month) Bucket],O$3) -> 0 | P22: =SUM(M22:O22) -> 0 | Q22: =COUNTIFS(MASTER[Sub Format],$B22,MASTER[Actual (Month) Bucket],Q$3) -> 0 | R22: =COUNTIFS(MASTER[Sub Format],$B22,MASTER[Actual (Month) Bucket],R$3) -> 0 | S22: =COUNTIFS(MASTER[Sub Format],$B22,MASTER[Actual (Month) Bucket],S$3) -> 0 | T22: =SUM(Q22:S22) -> 0 | U22: =COUNTIFS(MASTER[Sub Format],$B22,MASTER[Actual (Month) Bucket],U$3) -> 0 | V22: =COUNTIFS(MASTER[Sub Format],$B22,MASTER[Actual (Month) Bucket],V$3) -> 0 | W22: =COUNTIFS(MASTER[Sub Format],$B22,MASTER[Actual (Month) Bucket],W$3) -> 0 | X22: =SUM(U22:W22) -> 0 | Y22: =L22+P22+T22+X22 -> 0 | Z22: =COUNTIFS(MASTER[LAUNCHED / YTL],"LAUNCHED",MASTER[Sub Format],$B22,MASTER[EPC Status (Current Week)],"EPC Ready") -> 0 | AA22: =COUNTIFS(MASTER[LAUNCHED / YTL],"YTL",MASTER[Sub Format],$B22,MASTER[EPC Status (Current Week)],"EPC Ready") -> 0 | AB22: =COUNTIFS(MASTER[LAUNCHED / YTL],"YTL - Dropped by Business",MASTER[Sub Format],$B22,MASTER[EPC Status (Current Week)],"EPC Ready") -> 0 | AC22: =COUNTIFS(MASTER[EPC Status (Current Week)],"EPC Ready",MASTER[Sub Format],$B22)+COUNTIFS(MASTER[EPC Status (Current Week)],"EPC Ready Previous FY",MASTER[Sub Format],$B22) -> 0 | AD22: =COUNTIFS(MASTER[LAUNCHED / YTL],"LAUNCHED",MASTER[Sub Format],$B22) -> 0 | AE22: =COUNTIFS(MASTER[LAUNCHED / YTL],"YTL",MASTER[Sub Format],$B22) -> 0 | AF22: =COUNTIFS(MASTER[LAUNCHED / YTL],"YTL - Dropped by Business",MASTER[Sub Format],$B22) -> 0 | AG22: =SUM(AQ22:BH22) -> 0 | AH22: =AQ22 -> 0 | AI22: =AR22 -> 0 | AJ22: =AS22 -> 0 | AK22: =AT22 -> 0 | AL22: =AU22 -> 0 | AM22: =AV22 -> 0 | AN22: =AW22 -> 0 | AO22: =AX22 -> 0 | AP22: =AY22 -> 0 | AQ22: =COUNTIFS(MASTER[Sub Format],$B22,MASTER[Planned (Month) Bucket],AQ$2,MASTER[EPC Status (Current Week)],"WIP") -> 0 | AR22: =COUNTIFS(MASTER[Sub Format],$B22,MASTER[Planned (Month) Bucket],AR$2,MASTER[EPC Status (Current Week)],"WIP") -> 0 | AS22: =COUNTIFS(MASTER[Sub Format],$B22,MASTER[Planned (Month) Bucket],AS$2,MASTER[EPC Status (Current Week)],"WIP") -> 0 | AT22: =COUNTIFS(MASTER[Sub Format],$B22,MASTER[Planned (Month) Bucket],AT$2,MASTER[EPC Status (Current Week)],"WIP") -> 0 | AU22: =COUNTIFS(MASTER[Sub Format],$B22,MASTER[Planned (Month) Bucket],AU$2,MASTER[EPC Status (Current Week)],"WIP") -> 0 | AV22: =COUNTIFS(MASTER[Sub Format],$B22,MASTER[Planned (Month) Bucket],AV$2,MASTER[EPC Status (Current Week)],"WIP") -> 0 | AW22: =COUNTIFS(MASTER[Sub Format],$B22,MASTER[Planned (Month) Bucket],AW$2,MASTER[EPC Status (Current Week)],"WIP") -> 0 | AX22: =COUNTIFS(MASTER[Sub Format],$B22,MASTER[Planned (Month) Bucket],AX$2,MASTER[EPC Status (Current Week)],"WIP") -> 0 | ... BH22: =COUNTIFS(MASTER[Sub Format],$B22,MASTER[Planned (Month) Bucket],BH$2,MASTER[EPC Status (Current Week)],"WIP") -> 0 | BI22: =COUNTIFS(MASTER[Sub Format],$B22,MASTER[EPC Status (Current Week)],BI$2) -> 0 | BJ22: =COUNTIFS(MASTER[Sub Format],$B22,MASTER[EPC Status (Current Week)],BJ$2) -> 0 | BK22: =COUNTIFS(MASTER[Sub Format],$B22,MASTER[EPC Status (Current Week)],BK$2) -> 0 | BL22: =COUNTIFS(MASTER[Sub Format],$B22,MASTER[EPC Status (Current Week)],BL$2) -> 0 | BM22: =SUM(BN22:BU22) -> 16 | BN22: =COUNTIFS(MASTER[Sub Format],$B22,MASTER[EPC Status (Current Week)],BN$3) -> 2 | BO22: =COUNTIFS(MASTER[Sub Format],$B22,MASTER[EPC Status (Current Week)],BO$3) -> 1 | BP22: =COUNTIFS(MASTER[Sub Format],$B22,MASTER[EPC Status (Current Week)],BP$3) -> 0 | BQ22: =COUNTIFS(MASTER[Sub Format],$B22,MASTER[EPC Status (Current Week)],BQ$3) -> 0 | BR22: =COUNTIFS(MASTER[Sub Format],$B22,MASTER[EPC Status (Current Week)],BR$3) -> 13 | BS22: =COUNTIFS(MASTER[Sub Format],$B22,MASTER[EPC Status (Current Week)],BS$3) -> 0 | BT22: =COUNTIFS(MASTER[Sub Format],$B22,MASTER[EPC Status (Current Week)],BT$3) -> 0 | BU22: =COUNTIFS(MASTER[Sub Format],$B22,MASTER[EPC Status (Current Week)],BU$3) -> 0
A23: 1.2 | B23: Trends 3.0 | C23: NSO | D23: Srinivas P | E23: 0 | F23: =COUNTIFS(MASTER[Sub Format],$B23,MASTER[EPC Status (Current Week)],$F$3) -> 0 | G23: =COUNTIFS(MASTER[LAUNCHED / YTL],"LAUNCHED",MASTER[Sub Format],$B23,MASTER[EPC Status (Current Week)],"EPC Ready Previous FY") -> 0 | H23: =COUNTIFS(MASTER[LAUNCHED / YTL],"YTL",MASTER[Sub Format],$B23,MASTER[EPC Status (Current Week)],"EPC Ready Previous FY") -> 0 | I23: =COUNTIFS(MASTER[Sub Format],$B23,MASTER[Actual (Month) Bucket],I$3) -> 0 | J23: =COUNTIFS(MASTER[Sub Format],$B23,MASTER[Actual (Month) Bucket],J$3) -> 3 | K23: =COUNTIFS(MASTER[Sub Format],$B23,MASTER[Actual (Month) Bucket],K$3) -> 0 | L23: =SUM(I23:K23) -> 3 | M23: =COUNTIFS(MASTER[Sub Format],$B23,MASTER[Actual (Month) Bucket],M$3) -> 0 | N23: =COUNTIFS(MASTER[Sub Format],$B23,MASTER[Actual (Month) Bucket],N$3) -> 0 | O23: =COUNTIFS(MASTER[Sub Format],$B23,MASTER[Actual (Month) Bucket],O$3) -> 0 | P23: =SUM(M23:O23) -> 0 | Q23: =COUNTIFS(MASTER[Sub Format],$B23,MASTER[Actual (Month) Bucket],Q$3) -> 0 | R23: =COUNTIFS(MASTER[Sub Format],$B23,MASTER[Actual (Month) Bucket],R$3) -> 0 | S23: =COUNTIFS(MASTER[Sub Format],$B23,MASTER[Actual (Month) Bucket],S$3) -> 0 | T23: =SUM(Q23:S23) -> 0 | U23: =COUNTIFS(MASTER[Sub Format],$B23,MASTER[Actual (Month) Bucket],U$3) -> 0 | V23: =COUNTIFS(MASTER[Sub Format],$B23,MASTER[Actual (Month) Bucket],V$3) -> 0 | W23: =COUNTIFS(MASTER[Sub Format],$B23,MASTER[Actual (Month) Bucket],W$3) -> 0 | X23: =SUM(U23:W23) -> 0 | Y23: =L23+P23+T23+X23 -> 3 | Z23: =COUNTIFS(MASTER[LAUNCHED / YTL],"LAUNCHED",MASTER[Sub Format],$B23,MASTER[EPC Status (Current Week)],"EPC Ready") -> 1 | AA23: =COUNTIFS(MASTER[LAUNCHED / YTL],"YTL",MASTER[Sub Format],$B23,MASTER[EPC Status (Current Week)],"EPC Ready") -> 2 | AB23: =COUNTIFS(MASTER[LAUNCHED / YTL],"YTL - Dropped by Business",MASTER[Sub Format],$B23,MASTER[EPC Status (Current Week)],"EPC Ready") -> 0 | AC23: =COUNTIFS(MASTER[EPC Status (Current Week)],"EPC Ready",MASTER[Sub Format],$B23)+COUNTIFS(MASTER[EPC Status (Current Week)],"EPC Ready Previous FY",MASTER[Sub Format],$B23) -> 3 | AD23: =COUNTIFS(MASTER[LAUNCHED / YTL],"LAUNCHED",MASTER[Sub Format],$B23) -> 1 | AE23: =COUNTIFS(MASTER[LAUNCHED / YTL],"YTL",MASTER[Sub Format],$B23) -> 2 | AF23: =COUNTIFS(MASTER[LAUNCHED / YTL],"YTL - Dropped by Business",MASTER[Sub Format],$B23) -> 0 | AG23: =SUM(AQ23:BH23) -> 1 | AH23: =AQ23 -> 0 | AI23: =AR23 -> 0 | AJ23: =AS23 -> 0 | AK23: =AT23 -> 0 | AL23: =AU23 -> 0 | AM23: =AV23 -> 0 | AN23: =AW23 -> 0 | AO23: =AX23 -> 0 | AP23: =AY23 -> 0 | AQ23: =COUNTIFS(MASTER[Sub Format],$B23,MASTER[Planned (Month) Bucket],AQ$2,MASTER[EPC Status (Current Week)],"WIP") -> 0 | AR23: =COUNTIFS(MASTER[Sub Format],$B23,MASTER[Planned (Month) Bucket],AR$2,MASTER[EPC Status (Current Week)],"WIP") -> 0 | AS23: =COUNTIFS(MASTER[Sub Format],$B23,MASTER[Planned (Month) Bucket],AS$2,MASTER[EPC Status (Current Week)],"WIP") -> 0 | AT23: =COUNTIFS(MASTER[Sub Format],$B23,MASTER[Planned (Month) Bucket],AT$2,MASTER[EPC Status (Current Week)],"WIP") -> 0 | AU23: =COUNTIFS(MASTER[Sub Format],$B23,MASTER[Planned (Month) Bucket],AU$2,MASTER[EPC Status (Current Week)],"WIP") -> 0 | AV23: =COUNTIFS(MASTER[Sub Format],$B23,MASTER[Planned (Month) Bucket],AV$2,MASTER[EPC Status (Current Week)],"WIP") -> 0 | AW23: =COUNTIFS(MASTER[Sub Format],$B23,MASTER[Planned (Month) Bucket],AW$2,MASTER[EPC Status (Current Week)],"WIP") -> 0 | AX23: =COUNTIFS(MASTER[Sub Format],$B23,MASTER[Planned (Month) Bucket],AX$2,MASTER[EPC Status (Current Week)],"WIP") -> 0 | ... BH23: =COUNTIFS(MASTER[Sub Format],$B23,MASTER[Planned (Month) Bucket],BH$2,MASTER[EPC Status (Current Week)],"WIP") -> 0 | BI23: =COUNTIFS(MASTER[Sub Format],$B23,MASTER[EPC Status (Current Week)],BI$2) -> 0 | BJ23: =COUNTIFS(MASTER[Sub Format],$B23,MASTER[EPC Status (Current Week)],BJ$2) -> 0 | BK23: =COUNTIFS(MASTER[Sub Format],$B23,MASTER[EPC Status (Current Week)],BK$2) -> 0 | BL23: =COUNTIFS(MASTER[Sub Format],$B23,MASTER[EPC Status (Current Week)],BL$2) -> 0 | BM23: =SUM(BN23:BU23) -> 4 | BN23: =COUNTIFS(MASTER[Sub Format],$B23,MASTER[EPC Status (Current Week)],BN$3) -> 2 | BO23: =COUNTIFS(MASTER[Sub Format],$B23,MASTER[EPC Status (Current Week)],BO$3) -> 1 | BP23: =COUNTIFS(MASTER[Sub Format],$B23,MASTER[EPC Status (Current Week)],BP$3) -> 0 | BQ23: =COUNTIFS(MASTER[Sub Format],$B23,MASTER[EPC Status (Current Week)],BQ$3) -> 0 | BR23: =COUNTIFS(MASTER[Sub Format],$B23,MASTER[EPC Status (Current Week)],BR$3) -> 1 | BS23: =COUNTIFS(MASTER[Sub Format],$B23,MASTER[EPC Status (Current Week)],BS$3) -> 0 | BT23: =COUNTIFS(MASTER[Sub Format],$B23,MASTER[EPC Status (Current Week)],BT$3) -> 0 | BU23: =COUNTIFS(MASTER[Sub Format],$B23,MASTER[EPC Status (Current Week)],BU$3) -> 0
A24: 1.3 | B24: Trends 4.0 | E24: 0 | F24: =COUNTIFS(MASTER[Sub Format],$B24,MASTER[EPC Status (Current Week)],$F$3) -> 0 | G24: =COUNTIFS(MASTER[LAUNCHED / YTL],"LAUNCHED",MASTER[Sub Format],$B24,MASTER[EPC Status (Current Week)],"EPC Ready Previous FY") -> 0 | H24: =COUNTIFS(MASTER[LAUNCHED / YTL],"YTL",MASTER[Sub Format],$B24,MASTER[EPC Status (Current Week)],"EPC Ready Previous FY") -> 0 | I24: =COUNTIFS(MASTER[Sub Format],$B24,MASTER[Actual (Month) Bucket],I$3) -> 0 | J24: =COUNTIFS(MASTER[Sub Format],$B24,MASTER[Actual (Month) Bucket],J$3) -> 0 | K24: =COUNTIFS(MASTER[Sub Format],$B24,MASTER[Actual (Month) Bucket],K$3) -> 0 | L24: =SUM(I24:K24) -> 0 | M24: =COUNTIFS(MASTER[Sub Format],$B24,MASTER[Actual (Month) Bucket],M$3) -> 0 | N24: =COUNTIFS(MASTER[Sub Format],$B24,MASTER[Actual (Month) Bucket],N$3) -> 0 | O24: =COUNTIFS(MASTER[Sub Format],$B24,MASTER[Actual (Month) Bucket],O$3) -> 0 | P24: =SUM(M24:O24) -> 0 | Q24: =COUNTIFS(MASTER[Sub Format],$B24,MASTER[Actual (Month) Bucket],Q$3) -> 0 | R24: =COUNTIFS(MASTER[Sub Format],$B24,MASTER[Actual (Month) Bucket],R$3) -> 0 | S24: =COUNTIFS(MASTER[Sub Format],$B24,MASTER[Actual (Month) Bucket],S$3) -> 0 | T24: =SUM(Q24:S24) -> 0 | U24: =COUNTIFS(MASTER[Sub Format],$B24,MASTER[Actual (Month) Bucket],U$3) -> 0 | V24: =COUNTIFS(MASTER[Sub Format],$B24,MASTER[Actual (Month) Bucket],V$3) -> 0 | W24: =COUNTIFS(MASTER[Sub Format],$B24,MASTER[Actual (Month) Bucket],W$3) -> 0 | X24: =SUM(U24:W24) -> 0 | Y24: =L24+P24+T24+X24 -> 0 | Z24: =COUNTIFS(MASTER[LAUNCHED / YTL],"LAUNCHED",MASTER[Sub Format],$B24,MASTER[EPC Status (Current Week)],"EPC Ready") -> 0 | AA24: =COUNTIFS(MASTER[LAUNCHED / YTL],"YTL",MASTER[Sub Format],$B24,MASTER[EPC Status (Current Week)],"EPC Ready") -> 0 | AB24: =COUNTIFS(MASTER[LAUNCHED / YTL],"YTL - Dropped by Business",MASTER[Sub Format],$B24,MASTER[EPC Status (Current Week)],"EPC Ready") -> 0 | AC24: =COUNTIFS(MASTER[EPC Status (Current Week)],"EPC Ready",MASTER[Sub Format],$B24)+COUNTIFS(MASTER[EPC Status (Current Week)],"EPC Ready Previous FY",MASTER[Sub Format],$B24) -> 0 | AD24: =COUNTIFS(MASTER[LAUNCHED / YTL],"LAUNCHED",MASTER[Sub Format],$B24) -> 0 | AE24: =COUNTIFS(MASTER[LAUNCHED / YTL],"YTL",MASTER[Sub Format],$B24) -> 0 | AF24: =COUNTIFS(MASTER[LAUNCHED / YTL],"YTL - Dropped by Business",MASTER[Sub Format],$B24) -> 0 | AG24: =SUM(AQ24:BH24) -> 1 | AH24: =AQ24 -> 0 | AI24: =AR24 -> 0 | AJ24: =AS24 -> 0 | AK24: =AT24 -> 0 | AL24: =AU24 -> 0 | AM24: =AV24 -> 0 | AN24: =AW24 -> 0 | AO24: =AX24 -> 0 | AP24: =AY24 -> 0 | AQ24: =COUNTIFS(MASTER[Sub Format],$B24,MASTER[Planned (Month) Bucket],AQ$2,MASTER[EPC Status (Current Week)],"WIP") -> 0 | AR24: =COUNTIFS(MASTER[Sub Format],$B24,MASTER[Planned (Month) Bucket],AR$2,MASTER[EPC Status (Current Week)],"WIP") -> 0 | AS24: =COUNTIFS(MASTER[Sub Format],$B24,MASTER[Planned (Month) Bucket],AS$2,MASTER[EPC Status (Current Week)],"WIP") -> 0 | AT24: =COUNTIFS(MASTER[Sub Format],$B24,MASTER[Planned (Month) Bucket],AT$2,MASTER[EPC Status (Current Week)],"WIP") -> 0 | AU24: =COUNTIFS(MASTER[Sub Format],$B24,MASTER[Planned (Month) Bucket],AU$2,MASTER[EPC Status (Current Week)],"WIP") -> 0 | AV24: =COUNTIFS(MASTER[Sub Format],$B24,MASTER[Planned (Month) Bucket],AV$2,MASTER[EPC Status (Current Week)],"WIP") -> 0 | AW24: =COUNTIFS(MASTER[Sub Format],$B24,MASTER[Planned (Month) Bucket],AW$2,MASTER[EPC Status (Current Week)],"WIP") -> 0 | AX24: =COUNTIFS(MASTER[Sub Format],$B24,MASTER[Planned (Month) Bucket],AX$2,MASTER[EPC Status (Current Week)],"WIP") -> 0 | ... BH24: =COUNTIFS(MASTER[Sub Format],$B24,MASTER[Planned (Month) Bucket],BH$2,MASTER[EPC Status (Current Week)],"WIP") -> 0 | BI24: =COUNTIFS(MASTER[Sub Format],$B24,MASTER[EPC Status (Current Week)],BI$2) -> 0 | BJ24: =COUNTIFS(MASTER[Sub Format],$B24,MASTER[EPC Status (Current Week)],BJ$2) -> 0 | BK24: =COUNTIFS(MASTER[Sub Format],$B24,MASTER[EPC Status (Current Week)],BK$2) -> 0 | BL24: =COUNTIFS(MASTER[Sub Format],$B24,MASTER[EPC Status (Current Week)],BL$2) -> 0 | BM24: =SUM(BN24:BU24) -> 0
A25: 2 | B25: Trends Small Town (TST + TST 3.0) | C25: NSO | D25: Srinivas P | E25: 0 | F25: =SUM(F26:F27) -> 0 | G25: =SUM(G26:G27) -> 0 | H25: =SUM(H26:H27) -> 0 | I25: =SUM(I26:I27) -> 0 | J25: =SUM(J26:J27) -> 0 | K25: =SUM(K26:K27) -> 0 | L25: =SUM(L26:L27) -> 0 | M25: =SUM(M26:M27) -> 0 | ... BU25: =SUM(BU26:BU27) -> 0
A26: 2.1 | B26: Trends Small Town | C26: NSO | D26: Srinivas P | E26: 0 | F26: =COUNTIFS(MASTER[Sub Format],$B26,MASTER[EPC Status (Current Week)],$F$3) -> 0 | G26: =COUNTIFS(MASTER[LAUNCHED / YTL],"LAUNCHED",MASTER[Sub Format],$B26,MASTER[EPC Status (Current Week)],"EPC Ready Previous FY") -> 0 | H26: =COUNTIFS(MASTER[LAUNCHED / YTL],"YTL",MASTER[Sub Format],$B26,MASTER[EPC Status (Current Week)],"EPC Ready Previous FY") -> 0 | I26: =COUNTIFS(MASTER[Sub Format],$B26,MASTER[Actual (Month) Bucket],I$3) -> 0 | J26: =COUNTIFS(MASTER[Sub Format],$B26,MASTER[Actual (Month) Bucket],J$3) -> 0 | K26: =COUNTIFS(MASTER[Sub Format],$B26,MASTER[Actual (Month) Bucket],K$3) -> 0 | L26: =SUM(I26:K26) -> 0 | M26: =COUNTIFS(MASTER[Sub Format],$B26,MASTER[Actual (Month) Bucket],M$3) -> 0 | N26: =COUNTIFS(MASTER[Sub Format],$B26,MASTER[Actual (Month) Bucket],N$3) -> 0 | O26: =COUNTIFS(MASTER[Sub Format],$B26,MASTER[Actual (Month) Bucket],O$3) -> 0 | P26: =SUM(M26:O26) -> 0 | Q26: =COUNTIFS(MASTER[Sub Format],$B26,MASTER[Actual (Month) Bucket],Q$3) -> 0 | R26: =COUNTIFS(MASTER[Sub Format],$B26,MASTER[Actual (Month) Bucket],R$3) -> 0 | S26: =COUNTIFS(MASTER[Sub Format],$B26,MASTER[Actual (Month) Bucket],S$3) -> 0 | T26: =SUM(Q26:S26) -> 0 | U26: =COUNTIFS(MASTER[Sub Format],$B26,MASTER[Actual (Month) Bucket],U$3) -> 0 | V26: =COUNTIFS(MASTER[Sub Format],$B26,MASTER[Actual (Month) Bucket],V$3) -> 0 | W26: =COUNTIFS(MASTER[Sub Format],$B26,MASTER[Actual (Month) Bucket],W$3) -> 0 | X26: =SUM(U26:W26) -> 0 | Y26: =L26+P26+T26+X26 -> 0 | Z26: =COUNTIFS(MASTER[LAUNCHED / YTL],"LAUNCHED",MASTER[Sub Format],$B26,MASTER[EPC Status (Current Week)],"EPC Ready") -> 0 | AA26: =COUNTIFS(MASTER[LAUNCHED / YTL],"YTL",MASTER[Sub Format],$B26,MASTER[EPC Status (Current Week)],"EPC Ready") -> 0 | AB26: =COUNTIFS(MASTER[LAUNCHED / YTL],"YTL - Dropped by Business",MASTER[Sub Format],$B26,MASTER[EPC Status (Current Week)],"EPC Ready") -> 0 | AC26: =COUNTIFS(MASTER[EPC Status (Current Week)],"EPC Ready",MASTER[Sub Format],$B26)+COUNTIFS(MASTER[EPC Status (Current Week)],"EPC Ready Previous FY",MASTER[Sub Format],$B26) -> 0 | AD26: =COUNTIFS(MASTER[LAUNCHED / YTL],"LAUNCHED",MASTER[Sub Format],$B26) -> 0 | AE26: =COUNTIFS(MASTER[LAUNCHED / YTL],"YTL",MASTER[Sub Format],$B26) -> 0 | AF26: =COUNTIFS(MASTER[LAUNCHED / YTL],"YTL - Dropped by Business",MASTER[Sub Format],$B26) -> 0 | AG26: =SUM(AQ26:BH26) -> 0 | AH26: =AQ26 -> 0 | AI26: =AR26 -> 0 | AJ26: =AS26 -> 0 | AK26: =AT26 -> 0 | AL26: =AU26 -> 0 | AM26: =AV26 -> 0 | AN26: =AW26 -> 0 | AO26: =AX26 -> 0 | AP26: =AY26 -> 0 | AQ26: =COUNTIFS(MASTER[Sub Format],$B26,MASTER[Planned (Month) Bucket],AQ$2,MASTER[EPC Status (Current Week)],"WIP") -> 0 | AR26: =COUNTIFS(MASTER[Sub Format],$B26,MASTER[Planned (Month) Bucket],AR$2,MASTER[EPC Status (Current Week)],"WIP") -> 0 | AS26: =COUNTIFS(MASTER[Sub Format],$B26,MASTER[Planned (Month) Bucket],AS$2,MASTER[EPC Status (Current Week)],"WIP") -> 0 | AT26: =COUNTIFS(MASTER[Sub Format],$B26,MASTER[Planned (Month) Bucket],AT$2,MASTER[EPC Status (Current Week)],"WIP") -> 0 | AU26: =COUNTIFS(MASTER[Sub Format],$B26,MASTER[Planned (Month) Bucket],AU$2,MASTER[EPC Status (Current Week)],"WIP") -> 0 | AV26: =COUNTIFS(MASTER[Sub Format],$B26,MASTER[Planned (Month) Bucket],AV$2,MASTER[EPC Status (Current Week)],"WIP") -> 0 | AW26: =COUNTIFS(MASTER[Sub Format],$B26,MASTER[Planned (Month) Bucket],AW$2,MASTER[EPC Status (Current Week)],"WIP") -> 0 | AX26: =COUNTIFS(MASTER[Sub Format],$B26,MASTER[Planned (Month) Bucket],AX$2,MASTER[EPC Status (Current Week)],"WIP") -> 0 | ... BH26: =COUNTIFS(MASTER[Sub Format],$B26,MASTER[Planned (Month) Bucket],BH$2,MASTER[EPC Status (Current Week)],"WIP") -> 0 | BI26: =COUNTIFS(MASTER[Sub Format],$B26,MASTER[EPC Status (Current Week)],BI$2) -> 0 | BJ26: =COUNTIFS(MASTER[Sub Format],$B26,MASTER[EPC Status (Current Week)],BJ$2) -> 0 | BK26: =COUNTIFS(MASTER[Sub Format],$B26,MASTER[EPC Status (Current Week)],BK$2) -> 0 | BL26: =COUNTIFS(MASTER[Sub Format],$B26,MASTER[EPC Status (Current Week)],BL$2) -> 0 | BM26: =SUM(BN26:BU26) -> 4 | BN26: =COUNTIFS(MASTER[Sub Format],$B26,MASTER[EPC Status (Current Week)],BN$3) -> 0 | BO26: =COUNTIFS(MASTER[Sub Format],$B26,MASTER[EPC Status (Current Week)],BO$3) -> 3 | BP26: =COUNTIFS(MASTER[Sub Format],$B26,MASTER[EPC Status (Current Week)],BP$3) -> 0 | BQ26: =COUNTIFS(MASTER[Sub Format],$B26,MASTER[EPC Status (Current Week)],BQ$3) -> 0 | BR26: =COUNTIFS(MASTER[Sub Format],$B26,MASTER[EPC Status (Current Week)],BR$3) -> 1 | BS26: =COUNTIFS(MASTER[Sub Format],$B26,MASTER[EPC Status (Current Week)],BS$3) -> 0 | BT26: =COUNTIFS(MASTER[Sub Format],$B26,MASTER[EPC Status (Current Week)],BT$3) -> 0 | BU26: =COUNTIFS(MASTER[Sub Format],$B26,MASTER[EPC Status (Current Week)],BU$3) -> 0
A27: 2.2 | B27: Trends Small Town 3.0 | C27: NSO | D27: Srinivas P | E27: 0 | F27: =COUNTIFS(MASTER[Sub Format],$B27,MASTER[EPC Status (Current Week)],$F$3) -> 0 | G27: =COUNTIFS(MASTER[LAUNCHED / YTL],"LAUNCHED",MASTER[Sub Format],$B27,MASTER[EPC Status (Current Week)],"EPC Ready Previous FY") -> 0 | H27: =COUNTIFS(MASTER[LAUNCHED / YTL],"YTL",MASTER[Sub Format],$B27,MASTER[EPC Status (Current Week)],"EPC Ready Previous FY") -> 0 | I27: =COUNTIFS(MASTER[Sub Format],$B27,MASTER[Actual (Month) Bucket],I$3) -> 0 | J27: =COUNTIFS(MASTER[Sub Format],$B27,MASTER[Actual (Month) Bucket],J$3) -> 0 | K27: =COUNTIFS(MASTER[Sub Format],$B27,MASTER[Actual (Month) Bucket],K$3) -> 0 | L27: =SUM(I27:K27) -> 0 | M27: =COUNTIFS(MASTER[Sub Format],$B27,MASTER[Actual (Month) Bucket],M$3) -> 0 | N27: =COUNTIFS(MASTER[Sub Format],$B27,MASTER[Actual (Month) Bucket],N$3) -> 0 | O27: =COUNTIFS(MASTER[Sub Format],$B27,MASTER[Actual (Month) Bucket],O$3) -> 0 | P27: =SUM(M27:O27) -> 0 | Q27: =COUNTIFS(MASTER[Sub Format],$B27,MASTER[Actual (Month) Bucket],Q$3) -> 0 | R27: =COUNTIFS(MASTER[Sub Format],$B27,MASTER[Actual (Month) Bucket],R$3) -> 0 | S27: =COUNTIFS(MASTER[Sub Format],$B27,MASTER[Actual (Month) Bucket],S$3) -> 0 | T27: =SUM(Q27:S27) -> 0 | U27: =COUNTIFS(MASTER[Sub Format],$B27,MASTER[Actual (Month) Bucket],U$3) -> 0 | V27: =COUNTIFS(MASTER[Sub Format],$B27,MASTER[Actual (Month) Bucket],V$3) -> 0 | W27: =COUNTIFS(MASTER[Sub Format],$B27,MASTER[Actual (Month) Bucket],W$3) -> 0 | X27: =SUM(U27:W27) -> 0 | Y27: =L27+P27+T27+X27 -> 0 | Z27: =COUNTIFS(MASTER[LAUNCHED / YTL],"LAUNCHED",MASTER[Sub Format],$B27,MASTER[EPC Status (Current Week)],"EPC Ready") -> 0 | AA27: =COUNTIFS(MASTER[LAUNCHED / YTL],"YTL",MASTER[Sub Format],$B27,MASTER[EPC Status (Current Week)],"EPC Ready") -> 0 | AB27: =COUNTIFS(MASTER[LAUNCHED / YTL],"YTL - Dropped by Business",MASTER[Sub Format],$B27,MASTER[EPC Status (Current Week)],"EPC Ready") -> 0 | AC27: =COUNTIFS(MASTER[EPC Status (Current Week)],"EPC Ready",MASTER[Sub Format],$B27)+COUNTIFS(MASTER[EPC Status (Current Week)],"EPC Ready Previous FY",MASTER[Sub Format],$B27) -> 0 | AD27: =COUNTIFS(MASTER[LAUNCHED / YTL],"LAUNCHED",MASTER[Sub Format],$B27) -> 0 | AE27: =COUNTIFS(MASTER[LAUNCHED / YTL],"YTL",MASTER[Sub Format],$B27) -> 0 | AF27: =COUNTIFS(MASTER[LAUNCHED / YTL],"YTL - Dropped by Business",MASTER[Sub Format],$B27) -> 0 | AG27: =SUM(AQ27:BH27) -> 0 | AH27: =AQ27 -> 0 | AI27: =AR27 -> 0 | AJ27: =AS27 -> 0 | AK27: =AT27 -> 0 | AL27: =AU27 -> 0 | AM27: =AV27 -> 0 | AN27: =AW27 -> 0 | AO27: =AX27 -> 0 | AP27: =AY27 -> 0 | AQ27: =COUNTIFS(MASTER[Sub Format],$B27,MASTER[Planned (Month) Bucket],AQ$2,MASTER[EPC Status (Current Week)],"WIP") -> 0 | AR27: =COUNTIFS(MASTER[Sub Format],$B27,MASTER[Planned (Month) Bucket],AR$2,MASTER[EPC Status (Current Week)],"WIP") -> 0 | AS27: =COUNTIFS(MASTER[Sub Format],$B27,MASTER[Planned (Month) Bucket],AS$2,MASTER[EPC Status (Current Week)],"WIP") -> 0 | AT27: =COUNTIFS(MASTER[Sub Format],$B27,MASTER[Planned (Month) Bucket],AT$2,MASTER[EPC Status (Current Week)],"WIP") -> 0 | AU27: =COUNTIFS(MASTER[Sub Format],$B27,MASTER[Planned (Month) Bucket],AU$2,MASTER[EPC Status (Current Week)],"WIP") -> 0 | AV27: =COUNTIFS(MASTER[Sub Format],$B27,MASTER[Planned (Month) Bucket],AV$2,MASTER[EPC Status (Current Week)],"WIP") -> 0 | AW27: =COUNTIFS(MASTER[Sub Format],$B27,MASTER[Planned (Month) Bucket],AW$2,MASTER[EPC Status (Current Week)],"WIP") -> 0 | AX27: =COUNTIFS(MASTER[Sub Format],$B27,MASTER[Planned (Month) Bucket],AX$2,MASTER[EPC Status (Current Week)],"WIP") -> 0 | ... BH27: =COUNTIFS(MASTER[Sub Format],$B27,MASTER[Planned (Month) Bucket],BH$2,MASTER[EPC Status (Current Week)],"WIP") -> 0 | BI27: =COUNTIFS(MASTER[Sub Format],$B27,MASTER[EPC Status (Current Week)],BI$2) -> 0 | BJ27: =COUNTIFS(MASTER[Sub Format],$B27,MASTER[EPC Status (Current Week)],BJ$2) -> 0 | BK27: =COUNTIFS(MASTER[Sub Format],$B27,MASTER[EPC Status (Current Week)],BK$2) -> 0 | BL27: =COUNTIFS(MASTER[Sub Format],$B27,MASTER[EPC Status (Current Week)],BL$2) -> 0 | BM27: =SUM(BN27:BU27) -> 1 | BN27: =COUNTIFS(MASTER[Sub Format],$B27,MASTER[EPC Status (Current Week)],BN$3) -> 0 | BO27: =COUNTIFS(MASTER[Sub Format],$B27,MASTER[EPC Status (Current Week)],BO$3) -> 1 | BP27: =COUNTIFS(MASTER[Sub Format],$B27,MASTER[EPC Status (Current Week)],BP$3) -> 0 | BQ27: =COUNTIFS(MASTER[Sub Format],$B27,MASTER[EPC Status (Current Week)],BQ$3) -> 0 | BR27: =COUNTIFS(MASTER[Sub Format],$B27,MASTER[EPC Status (Current Week)],BR$3) -> 0 | BS27: =COUNTIFS(MASTER[Sub Format],$B27,MASTER[EPC Status (Current Week)],BS$3) -> 0 | BT27: =COUNTIFS(MASTER[Sub Format],$B27,MASTER[EPC Status (Current Week)],BT$3) -> 0 | BU27: =COUNTIFS(MASTER[Sub Format],$B27,MASTER[EPC Status (Current Week)],BU$3) -> 0
A28: 3 | B28: Trends Woman (Woman + Woman 3.0) | C28: NSO | D28: Srinivas P | E28: 0 | F28: =SUM(F29:F30) -> 0 | G28: =SUM(G29:G30) -> 0 | H28: =SUM(H29:H30) -> 0 | I28: =SUM(I29:I30) -> 0 | J28: =SUM(J29:J30) -> 0 | K28: =SUM(K29:K30) -> 0 | L28: =SUM(L29:L30) -> 0 | M28: =SUM(M29:M30) -> 0 | ... BU28: =SUM(BU29:BU30) -> 0
A29: 3.1 | B29: Trends Woman | C29: NSO | D29: Srinivas P | E29: 0 | F29: =COUNTIFS(MASTER[Sub Format],$B29,MASTER[EPC Status (Current Week)],$F$3) -> 0 | G29: =COUNTIFS(MASTER[LAUNCHED / YTL],"LAUNCHED",MASTER[Sub Format],$B29,MASTER[EPC Status (Current Week)],"EPC Ready Previous FY") -> 0 | H29: =COUNTIFS(MASTER[LAUNCHED / YTL],"YTL",MASTER[Sub Format],$B29,MASTER[EPC Status (Current Week)],"EPC Ready Previous FY") -> 0 | I29: =COUNTIFS(MASTER[Sub Format],$B29,MASTER[Actual (Month) Bucket],I$3) -> 0 | J29: =COUNTIFS(MASTER[Sub Format],$B29,MASTER[Actual (Month) Bucket],J$3) -> 0 | K29: =COUNTIFS(MASTER[Sub Format],$B29,MASTER[Actual (Month) Bucket],K$3) -> 0 | L29: =SUM(I29:K29) -> 0 | M29: =COUNTIFS(MASTER[Sub Format],$B29,MASTER[Actual (Month) Bucket],M$3) -> 0 | N29: =COUNTIFS(MASTER[Sub Format],$B29,MASTER[Actual (Month) Bucket],N$3) -> 0 | O29: =COUNTIFS(MASTER[Sub Format],$B29,MASTER[Actual (Month) Bucket],O$3) -> 0 | P29: =SUM(M29:O29) -> 0 | Q29: =COUNTIFS(MASTER[Sub Format],$B29,MASTER[Actual (Month) Bucket],Q$3) -> 0 | R29: =COUNTIFS(MASTER[Sub Format],$B29,MASTER[Actual (Month) Bucket],R$3) -> 0 | S29: =COUNTIFS(MASTER[Sub Format],$B29,MASTER[Actual (Month) Bucket],S$3) -> 0 | T29: =SUM(Q29:S29) -> 0 | U29: =COUNTIFS(MASTER[Sub Format],$B29,MASTER[Actual (Month) Bucket],U$3) -> 0 | V29: =COUNTIFS(MASTER[Sub Format],$B29,MASTER[Actual (Month) Bucket],V$3) -> 0 | W29: =COUNTIFS(MASTER[Sub Format],$B29,MASTER[Actual (Month) Bucket],W$3) -> 0 | X29: =SUM(U29:W29) -> 0 | Y29: =L29+P29+T29+X29 -> 0 | Z29: =COUNTIFS(MASTER[LAUNCHED / YTL],"LAUNCHED",MASTER[Sub Format],$B29,MASTER[EPC Status (Current Week)],"EPC Ready") -> 0 | AA29: =COUNTIFS(MASTER[LAUNCHED / YTL],"YTL",MASTER[Sub Format],$B29,MASTER[EPC Status (Current Week)],"EPC Ready") -> 0 | AB29: =COUNTIFS(MASTER[LAUNCHED / YTL],"YTL - Dropped by Business",MASTER[Sub Format],$B29,MASTER[EPC Status (Current Week)],"EPC Ready") -> 0 | AC29: =COUNTIFS(MASTER[EPC Status (Current Week)],"EPC Ready",MASTER[Sub Format],$B29)+COUNTIFS(MASTER[EPC Status (Current Week)],"EPC Ready Previous FY",MASTER[Sub Format],$B29) -> 0 | AD29: =COUNTIFS(MASTER[LAUNCHED / YTL],"LAUNCHED",MASTER[Sub Format],$B29) -> 0 | AE29: =COUNTIFS(MASTER[LAUNCHED / YTL],"YTL",MASTER[Sub Format],$B29) -> 0 | AF29: =COUNTIFS(MASTER[LAUNCHED / YTL],"YTL - Dropped by Business",MASTER[Sub Format],$B29) -> 0 | AG29: =SUM(AQ29:BH29) -> 0 | AH29: =AQ29 -> 0 | AI29: =AR29 -> 0 | AJ29: =AS29 -> 0 | AK29: =AT29 -> 0 | AL29: =AU29 -> 0 | AM29: =AV29 -> 0 | AN29: =AW29 -> 0 | AO29: =AX29 -> 0 | AP29: =AY29 -> 0 | AQ29: =COUNTIFS(MASTER[Sub Format],$B29,MASTER[Planned (Month) Bucket],AQ$2,MASTER[EPC Status (Current Week)],"WIP") -> 0 | AR29: =COUNTIFS(MASTER[Sub Format],$B29,MASTER[Planned (Month) Bucket],AR$2,MASTER[EPC Status (Current Week)],"WIP") -> 0 | AS29: =COUNTIFS(MASTER[Sub Format],$B29,MASTER[Planned (Month) Bucket],AS$2,MASTER[EPC Status (Current Week)],"WIP") -> 0 | AT29: =COUNTIFS(MASTER[Sub Format],$B29,MASTER[Planned (Month) Bucket],AT$2,MASTER[EPC Status (Current Week)],"WIP") -> 0 | AU29: =COUNTIFS(MASTER[Sub Format],$B29,MASTER[Planned (Month) Bucket],AU$2,MASTER[EPC Status (Current Week)],"WIP") -> 0 | AV29: =COUNTIFS(MASTER[Sub Format],$B29,MASTER[Planned (Month) Bucket],AV$2,MASTER[EPC Status (Current Week)],"WIP") -> 0 | AW29: =COUNTIFS(MASTER[Sub Format],$B29,MASTER[Planned (Month) Bucket],AW$2,MASTER[EPC Status (Current Week)],"WIP") -> 0 | AX29: =COUNTIFS(MASTER[Sub Format],$B29,MASTER[Planned (Month) Bucket],AX$2,MASTER[EPC Status (Current Week)],"WIP") -> 0 | ... BH29: =COUNTIFS(MASTER[Sub Format],$B29,MASTER[Planned (Month) Bucket],BH$2,MASTER[EPC Status (Current Week)],"WIP") -> 0 | BI29: =COUNTIFS(MASTER[Sub Format],$B29,MASTER[EPC Status (Current Week)],BI$2) -> 0 | BJ29: =COUNTIFS(MASTER[Sub Format],$B29,MASTER[EPC Status (Current Week)],BJ$2) -> 0 | BK29: =COUNTIFS(MASTER[Sub Format],$B29,MASTER[EPC Status (Current Week)],BK$2) -> 0 | BL29: =COUNTIFS(MASTER[Sub Format],$B29,MASTER[EPC Status (Current Week)],BL$2) -> 0 | BM29: =SUM(BN29:BU29) -> 3 | BN29: =COUNTIFS(MASTER[Sub Format],$B29,MASTER[EPC Status (Current Week)],BN$3) -> 1 | BO29: =COUNTIFS(MASTER[Sub Format],$B29,MASTER[EPC Status (Current Week)],BO$3) -> 0 | BP29: =COUNTIFS(MASTER[Sub Format],$B29,MASTER[EPC Status (Current Week)],BP$3) -> 0 | BQ29: =COUNTIFS(MASTER[Sub Format],$B29,MASTER[EPC Status (Current Week)],BQ$3) -> 0 | BR29: =COUNTIFS(MASTER[Sub Format],$B29,MASTER[EPC Status (Current Week)],BR$3) -> 2 | BS29: =COUNTIFS(MASTER[Sub Format],$B29,MASTER[EPC Status (Current Week)],BS$3) -> 0 | BT29: =COUNTIFS(MASTER[Sub Format],$B29,MASTER[EPC Status (Current Week)],BT$3) -> 0 | BU29: =COUNTIFS(MASTER[Sub Format],$B29,MASTER[EPC Status (Current Week)],BU$3) -> 0
A30: 3.2 | B30: Trends WIW 3.0 | C30: NSO | D30: Srinivas P | E30: 0 | F30: =COUNTIFS(MASTER[Sub Format],$B30,MASTER[EPC Status (Current Week)],$F$3) -> 0 | G30: =COUNTIFS(MASTER[LAUNCHED / YTL],"LAUNCHED",MASTER[Sub Format],$B30,MASTER[EPC Status (Current Week)],"EPC Ready Previous FY") -> 0 | H30: =COUNTIFS(MASTER[LAUNCHED / YTL],"YTL",MASTER[Sub Format],$B30,MASTER[EPC Status (Current Week)],"EPC Ready Previous FY") -> 0 | I30: =COUNTIFS(MASTER[Sub Format],$B30,MASTER[Actual (Month) Bucket],I$3) -> 0 | J30: =COUNTIFS(MASTER[Sub Format],$B30,MASTER[Actual (Month) Bucket],J$3) -> 0 | K30: =COUNTIFS(MASTER[Sub Format],$B30,MASTER[Actual (Month) Bucket],K$3) -> 0 | L30: =SUM(I30:K30) -> 0 | M30: =COUNTIFS(MASTER[Sub Format],$B30,MASTER[Actual (Month) Bucket],M$3) -> 0 | N30: =COUNTIFS(MASTER[Sub Format],$B30,MASTER[Actual (Month) Bucket],N$3) -> 0 | O30: =COUNTIFS(MASTER[Sub Format],$B30,MASTER[Actual (Month) Bucket],O$3) -> 0 | P30: =SUM(M30:O30) -> 0 | Q30: =COUNTIFS(MASTER[Sub Format],$B30,MASTER[Actual (Month) Bucket],Q$3) -> 0 | R30: =COUNTIFS(MASTER[Sub Format],$B30,MASTER[Actual (Month) Bucket],R$3) -> 0 | S30: =COUNTIFS(MASTER[Sub Format],$B30,MASTER[Actual (Month) Bucket],S$3) -> 0 | T30: =SUM(Q30:S30) -> 0 | U30: =COUNTIFS(MASTER[Sub Format],$B30,MASTER[Actual (Month) Bucket],U$3) -> 0 | V30: =COUNTIFS(MASTER[Sub Format],$B30,MASTER[Actual (Month) Bucket],V$3) -> 0 | W30: =COUNTIFS(MASTER[Sub Format],$B30,MASTER[Actual (Month) Bucket],W$3) -> 0 | X30: =SUM(U30:W30) -> 0 | Y30: =L30+P30+T30+X30 -> 0 | Z30: =COUNTIFS(MASTER[LAUNCHED / YTL],"LAUNCHED",MASTER[Sub Format],$B30,MASTER[EPC Status (Current Week)],"EPC Ready") -> 0 | AA30: =COUNTIFS(MASTER[LAUNCHED / YTL],"YTL",MASTER[Sub Format],$B30,MASTER[EPC Status (Current Week)],"EPC Ready") -> 0 | AB30: =COUNTIFS(MASTER[LAUNCHED / YTL],"YTL - Dropped by Business",MASTER[Sub Format],$B30,MASTER[EPC Status (Current Week)],"EPC Ready") -> 0 | AC30: =COUNTIFS(MASTER[EPC Status (Current Week)],"EPC Ready",MASTER[Sub Format],$B30)+COUNTIFS(MASTER[EPC Status (Current Week)],"EPC Ready Previous FY",MASTER[Sub Format],$B30) -> 0 | AD30: =COUNTIFS(MASTER[LAUNCHED / YTL],"LAUNCHED",MASTER[Sub Format],$B30) -> 0 | AE30: =COUNTIFS(MASTER[LAUNCHED / YTL],"YTL",MASTER[Sub Format],$B30) -> 0 | AF30: =COUNTIFS(MASTER[LAUNCHED / YTL],"YTL - Dropped by Business",MASTER[Sub Format],$B30) -> 0 | AG30: =SUM(AQ30:BH30) -> 0 | AH30: =AQ30 -> 0 | AI30: =AR30 -> 0 | AJ30: =AS30 -> 0 | AK30: =AT30 -> 0 | AL30: =AU30 -> 0 | AM30: =AV30 -> 0 | AN30: =AW30 -> 0 | AO30: =AX30 -> 0 | AP30: =AY30 -> 0 | AQ30: =COUNTIFS(MASTER[Sub Format],$B30,MASTER[Planned (Month) Bucket],AQ$2,MASTER[EPC Status (Current Week)],"WIP") -> 0 | AR30: =COUNTIFS(MASTER[Sub Format],$B30,MASTER[Planned (Month) Bucket],AR$2,MASTER[EPC Status (Current Week)],"WIP") -> 0 | AS30: =COUNTIFS(MASTER[Sub Format],$B30,MASTER[Planned (Month) Bucket],AS$2,MASTER[EPC Status (Current Week)],"WIP") -> 0 | AT30: =COUNTIFS(MASTER[Sub Format],$B30,MASTER[Planned (Month) Bucket],AT$2,MASTER[EPC Status (Current Week)],"WIP") -> 0 | AU30: =COUNTIFS(MASTER[Sub Format],$B30,MASTER[Planned (Month) Bucket],AU$2,MASTER[EPC Status (Current Week)],"WIP") -> 0 | AV30: =COUNTIFS(MASTER[Sub Format],$B30,MASTER[Planned (Month) Bucket],AV$2,MASTER[EPC Status (Current Week)],"WIP") -> 0 | AW30: =COUNTIFS(MASTER[Sub Format],$B30,MASTER[Planned (Month) Bucket],AW$2,MASTER[EPC Status (Current Week)],"WIP") -> 0 | AX30: =COUNTIFS(MASTER[Sub Format],$B30,MASTER[Planned (Month) Bucket],AX$2,MASTER[EPC Status (Current Week)],"WIP") -> 0 | ... BH30: =COUNTIFS(MASTER[Sub Format],$B30,MASTER[Planned (Month) Bucket],BH$2,MASTER[EPC Status (Current Week)],"WIP") -> 0 | BI30: =COUNTIFS(MASTER[Sub Format],$B30,MASTER[EPC Status (Current Week)],BI$2) -> 0 | BJ30: =COUNTIFS(MASTER[Sub Format],$B30,MASTER[EPC Status (Current Week)],BJ$2) -> 0 | BK30: =COUNTIFS(MASTER[Sub Format],$B30,MASTER[EPC Status (Current Week)],BK$2) -> 0 | BL30: =COUNTIFS(MASTER[Sub Format],$B30,MASTER[EPC Status (Current Week)],BL$2) -> 0 | BM30: =SUM(BN30:BU30) -> 0 | BN30: =COUNTIFS(MASTER[Sub Format],$B30,MASTER[EPC Status (Current Week)],BN$3) -> 0 | BO30: =COUNTIFS(MASTER[Sub Format],$B30,MASTER[EPC Status (Current Week)],BO$3) -> 0 | BP30: =COUNTIFS(MASTER[Sub Format],$B30,MASTER[EPC Status (Current Week)],BP$3) -> 0 | BQ30: =COUNTIFS(MASTER[Sub Format],$B30,MASTER[EPC Status (Current Week)],BQ$3) -> 0 | BR30: =COUNTIFS(MASTER[Sub Format],$B30,MASTER[EPC Status (Current Week)],BR$3) -> 0 | BS30: =COUNTIFS(MASTER[Sub Format],$B30,MASTER[EPC Status (Current Week)],BS$3) -> 0 | BT30: =COUNTIFS(MASTER[Sub Format],$B30,MASTER[EPC Status (Current Week)],BT$3) -> 0 | BU30: =COUNTIFS(MASTER[Sub Format],$B30,MASTER[EPC Status (Current Week)],BU$3) -> 0
A31: 4 | B31: Yousta (Yousta + Yousta Conversion) | C31: NSO | D31: Srinivas P | E31: 5 | F31: =SUM(F32:F33) -> 1 | G31: =SUM(G32:G33) -> 1 | H31: =SUM(H32:H33) -> 0 | I31: =SUM(I32:I33) -> 0 | J31: =SUM(J32:J33) -> 0 | K31: =SUM(K32:K33) -> 1 | L31: =SUM(L32:L33) -> 1 | M31: =SUM(M32:M33) -> 0 | ... BU31: =SUM(BU32:BU33) -> 0
A32: 4.1 | B32: Yousta | C32: NSO | D32: Srinivas P | E32: 5 | F32: =COUNTIFS(MASTER[Sub Format],$B32,MASTER[EPC Status (Current Week)],$F$3) -> 1 | G32: =COUNTIFS(MASTER[LAUNCHED / YTL],"LAUNCHED",MASTER[Sub Format],$B32,MASTER[EPC Status (Current Week)],"EPC Ready Previous FY") -> 1 | H32: =COUNTIFS(MASTER[LAUNCHED / YTL],"YTL",MASTER[Sub Format],$B32,MASTER[EPC Status (Current Week)],"EPC Ready Previous FY") -> 0 | I32: =COUNTIFS(MASTER[Sub Format],$B32,MASTER[Actual (Month) Bucket],I$3) -> 0 | J32: =COUNTIFS(MASTER[Sub Format],$B32,MASTER[Actual (Month) Bucket],J$3) -> 0 | K32: =COUNTIFS(MASTER[Sub Format],$B32,MASTER[Actual (Month) Bucket],K$3) -> 1 | L32: =SUM(I32:K32) -> 1 | M32: =COUNTIFS(MASTER[Sub Format],$B32,MASTER[Actual (Month) Bucket],M$3) -> 0 | N32: =COUNTIFS(MASTER[Sub Format],$B32,MASTER[Actual (Month) Bucket],N$3) -> 0 | O32: =COUNTIFS(MASTER[Sub Format],$B32,MASTER[Actual (Month) Bucket],O$3) -> 0 | P32: =SUM(M32:O32) -> 0 | Q32: =COUNTIFS(MASTER[Sub Format],$B32,MASTER[Actual (Month) Bucket],Q$3) -> 0 | R32: =COUNTIFS(MASTER[Sub Format],$B32,MASTER[Actual (Month) Bucket],R$3) -> 0 | S32: =COUNTIFS(MASTER[Sub Format],$B32,MASTER[Actual (Month) Bucket],S$3) -> 0 | T32: =SUM(Q32:S32) -> 0 | U32: =COUNTIFS(MASTER[Sub Format],$B32,MASTER[Actual (Month) Bucket],U$3) -> 0 | V32: =COUNTIFS(MASTER[Sub Format],$B32,MASTER[Actual (Month) Bucket],V$3) -> 0 | W32: =COUNTIFS(MASTER[Sub Format],$B32,MASTER[Actual (Month) Bucket],W$3) -> 0 | X32: =SUM(U32:W32) -> 0 | Y32: =L32+P32+T32+X32 -> 1 | Z32: =COUNTIFS(MASTER[LAUNCHED / YTL],"LAUNCHED",MASTER[Sub Format],$B32,MASTER[EPC Status (Current Week)],"EPC Ready") -> 0 | AA32: =COUNTIFS(MASTER[LAUNCHED / YTL],"YTL",MASTER[Sub Format],$B32,MASTER[EPC Status (Current Week)],"EPC Ready") -> 1 | AB32: =COUNTIFS(MASTER[LAUNCHED / YTL],"YTL - Dropped by Business",MASTER[Sub Format],$B32,MASTER[EPC Status (Current Week)],"EPC Ready") -> 0 | AC32: =COUNTIFS(MASTER[EPC Status (Current Week)],"EPC Ready",MASTER[Sub Format],$B32)+COUNTIFS(MASTER[EPC Status (Current Week)],"EPC Ready Previous FY",MASTER[Sub Format],$B32) -> 2 | AD32: =COUNTIFS(MASTER[LAUNCHED / YTL],"LAUNCHED",MASTER[Sub Format],$B32) -> 1 | AE32: =COUNTIFS(MASTER[LAUNCHED / YTL],"YTL",MASTER[Sub Format],$B32) -> 1 | AF32: =COUNTIFS(MASTER[LAUNCHED / YTL],"YTL - Dropped by Business",MASTER[Sub Format],$B32) -> 0 | AG32: =SUM(AQ32:BH32) -> 2 | AH32: =AQ32 -> 0 | AI32: =AR32 -> 0 | AJ32: =AS32 -> 0 | AK32: =AT32 -> 0 | AL32: =AU32 -> 0 | AM32: =AV32 -> 0 | AN32: =AW32 -> 0 | AO32: =AX32 -> 0 | AP32: =AY32 -> 0 | AQ32: =COUNTIFS(MASTER[Sub Format],$B32,MASTER[Planned (Month) Bucket],AQ$2,MASTER[EPC Status (Current Week)],"WIP") -> 0 | AR32: =COUNTIFS(MASTER[Sub Format],$B32,MASTER[Planned (Month) Bucket],AR$2,MASTER[EPC Status (Current Week)],"WIP") -> 0 | AS32: =COUNTIFS(MASTER[Sub Format],$B32,MASTER[Planned (Month) Bucket],AS$2,MASTER[EPC Status (Current Week)],"WIP") -> 0 | AT32: =COUNTIFS(MASTER[Sub Format],$B32,MASTER[Planned (Month) Bucket],AT$2,MASTER[EPC Status (Current Week)],"WIP") -> 0 | AU32: =COUNTIFS(MASTER[Sub Format],$B32,MASTER[Planned (Month) Bucket],AU$2,MASTER[EPC Status (Current Week)],"WIP") -> 0 | AV32: =COUNTIFS(MASTER[Sub Format],$B32,MASTER[Planned (Month) Bucket],AV$2,MASTER[EPC Status (Current Week)],"WIP") -> 0 | AW32: =COUNTIFS(MASTER[Sub Format],$B32,MASTER[Planned (Month) Bucket],AW$2,MASTER[EPC Status (Current Week)],"WIP") -> 0 | AX32: =COUNTIFS(MASTER[Sub Format],$B32,MASTER[Planned (Month) Bucket],AX$2,MASTER[EPC Status (Current Week)],"WIP") -> 0 | ... BH32: =COUNTIFS(MASTER[Sub Format],$B32,MASTER[Planned (Month) Bucket],BH$2,MASTER[EPC Status (Current Week)],"WIP") -> 0 | BI32: =COUNTIFS(MASTER[Sub Format],$B32,MASTER[EPC Status (Current Week)],BI$2) -> 0 | BJ32: =COUNTIFS(MASTER[Sub Format],$B32,MASTER[EPC Status (Current Week)],BJ$2) -> 0 | BK32: =COUNTIFS(MASTER[Sub Format],$B32,MASTER[EPC Status (Current Week)],BK$2) -> 0 | BL32: =COUNTIFS(MASTER[Sub Format],$B32,MASTER[EPC Status (Current Week)],BL$2) -> 0 | BM32: =SUM(BN32:BU32) -> 23 | BN32: =COUNTIFS(MASTER[Sub Format],$B32,MASTER[EPC Status (Current Week)],BN$3) -> 8 | BO32: =COUNTIFS(MASTER[Sub Format],$B32,MASTER[EPC Status (Current Week)],BO$3) -> 6 | BP32: =COUNTIFS(MASTER[Sub Format],$B32,MASTER[EPC Status (Current Week)],BP$3) -> 2 | BQ32: =COUNTIFS(MASTER[Sub Format],$B32,MASTER[EPC Status (Current Week)],BQ$3) -> 0 | BR32: =COUNTIFS(MASTER[Sub Format],$B32,MASTER[EPC Status (Current Week)],BR$3) -> 6 | BS32: =COUNTIFS(MASTER[Sub Format],$B32,MASTER[EPC Status (Current Week)],BS$3) -> 0 | BT32: =COUNTIFS(MASTER[Sub Format],$B32,MASTER[EPC Status (Current Week)],BT$3) -> 1 | BU32: =COUNTIFS(MASTER[Sub Format],$B32,MASTER[EPC Status (Current Week)],BU$3) -> 0
A33: 4.2 | B33: Yousta Conversion | C33: NSO | D33: Srinivas P | E33: 0 | F33: =COUNTIFS(MASTER[Sub Format],$B33,MASTER[EPC Status (Current Week)],$F$3) -> 0 | G33: =COUNTIFS(MASTER[LAUNCHED / YTL],"LAUNCHED",MASTER[Sub Format],$B33,MASTER[EPC Status (Current Week)],"EPC Ready Previous FY") -> 0 | H33: =COUNTIFS(MASTER[LAUNCHED / YTL],"YTL",MASTER[Sub Format],$B33,MASTER[EPC Status (Current Week)],"EPC Ready Previous FY") -> 0 | I33: =COUNTIFS(MASTER[Sub Format],$B33,MASTER[Actual (Month) Bucket],I$3) -> 0 | J33: =COUNTIFS(MASTER[Sub Format],$B33,MASTER[Actual (Month) Bucket],J$3) -> 0 | K33: =COUNTIFS(MASTER[Sub Format],$B33,MASTER[Actual (Month) Bucket],K$3) -> 0 | L33: =SUM(I33:K33) -> 0 | M33: =COUNTIFS(MASTER[Sub Format],$B33,MASTER[Actual (Month) Bucket],M$3) -> 0 | N33: =COUNTIFS(MASTER[Sub Format],$B33,MASTER[Actual (Month) Bucket],N$3) -> 0 | O33: =COUNTIFS(MASTER[Sub Format],$B33,MASTER[Actual (Month) Bucket],O$3) -> 0 | P33: =SUM(M33:O33) -> 0 | Q33: =COUNTIFS(MASTER[Sub Format],$B33,MASTER[Actual (Month) Bucket],Q$3) -> 0 | R33: =COUNTIFS(MASTER[Sub Format],$B33,MASTER[Actual (Month) Bucket],R$3) -> 0 | S33: =COUNTIFS(MASTER[Sub Format],$B33,MASTER[Actual (Month) Bucket],S$3) -> 0 | T33: =SUM(Q33:S33) -> 0 | U33: =COUNTIFS(MASTER[Sub Format],$B33,MASTER[Actual (Month) Bucket],U$3) -> 0 | V33: =COUNTIFS(MASTER[Sub Format],$B33,MASTER[Actual (Month) Bucket],V$3) -> 0 | W33: =COUNTIFS(MASTER[Sub Format],$B33,MASTER[Actual (Month) Bucket],W$3) -> 0 | X33: =SUM(U33:W33) -> 0 | Y33: =L33+P33+T33+X33 -> 0 | Z33: =COUNTIFS(MASTER[LAUNCHED / YTL],"LAUNCHED",MASTER[Sub Format],$B33,MASTER[EPC Status (Current Week)],"EPC Ready") -> 0 | AA33: =COUNTIFS(MASTER[LAUNCHED / YTL],"YTL",MASTER[Sub Format],$B33,MASTER[EPC Status (Current Week)],"EPC Ready") -> 0 | AB33: =COUNTIFS(MASTER[LAUNCHED / YTL],"YTL - Dropped by Business",MASTER[Sub Format],$B33,MASTER[EPC Status (Current Week)],"EPC Ready") -> 0 | AC33: =COUNTIFS(MASTER[EPC Status (Current Week)],"EPC Ready",MASTER[Sub Format],$B33)+COUNTIFS(MASTER[EPC Status (Current Week)],"EPC Ready Previous FY",MASTER[Sub Format],$B33) -> 0 | AD33: =COUNTIFS(MASTER[LAUNCHED / YTL],"LAUNCHED",MASTER[Sub Format],$B33) -> 0 | AE33: =COUNTIFS(MASTER[LAUNCHED / YTL],"YTL",MASTER[Sub Format],$B33) -> 0 | AF33: =COUNTIFS(MASTER[LAUNCHED / YTL],"YTL - Dropped by Business",MASTER[Sub Format],$B33) -> 0 | AG33: =SUM(AQ33:BH33) -> 1 | AH33: =AQ33 -> 0 | AI33: =AR33 -> 0 | AJ33: =AS33 -> 0 | AK33: =AT33 -> 0 | AL33: =AU33 -> 0 | AM33: =AV33 -> 0 | AN33: =AW33 -> 0 | AO33: =AX33 -> 0 | AP33: =AY33 -> 0 | AQ33: =COUNTIFS(MASTER[Sub Format],$B33,MASTER[Planned (Month) Bucket],AQ$2,MASTER[EPC Status (Current Week)],"WIP") -> 0 | AR33: =COUNTIFS(MASTER[Sub Format],$B33,MASTER[Planned (Month) Bucket],AR$2,MASTER[EPC Status (Current Week)],"WIP") -> 0 | AS33: =COUNTIFS(MASTER[Sub Format],$B33,MASTER[Planned (Month) Bucket],AS$2,MASTER[EPC Status (Current Week)],"WIP") -> 0 | AT33: =COUNTIFS(MASTER[Sub Format],$B33,MASTER[Planned (Month) Bucket],AT$2,MASTER[EPC Status (Current Week)],"WIP") -> 0 | AU33: =COUNTIFS(MASTER[Sub Format],$B33,MASTER[Planned (Month) Bucket],AU$2,MASTER[EPC Status (Current Week)],"WIP") -> 0 | AV33: =COUNTIFS(MASTER[Sub Format],$B33,MASTER[Planned (Month) Bucket],AV$2,MASTER[EPC Status (Current Week)],"WIP") -> 0 | AW33: =COUNTIFS(MASTER[Sub Format],$B33,MASTER[Planned (Month) Bucket],AW$2,MASTER[EPC Status (Current Week)],"WIP") -> 0 | AX33: =COUNTIFS(MASTER[Sub Format],$B33,MASTER[Planned (Month) Bucket],AX$2,MASTER[EPC Status (Current Week)],"WIP") -> 0 | ... BH33: =COUNTIFS(MASTER[Sub Format],$B33,MASTER[Planned (Month) Bucket],BH$2,MASTER[EPC Status (Current Week)],"WIP") -> 0 | BI33: =COUNTIFS(MASTER[Sub Format],$B33,MASTER[EPC Status (Current Week)],BI$2) -> 0 | BJ33: =COUNTIFS(MASTER[Sub Format],$B33,MASTER[EPC Status (Current Week)],BJ$2) -> 1 | BK33: =COUNTIFS(MASTER[Sub Format],$B33,MASTER[EPC Status (Current Week)],BK$2) -> 0 | BL33: =COUNTIFS(MASTER[Sub Format],$B33,MASTER[EPC Status (Current Week)],BL$2) -> 0 | BM33: =SUM(BN33:BU33) -> 3 | BN33: =COUNTIFS(MASTER[Sub Format],$B33,MASTER[EPC Status (Current Week)],BN$3) -> 2 | BO33: =COUNTIFS(MASTER[Sub Format],$B33,MASTER[EPC Status (Current Week)],BO$3) -> 1 | BP33: =COUNTIFS(MASTER[Sub Format],$B33,MASTER[EPC Status (Current Week)],BP$3) -> 0 | BQ33: =COUNTIFS(MASTER[Sub Format],$B33,MASTER[EPC Status (Current Week)],BQ$3) -> 0 | BR33: =COUNTIFS(MASTER[Sub Format],$B33,MASTER[EPC Status (Current Week)],BR$3) -> 0 | BS33: =COUNTIFS(MASTER[Sub Format],$B33,MASTER[EPC Status (Current Week)],BS$3) -> 0 | BT33: =COUNTIFS(MASTER[Sub Format],$B33,MASTER[EPC Status (Current Week)],BT$3) -> 0 | BU33: =COUNTIFS(MASTER[Sub Format],$B33,MASTER[EPC Status (Current Week)],BU$3) -> 0
A34: 5 | B34: Azorte (Azorte + Azorte Conversion) | C34: NSO | D34: Srinivas P | E34: 12 | F34: =SUM(F35:F36) -> 0 | G34: =SUM(G35:G36) -> 0 | H34: =SUM(H35:H36) -> 0 | I34: =SUM(I35:I36) -> 1 | J34: =SUM(J35:J36) -> 2 | K34: =SUM(K35:K36) -> 0 | L34: =SUM(L35:L36) -> 3 | M34: =SUM(M35:M36) -> 0 | ... BU34: =SUM(BU35:BU36) -> 0
A35: 5.1 | B35: Azorte | C35: NSO | D35: Srinivas P | E35: 12 | F35: =COUNTIFS(MASTER[Sub Format],$B35,MASTER[EPC Status (Current Week)],$F$3) -> 0 | G35: =COUNTIFS(MASTER[LAUNCHED / YTL],"LAUNCHED",MASTER[Sub Format],$B35,MASTER[EPC Status (Current Week)],"EPC Ready Previous FY") -> 0 | H35: =COUNTIFS(MASTER[LAUNCHED / YTL],"YTL",MASTER[Sub Format],$B35,MASTER[EPC Status (Current Week)],"EPC Ready Previous FY") -> 0 | I35: =COUNTIFS(MASTER[Sub Format],$B35,MASTER[Actual (Month) Bucket],I$3) -> 0 | J35: =COUNTIFS(MASTER[Sub Format],$B35,MASTER[Actual (Month) Bucket],J$3) -> 1 | K35: =COUNTIFS(MASTER[Sub Format],$B35,MASTER[Actual (Month) Bucket],K$3) -> 0 | L35: =SUM(I35:K35) -> 1 | M35: =COUNTIFS(MASTER[Sub Format],$B35,MASTER[Actual (Month) Bucket],M$3) -> 0 | N35: =COUNTIFS(MASTER[Sub Format],$B35,MASTER[Actual (Month) Bucket],N$3) -> 0 | O35: =COUNTIFS(MASTER[Sub Format],$B35,MASTER[Actual (Month) Bucket],O$3) -> 0 | P35: =SUM(M35:O35) -> 0 | Q35: =COUNTIFS(MASTER[Sub Format],$B35,MASTER[Actual (Month) Bucket],Q$3) -> 0 | R35: =COUNTIFS(MASTER[Sub Format],$B35,MASTER[Actual (Month) Bucket],R$3) -> 0 | S35: =COUNTIFS(MASTER[Sub Format],$B35,MASTER[Actual (Month) Bucket],S$3) -> 0 | T35: =SUM(Q35:S35) -> 0 | U35: =COUNTIFS(MASTER[Sub Format],$B35,MASTER[Actual (Month) Bucket],U$3) -> 0 | V35: =COUNTIFS(MASTER[Sub Format],$B35,MASTER[Actual (Month) Bucket],V$3) -> 0 | W35: =COUNTIFS(MASTER[Sub Format],$B35,MASTER[Actual (Month) Bucket],W$3) -> 0 | X35: =SUM(U35:W35) -> 0 | Y35: =L35+P35+T35+X35 -> 1 | Z35: =COUNTIFS(MASTER[LAUNCHED / YTL],"LAUNCHED",MASTER[Sub Format],$B35,MASTER[EPC Status (Current Week)],"EPC Ready") -> 1 | AA35: =COUNTIFS(MASTER[LAUNCHED / YTL],"YTL",MASTER[Sub Format],$B35,MASTER[EPC Status (Current Week)],"EPC Ready") -> 0 | AB35: =COUNTIFS(MASTER[LAUNCHED / YTL],"YTL - Dropped by Business",MASTER[Sub Format],$B35,MASTER[EPC Status (Current Week)],"EPC Ready") -> 0 | AC35: =COUNTIFS(MASTER[EPC Status (Current Week)],"EPC Ready",MASTER[Sub Format],$B35)+COUNTIFS(MASTER[EPC Status (Current Week)],"EPC Ready Previous FY",MASTER[Sub Format],$B35) -> 1 | AD35: =COUNTIFS(MASTER[LAUNCHED / YTL],"LAUNCHED",MASTER[Sub Format],$B35) -> 1 | AE35: =COUNTIFS(MASTER[LAUNCHED / YTL],"YTL",MASTER[Sub Format],$B35) -> 0 | AF35: =COUNTIFS(MASTER[LAUNCHED / YTL],"YTL - Dropped by Business",MASTER[Sub Format],$B35) -> 0 | AG35: =SUM(AQ35:BH35) -> 1 | AH35: =AQ35 -> 0 | AI35: =AR35 -> 0 | AJ35: =AS35 -> 0 | AK35: =AT35 -> 0 | AL35: =AU35 -> 0 | AM35: =AV35 -> 0 | AN35: =AW35 -> 0 | AO35: =AX35 -> 0 | AP35: =AY35 -> 0 | AQ35: =COUNTIFS(MASTER[Sub Format],$B35,MASTER[Planned (Month) Bucket],AQ$2,MASTER[EPC Status (Current Week)],"WIP") -> 0 | AR35: =COUNTIFS(MASTER[Sub Format],$B35,MASTER[Planned (Month) Bucket],AR$2,MASTER[EPC Status (Current Week)],"WIP") -> 0 | AS35: =COUNTIFS(MASTER[Sub Format],$B35,MASTER[Planned (Month) Bucket],AS$2,MASTER[EPC Status (Current Week)],"WIP") -> 0 | AT35: =COUNTIFS(MASTER[Sub Format],$B35,MASTER[Planned (Month) Bucket],AT$2,MASTER[EPC Status (Current Week)],"WIP") -> 0 | AU35: =COUNTIFS(MASTER[Sub Format],$B35,MASTER[Planned (Month) Bucket],AU$2,MASTER[EPC Status (Current Week)],"WIP") -> 0 | AV35: =COUNTIFS(MASTER[Sub Format],$B35,MASTER[Planned (Month) Bucket],AV$2,MASTER[EPC Status (Current Week)],"WIP") -> 0 | AW35: =COUNTIFS(MASTER[Sub Format],$B35,MASTER[Planned (Month) Bucket],AW$2,MASTER[EPC Status (Current Week)],"WIP") -> 0 | AX35: =COUNTIFS(MASTER[Sub Format],$B35,MASTER[Planned (Month) Bucket],AX$2,MASTER[EPC Status (Current Week)],"WIP") -> 0 | ... BH35: =COUNTIFS(MASTER[Sub Format],$B35,MASTER[Planned (Month) Bucket],BH$2,MASTER[EPC Status (Current Week)],"WIP") -> 0 | BI35: =COUNTIFS(MASTER[Sub Format],$B35,MASTER[EPC Status (Current Week)],BI$2) -> 0 | BJ35: =COUNTIFS(MASTER[Sub Format],$B35,MASTER[EPC Status (Current Week)],BJ$2) -> 0 | BK35: =COUNTIFS(MASTER[Sub Format],$B35,MASTER[EPC Status (Current Week)],BK$2) -> 0 | BL35: =COUNTIFS(MASTER[Sub Format],$B35,MASTER[EPC Status (Current Week)],BL$2) -> 0 | BM35: =SUM(BN35:BU35) -> 6 | BN35: =COUNTIFS(MASTER[Sub Format],$B35,MASTER[EPC Status (Current Week)],BN$3) -> 0 | BO35: =COUNTIFS(MASTER[Sub Format],$B35,MASTER[EPC Status (Current Week)],BO$3) -> 2 | BP35: =COUNTIFS(MASTER[Sub Format],$B35,MASTER[EPC Status (Current Week)],BP$3) -> 1 | BQ35: =COUNTIFS(MASTER[Sub Format],$B35,MASTER[EPC Status (Current Week)],BQ$3) -> 0 | BR35: =COUNTIFS(MASTER[Sub Format],$B35,MASTER[EPC Status (Current Week)],BR$3) -> 3 | BS35: =COUNTIFS(MASTER[Sub Format],$B35,MASTER[EPC Status (Current Week)],BS$3) -> 0 | BT35: =COUNTIFS(MASTER[Sub Format],$B35,MASTER[EPC Status (Current Week)],BT$3) -> 0 | BU35: =COUNTIFS(MASTER[Sub Format],$B35,MASTER[EPC Status (Current Week)],BU$3) -> 0
A36: 5.2 | B36: Azorte Conversion | C36: NSO | D36: Srinivas P | E36: 0 | F36: =COUNTIFS(MASTER[Sub Format],$B36,MASTER[EPC Status (Current Week)],$F$3) -> 0 | G36: =COUNTIFS(MASTER[LAUNCHED / YTL],"LAUNCHED",MASTER[Sub Format],$B36,MASTER[EPC Status (Current Week)],"EPC Ready Previous FY") -> 0 | H36: =COUNTIFS(MASTER[LAUNCHED / YTL],"YTL",MASTER[Sub Format],$B36,MASTER[EPC Status (Current Week)],"EPC Ready Previous FY") -> 0 | I36: =COUNTIFS(MASTER[Sub Format],$B36,MASTER[Actual (Month) Bucket],I$3) -> 1 | J36: =COUNTIFS(MASTER[Sub Format],$B36,MASTER[Actual (Month) Bucket],J$3) -> 1 | K36: =COUNTIFS(MASTER[Sub Format],$B36,MASTER[Actual (Month) Bucket],K$3) -> 0 | L36: =SUM(I36:K36) -> 2 | M36: =COUNTIFS(MASTER[Sub Format],$B36,MASTER[Actual (Month) Bucket],M$3) -> 0 | N36: =COUNTIFS(MASTER[Sub Format],$B36,MASTER[Actual (Month) Bucket],N$3) -> 0 | O36: =COUNTIFS(MASTER[Sub Format],$B36,MASTER[Actual (Month) Bucket],O$3) -> 0 | P36: =SUM(M36:O36) -> 0 | Q36: =COUNTIFS(MASTER[Sub Format],$B36,MASTER[Actual (Month) Bucket],Q$3) -> 0 | R36: =COUNTIFS(MASTER[Sub Format],$B36,MASTER[Actual (Month) Bucket],R$3) -> 0 | S36: =COUNTIFS(MASTER[Sub Format],$B36,MASTER[Actual (Month) Bucket],S$3) -> 0 | T36: =SUM(Q36:S36) -> 0 | U36: =COUNTIFS(MASTER[Sub Format],$B36,MASTER[Actual (Month) Bucket],U$3) -> 0 | V36: =COUNTIFS(MASTER[Sub Format],$B36,MASTER[Actual (Month) Bucket],V$3) -> 0 | W36: =COUNTIFS(MASTER[Sub Format],$B36,MASTER[Actual (Month) Bucket],W$3) -> 0 | X36: =SUM(U36:W36) -> 0 | Y36: =L36+P36+T36+X36 -> 2 | Z36: =COUNTIFS(MASTER[LAUNCHED / YTL],"LAUNCHED",MASTER[Sub Format],$B36,MASTER[EPC Status (Current Week)],"EPC Ready") -> 2 | AA36: =COUNTIFS(MASTER[LAUNCHED / YTL],"YTL",MASTER[Sub Format],$B36,MASTER[EPC Status (Current Week)],"EPC Ready") -> 0 | AB36: =COUNTIFS(MASTER[LAUNCHED / YTL],"YTL - Dropped by Business",MASTER[Sub Format],$B36,MASTER[EPC Status (Current Week)],"EPC Ready") -> 0 | AC36: =COUNTIFS(MASTER[EPC Status (Current Week)],"EPC Ready",MASTER[Sub Format],$B36)+COUNTIFS(MASTER[EPC Status (Current Week)],"EPC Ready Previous FY",MASTER[Sub Format],$B36) -> 2 | AD36: =COUNTIFS(MASTER[LAUNCHED / YTL],"LAUNCHED",MASTER[Sub Format],$B36) -> 2 | AE36: =COUNTIFS(MASTER[LAUNCHED / YTL],"YTL",MASTER[Sub Format],$B36) -> 0 | AF36: =COUNTIFS(MASTER[LAUNCHED / YTL],"YTL - Dropped by Business",MASTER[Sub Format],$B36) -> 0 | AG36: =SUM(AQ36:BH36) -> 1 | AH36: =AQ36 -> 0 | AI36: =AR36 -> 0 | AJ36: =AS36 -> 0 | AK36: =AT36 -> 0 | AL36: =AU36 -> 0 | AM36: =AV36 -> 0 | AN36: =AW36 -> 0 | AO36: =AX36 -> 0 | AP36: =AY36 -> 0 | AQ36: =COUNTIFS(MASTER[Sub Format],$B36,MASTER[Planned (Month) Bucket],AQ$2,MASTER[EPC Status (Current Week)],"WIP") -> 0 | AR36: =COUNTIFS(MASTER[Sub Format],$B36,MASTER[Planned (Month) Bucket],AR$2,MASTER[EPC Status (Current Week)],"WIP") -> 0 | AS36: =COUNTIFS(MASTER[Sub Format],$B36,MASTER[Planned (Month) Bucket],AS$2,MASTER[EPC Status (Current Week)],"WIP") -> 0 | AT36: =COUNTIFS(MASTER[Sub Format],$B36,MASTER[Planned (Month) Bucket],AT$2,MASTER[EPC Status (Current Week)],"WIP") -> 0 | AU36: =COUNTIFS(MASTER[Sub Format],$B36,MASTER[Planned (Month) Bucket],AU$2,MASTER[EPC Status (Current Week)],"WIP") -> 0 | AV36: =COUNTIFS(MASTER[Sub Format],$B36,MASTER[Planned (Month) Bucket],AV$2,MASTER[EPC Status (Current Week)],"WIP") -> 0 | AW36: =COUNTIFS(MASTER[Sub Format],$B36,MASTER[Planned (Month) Bucket],AW$2,MASTER[EPC Status (Current Week)],"WIP") -> 0 | AX36: =COUNTIFS(MASTER[Sub Format],$B36,MASTER[Planned (Month) Bucket],AX$2,MASTER[EPC Status (Current Week)],"WIP") -> 0 | ... BH36: =COUNTIFS(MASTER[Sub Format],$B36,MASTER[Planned (Month) Bucket],BH$2,MASTER[EPC Status (Current Week)],"WIP") -> 0 | BI36: =COUNTIFS(MASTER[Sub Format],$B36,MASTER[EPC Status (Current Week)],BI$2) -> 2 | BJ36: =COUNTIFS(MASTER[Sub Format],$B36,MASTER[EPC Status (Current Week)],BJ$2) -> 0 | BK36: =COUNTIFS(MASTER[Sub Format],$B36,MASTER[EPC Status (Current Week)],BK$2) -> 0 | BL36: =COUNTIFS(MASTER[Sub Format],$B36,MASTER[EPC Status (Current Week)],BL$2) -> 0 | BM36: =SUM(BN36:BU36) -> 0 | BN36: =COUNTIFS(MASTER[Sub Format],$B36,MASTER[EPC Status (Current Week)],BN$3) -> 0 | BO36: =COUNTIFS(MASTER[Sub Format],$B36,MASTER[EPC Status (Current Week)],BO$3) -> 0 | BP36: =COUNTIFS(MASTER[Sub Format],$B36,MASTER[EPC Status (Current Week)],BP$3) -> 0 | BQ36: =COUNTIFS(MASTER[Sub Format],$B36,MASTER[EPC Status (Current Week)],BQ$3) -> 0 | BR36: =COUNTIFS(MASTER[Sub Format],$B36,MASTER[EPC Status (Current Week)],BR$3) -> 0 | BS36: =COUNTIFS(MASTER[Sub Format],$B36,MASTER[EPC Status (Current Week)],BS$3) -> 0 | BT36: =COUNTIFS(MASTER[Sub Format],$B36,MASTER[EPC Status (Current Week)],BT$3) -> 0 | BU36: =COUNTIFS(MASTER[Sub Format],$B36,MASTER[EPC Status (Current Week)],BU$3) -> 0
A37: 6 | B37: Trends Man | C37: NSO | D37: Srinivas P | E37: 0 | F37: =COUNTIFS(MASTER[Sub Format],$B37,MASTER[EPC Status (Current Week)],$F$3) -> 0 | G37: =COUNTIFS(MASTER[LAUNCHED / YTL],"LAUNCHED",MASTER[Sub Format],$B37,MASTER[EPC Status (Current Week)],"EPC Ready Previous FY") -> 0 | H37: =COUNTIFS(MASTER[LAUNCHED / YTL],"YTL",MASTER[Sub Format],$B37,MASTER[EPC Status (Current Week)],"EPC Ready Previous FY") -> 0 | I37: =COUNTIFS(MASTER[Sub Format],$B37,MASTER[Actual (Month) Bucket],I$3) -> 0 | J37: =COUNTIFS(MASTER[Sub Format],$B37,MASTER[Actual (Month) Bucket],J$3) -> 0 | K37: =COUNTIFS(MASTER[Sub Format],$B37,MASTER[Actual (Month) Bucket],K$3) -> 0 | L37: =SUM(I37:K37) -> 0 | M37: =COUNTIFS(MASTER[Sub Format],$B37,MASTER[Actual (Month) Bucket],M$3) -> 0 | N37: =COUNTIFS(MASTER[Sub Format],$B37,MASTER[Actual (Month) Bucket],N$3) -> 0 | O37: =COUNTIFS(MASTER[Sub Format],$B37,MASTER[Actual (Month) Bucket],O$3) -> 0 | P37: =SUM(M37:O37) -> 0 | Q37: =COUNTIFS(MASTER[Sub Format],$B37,MASTER[Actual (Month) Bucket],Q$3) -> 0 | R37: =COUNTIFS(MASTER[Sub Format],$B37,MASTER[Actual (Month) Bucket],R$3) -> 0 | S37: =COUNTIFS(MASTER[Sub Format],$B37,MASTER[Actual (Month) Bucket],S$3) -> 0 | T37: =SUM(Q37:S37) -> 0 | U37: =COUNTIFS(MASTER[Sub Format],$B37,MASTER[Actual (Month) Bucket],U$3) -> 0 | V37: =COUNTIFS(MASTER[Sub Format],$B37,MASTER[Actual (Month) Bucket],V$3) -> 0 | W37: =COUNTIFS(MASTER[Sub Format],$B37,MASTER[Actual (Month) Bucket],W$3) -> 0 | X37: =SUM(U37:W37) -> 0 | Y37: =L37+P37+T37+X37 -> 0 | Z37: =COUNTIFS(MASTER[LAUNCHED / YTL],"LAUNCHED",MASTER[Sub Format],$B37,MASTER[EPC Status (Current Week)],"EPC Ready") -> 0 | AA37: =COUNTIFS(MASTER[LAUNCHED / YTL],"YTL",MASTER[Sub Format],$B37,MASTER[EPC Status (Current Week)],"EPC Ready") -> 0 | AB37: =COUNTIFS(MASTER[LAUNCHED / YTL],"YTL - Dropped by Business",MASTER[Sub Format],$B37,MASTER[EPC Status (Current Week)],"EPC Ready") -> 0 | AC37: =COUNTIFS(MASTER[EPC Status (Current Week)],"EPC Ready",MASTER[Sub Format],$B37)+COUNTIFS(MASTER[EPC Status (Current Week)],"EPC Ready Previous FY",MASTER[Sub Format],$B37) -> 0 | AD37: =COUNTIFS(MASTER[LAUNCHED / YTL],"LAUNCHED",MASTER[Sub Format],$B37) -> 0 | AE37: =COUNTIFS(MASTER[LAUNCHED / YTL],"YTL",MASTER[Sub Format],$B37) -> 0 | AF37: =COUNTIFS(MASTER[LAUNCHED / YTL],"YTL - Dropped by Business",MASTER[Sub Format],$B37) -> 0 | AG37: =SUM(AQ37:BH37) -> 0 | AH37: =AQ37 -> 0 | AI37: =AR37 -> 0 | AJ37: =AS37 -> 0 | AK37: =AT37 -> 0 | AL37: =AU37 -> 0 | AM37: =AV37 -> 0 | AN37: =AW37 -> 0 | AO37: =AX37 -> 0 | AP37: =AY37 -> 0 | AQ37: =COUNTIFS(MASTER[Sub Format],$B37,MASTER[Planned (Month) Bucket],AQ$2,MASTER[EPC Status (Current Week)],"WIP") -> 0 | AR37: =COUNTIFS(MASTER[Sub Format],$B37,MASTER[Planned (Month) Bucket],AR$2,MASTER[EPC Status (Current Week)],"WIP") -> 0 | AS37: =COUNTIFS(MASTER[Sub Format],$B37,MASTER[Planned (Month) Bucket],AS$2,MASTER[EPC Status (Current Week)],"WIP") -> 0 | AT37: =COUNTIFS(MASTER[Sub Format],$B37,MASTER[Planned (Month) Bucket],AT$2,MASTER[EPC Status (Current Week)],"WIP") -> 0 | AU37: =COUNTIFS(MASTER[Sub Format],$B37,MASTER[Planned (Month) Bucket],AU$2,MASTER[EPC Status (Current Week)],"WIP") -> 0 | AV37: =COUNTIFS(MASTER[Sub Format],$B37,MASTER[Planned (Month) Bucket],AV$2,MASTER[EPC Status (Current Week)],"WIP") -> 0 | AW37: =COUNTIFS(MASTER[Sub Format],$B37,MASTER[Planned (Month) Bucket],AW$2,MASTER[EPC Status (Current Week)],"WIP") -> 0 | AX37: =COUNTIFS(MASTER[Sub Format],$B37,MASTER[Planned (Month) Bucket],AX$2,MASTER[EPC Status (Current Week)],"WIP") -> 0 | ... BH37: =COUNTIFS(MASTER[Sub Format],$B37,MASTER[Planned (Month) Bucket],BH$2,MASTER[EPC Status (Current Week)],"WIP") -> 0 | BI37: =COUNTIFS(MASTER[Sub Format],$B37,MASTER[EPC Status (Current Week)],BI$2) -> 0 | BJ37: =COUNTIFS(MASTER[Sub Format],$B37,MASTER[EPC Status (Current Week)],BJ$2) -> 0 | BK37: =COUNTIFS(MASTER[Sub Format],$B37,MASTER[EPC Status (Current Week)],BK$2) -> 0 | BL37: =COUNTIFS(MASTER[Sub Format],$B37,MASTER[EPC Status (Current Week)],BL$2) -> 0 | BM37: =SUM(BN37:BU37) -> 4 | BN37: =COUNTIFS(MASTER[Sub Format],$B37,MASTER[EPC Status (Current Week)],BN$3) -> 1 | BO37: =COUNTIFS(MASTER[Sub Format],$B37,MASTER[EPC Status (Current Week)],BO$3) -> 1 | BP37: =COUNTIFS(MASTER[Sub Format],$B37,MASTER[EPC Status (Current Week)],BP$3) -> 0 | BQ37: =COUNTIFS(MASTER[Sub Format],$B37,MASTER[EPC Status (Current Week)],BQ$3) -> 0 | BR37: =COUNTIFS(MASTER[Sub Format],$B37,MASTER[EPC Status (Current Week)],BR$3) -> 2 | BS37: =COUNTIFS(MASTER[Sub Format],$B37,MASTER[EPC Status (Current Week)],BS$3) -> 0 | BT37: =COUNTIFS(MASTER[Sub Format],$B37,MASTER[EPC Status (Current Week)],BT$3) -> 0 | BU37: =COUNTIFS(MASTER[Sub Format],$B37,MASTER[EPC Status (Current Week)],BU$3) -> 0
A38: 7 | B38: Trends Junior | C38: NSO | D38: Srinivas P | E38: 0 | F38: =COUNTIFS(MASTER[Sub Format],$B38,MASTER[EPC Status (Current Week)],$F$3) -> 0 | G38: =COUNTIFS(MASTER[LAUNCHED / YTL],"LAUNCHED",MASTER[Sub Format],$B38,MASTER[EPC Status (Current Week)],"EPC Ready Previous FY") -> 0 | H38: =COUNTIFS(MASTER[LAUNCHED / YTL],"YTL",MASTER[Sub Format],$B38,MASTER[EPC Status (Current Week)],"EPC Ready Previous FY") -> 0 | I38: =COUNTIFS(MASTER[Sub Format],$B38,MASTER[Actual (Month) Bucket],I$3) -> 0 | J38: =COUNTIFS(MASTER[Sub Format],$B38,MASTER[Actual (Month) Bucket],J$3) -> 0 | K38: =COUNTIFS(MASTER[Sub Format],$B38,MASTER[Actual (Month) Bucket],K$3) -> 0 | L38: =SUM(I38:K38) -> 0 | M38: =COUNTIFS(MASTER[Sub Format],$B38,MASTER[Actual (Month) Bucket],M$3) -> 0 | N38: =COUNTIFS(MASTER[Sub Format],$B38,MASTER[Actual (Month) Bucket],N$3) -> 0 | O38: =COUNTIFS(MASTER[Sub Format],$B38,MASTER[Actual (Month) Bucket],O$3) -> 0 | P38: =SUM(M38:O38) -> 0 | Q38: =COUNTIFS(MASTER[Sub Format],$B38,MASTER[Actual (Month) Bucket],Q$3) -> 0 | R38: =COUNTIFS(MASTER[Sub Format],$B38,MASTER[Actual (Month) Bucket],R$3) -> 0 | S38: =COUNTIFS(MASTER[Sub Format],$B38,MASTER[Actual (Month) Bucket],S$3) -> 0 | T38: =SUM(Q38:S38) -> 0 | U38: =COUNTIFS(MASTER[Sub Format],$B38,MASTER[Actual (Month) Bucket],U$3) -> 0 | V38: =COUNTIFS(MASTER[Sub Format],$B38,MASTER[Actual (Month) Bucket],V$3) -> 0 | W38: =COUNTIFS(MASTER[Sub Format],$B38,MASTER[Actual (Month) Bucket],W$3) -> 0 | X38: =SUM(U38:W38) -> 0 | Y38: =L38+P38+T38+X38 -> 0 | Z38: =COUNTIFS(MASTER[LAUNCHED / YTL],"LAUNCHED",MASTER[Sub Format],$B38,MASTER[EPC Status (Current Week)],"EPC Ready") -> 0 | AA38: =COUNTIFS(MASTER[LAUNCHED / YTL],"YTL",MASTER[Sub Format],$B38,MASTER[EPC Status (Current Week)],"EPC Ready") -> 0 | AB38: =COUNTIFS(MASTER[LAUNCHED / YTL],"YTL - Dropped by Business",MASTER[Sub Format],$B38,MASTER[EPC Status (Current Week)],"EPC Ready") -> 0 | AC38: =COUNTIFS(MASTER[EPC Status (Current Week)],"EPC Ready",MASTER[Sub Format],$B38)+COUNTIFS(MASTER[EPC Status (Current Week)],"EPC Ready Previous FY",MASTER[Sub Format],$B38) -> 0 | AD38: =COUNTIFS(MASTER[LAUNCHED / YTL],"LAUNCHED",MASTER[Sub Format],$B38) -> 0 | AE38: =COUNTIFS(MASTER[LAUNCHED / YTL],"YTL",MASTER[Sub Format],$B38) -> 0 | AF38: =COUNTIFS(MASTER[LAUNCHED / YTL],"YTL - Dropped by Business",MASTER[Sub Format],$B38) -> 0 | AG38: =SUM(AQ38:BH38) -> 0 | AH38: =AQ38 -> 0 | AI38: =AR38 -> 0 | AJ38: =AS38 -> 0 | AK38: =AT38 -> 0 | AL38: =AU38 -> 0 | AM38: =AV38 -> 0 | AN38: =AW38 -> 0 | AO38: =AX38 -> 0 | AP38: =AY38 -> 0 | AQ38: =COUNTIFS(MASTER[Sub Format],$B38,MASTER[Planned (Month) Bucket],AQ$2,MASTER[EPC Status (Current Week)],"WIP") -> 0 | AR38: =COUNTIFS(MASTER[Sub Format],$B38,MASTER[Planned (Month) Bucket],AR$2,MASTER[EPC Status (Current Week)],"WIP") -> 0 | AS38: =COUNTIFS(MASTER[Sub Format],$B38,MASTER[Planned (Month) Bucket],AS$2,MASTER[EPC Status (Current Week)],"WIP") -> 0 | AT38: =COUNTIFS(MASTER[Sub Format],$B38,MASTER[Planned (Month) Bucket],AT$2,MASTER[EPC Status (Current Week)],"WIP") -> 0 | AU38: =COUNTIFS(MASTER[Sub Format],$B38,MASTER[Planned (Month) Bucket],AU$2,MASTER[EPC Status (Current Week)],"WIP") -> 0 | AV38: =COUNTIFS(MASTER[Sub Format],$B38,MASTER[Planned (Month) Bucket],AV$2,MASTER[EPC Status (Current Week)],"WIP") -> 0 | AW38: =COUNTIFS(MASTER[Sub Format],$B38,MASTER[Planned (Month) Bucket],AW$2,MASTER[EPC Status (Current Week)],"WIP") -> 0 | AX38: =COUNTIFS(MASTER[Sub Format],$B38,MASTER[Planned (Month) Bucket],AX$2,MASTER[EPC Status (Current Week)],"WIP") -> 0 | ... BH38: =COUNTIFS(MASTER[Sub Format],$B38,MASTER[Planned (Month) Bucket],BH$2,MASTER[EPC Status (Current Week)],"WIP") -> 0 | BI38: =COUNTIFS(MASTER[Sub Format],$B38,MASTER[EPC Status (Current Week)],BI$2) -> 0 | BJ38: =COUNTIFS(MASTER[Sub Format],$B38,MASTER[EPC Status (Current Week)],BJ$2) -> 0 | BK38: =COUNTIFS(MASTER[Sub Format],$B38,MASTER[EPC Status (Current Week)],BK$2) -> 0 | BL38: =COUNTIFS(MASTER[Sub Format],$B38,MASTER[EPC Status (Current Week)],BL$2) -> 0 | BM38: =SUM(BN38:BU38) -> 0 | BN38: =COUNTIFS(MASTER[Sub Format],$B38,MASTER[EPC Status (Current Week)],BN$3) -> 0 | BO38: =COUNTIFS(MASTER[Sub Format],$B38,MASTER[EPC Status (Current Week)],BO$3) -> 0 | BP38: =COUNTIFS(MASTER[Sub Format],$B38,MASTER[EPC Status (Current Week)],BP$3) -> 0 | BQ38: =COUNTIFS(MASTER[Sub Format],$B38,MASTER[EPC Status (Current Week)],BQ$3) -> 0 | BR38: =COUNTIFS(MASTER[Sub Format],$B38,MASTER[EPC Status (Current Week)],BR$3) -> 0 | BS38: =COUNTIFS(MASTER[Sub Format],$B38,MASTER[EPC Status (Current Week)],BS$3) -> 0 | BT38: =COUNTIFS(MASTER[Sub Format],$B38,MASTER[EPC Status (Current Week)],BT$3) -> 0 | BU38: =COUNTIFS(MASTER[Sub Format],$B38,MASTER[EPC Status (Current Week)],BU$3) -> 0
A39: 8 | B39: Avantra | C39: NSO | D39: Srinivas P | E39: 0 | F39: =COUNTIFS(MASTER[Sub Format],$B39,MASTER[EPC Status (Current Week)],$F$3) -> 0 | G39: =COUNTIFS(MASTER[LAUNCHED / YTL],"LAUNCHED",MASTER[Sub Format],$B39,MASTER[EPC Status (Current Week)],"EPC Ready Previous FY") -> 0 | H39: =COUNTIFS(MASTER[LAUNCHED / YTL],"YTL",MASTER[Sub Format],$B39,MASTER[EPC Status (Current Week)],"EPC Ready Previous FY") -> 0 | I39: =COUNTIFS(MASTER[Sub Format],$B39,MASTER[Actual (Month) Bucket],I$3) -> 0 | J39: =COUNTIFS(MASTER[Sub Format],$B39,MASTER[Actual (Month) Bucket],J$3) -> 0 | K39: =COUNTIFS(MASTER[Sub Format],$B39,MASTER[Actual (Month) Bucket],K$3) -> 0 | L39: =SUM(I39:K39) -> 0 | M39: =COUNTIFS(MASTER[Sub Format],$B39,MASTER[Actual (Month) Bucket],M$3) -> 0 | N39: =COUNTIFS(MASTER[Sub Format],$B39,MASTER[Actual (Month) Bucket],N$3) -> 0 | O39: =COUNTIFS(MASTER[Sub Format],$B39,MASTER[Actual (Month) Bucket],O$3) -> 0 | P39: =SUM(M39:O39) -> 0 | Q39: =COUNTIFS(MASTER[Sub Format],$B39,MASTER[Actual (Month) Bucket],Q$3) -> 0 | R39: =COUNTIFS(MASTER[Sub Format],$B39,MASTER[Actual (Month) Bucket],R$3) -> 0 | S39: =COUNTIFS(MASTER[Sub Format],$B39,MASTER[Actual (Month) Bucket],S$3) -> 0 | T39: =SUM(Q39:S39) -> 0 | U39: =COUNTIFS(MASTER[Sub Format],$B39,MASTER[Actual (Month) Bucket],U$3) -> 0 | V39: =COUNTIFS(MASTER[Sub Format],$B39,MASTER[Actual (Month) Bucket],V$3) -> 0 | W39: =COUNTIFS(MASTER[Sub Format],$B39,MASTER[Actual (Month) Bucket],W$3) -> 0 | X39: =SUM(U39:W39) -> 0 | Y39: =L39+P39+T39+X39 -> 0 | Z39: =COUNTIFS(MASTER[LAUNCHED / YTL],"LAUNCHED",MASTER[Sub Format],$B39,MASTER[EPC Status (Current Week)],"EPC Ready") -> 0 | AA39: =COUNTIFS(MASTER[LAUNCHED / YTL],"YTL",MASTER[Sub Format],$B39,MASTER[EPC Status (Current Week)],"EPC Ready") -> 0 | AB39: =COUNTIFS(MASTER[LAUNCHED / YTL],"YTL - Dropped by Business",MASTER[Sub Format],$B39,MASTER[EPC Status (Current Week)],"EPC Ready") -> 0 | AC39: =COUNTIFS(MASTER[EPC Status (Current Week)],"EPC Ready",MASTER[Sub Format],$B39)+COUNTIFS(MASTER[EPC Status (Current Week)],"EPC Ready Previous FY",MASTER[Sub Format],$B39) -> 0 | AD39: =COUNTIFS(MASTER[LAUNCHED / YTL],"LAUNCHED",MASTER[Sub Format],$B39) -> 0 | AE39: =COUNTIFS(MASTER[LAUNCHED / YTL],"YTL",MASTER[Sub Format],$B39) -> 0 | AF39: =COUNTIFS(MASTER[LAUNCHED / YTL],"YTL - Dropped by Business",MASTER[Sub Format],$B39) -> 0 | AG39: =SUM(AQ39:BH39) -> 0 | AH39: =AQ39 -> 0 | AI39: =AR39 -> 0 | AJ39: =AS39 -> 0 | AK39: =AT39 -> 0 | AL39: =AU39 -> 0 | AM39: =AV39 -> 0 | AN39: =AW39 -> 0 | AO39: =AX39 -> 0 | AP39: =AY39 -> 0 | AQ39: =COUNTIFS(MASTER[Sub Format],$B39,MASTER[Planned (Month) Bucket],AQ$2,MASTER[EPC Status (Current Week)],"WIP") -> 0 | AR39: =COUNTIFS(MASTER[Sub Format],$B39,MASTER[Planned (Month) Bucket],AR$2,MASTER[EPC Status (Current Week)],"WIP") -> 0 | AS39: =COUNTIFS(MASTER[Sub Format],$B39,MASTER[Planned (Month) Bucket],AS$2,MASTER[EPC Status (Current Week)],"WIP") -> 0 | AT39: =COUNTIFS(MASTER[Sub Format],$B39,MASTER[Planned (Month) Bucket],AT$2,MASTER[EPC Status (Current Week)],"WIP") -> 0 | AU39: =COUNTIFS(MASTER[Sub Format],$B39,MASTER[Planned (Month) Bucket],AU$2,MASTER[EPC Status (Current Week)],"WIP") -> 0 | AV39: =COUNTIFS(MASTER[Sub Format],$B39,MASTER[Planned (Month) Bucket],AV$2,MASTER[EPC Status (Current Week)],"WIP") -> 0 | AW39: =COUNTIFS(MASTER[Sub Format],$B39,MASTER[Planned (Month) Bucket],AW$2,MASTER[EPC Status (Current Week)],"WIP") -> 0 | AX39: =COUNTIFS(MASTER[Sub Format],$B39,MASTER[Planned (Month) Bucket],AX$2,MASTER[EPC Status (Current Week)],"WIP") -> 0 | ... BH39: =COUNTIFS(MASTER[Sub Format],$B39,MASTER[Planned (Month) Bucket],BH$2,MASTER[EPC Status (Current Week)],"WIP") -> 0 | BI39: =COUNTIFS(MASTER[Sub Format],$B39,MASTER[EPC Status (Current Week)],BI$2) -> 0 | BJ39: =COUNTIFS(MASTER[Sub Format],$B39,MASTER[EPC Status (Current Week)],BJ$2) -> 0 | BK39: =COUNTIFS(MASTER[Sub Format],$B39,MASTER[EPC Status (Current Week)],BK$2) -> 0 | BL39: =COUNTIFS(MASTER[Sub Format],$B39,MASTER[EPC Status (Current Week)],BL$2) -> 0 | BM39: =SUM(BN39:BU39) -> 1 | BN39: =COUNTIFS(MASTER[Sub Format],$B39,MASTER[EPC Status (Current Week)],BN$3) -> 0 | BO39: =COUNTIFS(MASTER[Sub Format],$B39,MASTER[EPC Status (Current Week)],BO$3) -> 1 | BP39: =COUNTIFS(MASTER[Sub Format],$B39,MASTER[EPC Status (Current Week)],BP$3) -> 0 | BQ39: =COUNTIFS(MASTER[Sub Format],$B39,MASTER[EPC Status (Current Week)],BQ$3) -> 0 | BR39: =COUNTIFS(MASTER[Sub Format],$B39,MASTER[EPC Status (Current Week)],BR$3) -> 0 | BS39: =COUNTIFS(MASTER[Sub Format],$B39,MASTER[EPC Status (Current Week)],BS$3) -> 0 | BT39: =COUNTIFS(MASTER[Sub Format],$B39,MASTER[EPC Status (Current Week)],BT$3) -> 0 | BU39: =COUNTIFS(MASTER[Sub Format],$B39,MASTER[EPC Status (Current Week)],BU$3) -> 0
